Workbook

Sheet Loan Input Parameters
A1: VEHICLE LOAN INPUT PARAMETERS
A3: Client | B3: Sean Van Wyk
A4: Transaction number | B4: ZAETC123456789
A6: Vehicle Type (New/Demo/Used) | B6: New
A8: Final invoice price | B8: 500000
A9: Deposit value | B9: 0
A10: Principal debt (before initiation fees to be financed) | B10: =B8-B9 -> 500000
A12: Initiation fees to be financed | B12: 1207.5
A13: Principal debt (after initiation fees to be financed) | B13: =SUM(B10:B12) -> 501207.5
A15: Annual interest rate offered | B15: 0.11
A16: Term of the loan (in months) | B16: 72
A17: Repayments in advance or arrears | B17: Arrears
A18: Monthly instalment (without balloon repayment) | B18: =IF(B17="Advance",PMT(B15/12,B16,-$B$13,0,1),PMT(B15/12,B16,-$B$13,0,0)) -> 9540.0232
A20: Ballon payment value | B20: 170000
A21: Monthly instalment (with balloon payment) | B21: =PMT(B15/12,B16,-$B$13,B20,IF(B17="Advance",1,0)) -> 7862.5631 | C21: =B20/'Depreciation Parameters'!B3 -> 0.34
A23: Monthly service charge | B23: 69
A24: Total monthly repayment | B24: =B21+B23 -> 7931.5631
A26: Payment start date | B26: 45200
A28: Product | B28: TRAFICC TOP-UP (G305)
A29: Product Option | B29: TOP-UP
A30: Monthly Premium | B30: =VLOOKUP(B28&B29,template!$D:$F,2,FALSE)+(B8*VLOOKUP(B28&B29,template!$D:$F,3,FALSE)) -> 310
A32: Depreciation Model Standard or Override: | B32: Override
A33: Depreciation Model: | B33: Standard | C33: Override
A34: Year 1 depreciation % | B34: {=IF(B33="Overide",'Depreciation Parameters'!#REF!,IF('Loan Input Parameters'!B6="New",'Depreciation Parameters'!$B$4:$B$9,IF('Loan Input Parameters'!B6="Demo",'Depreciation Parameters'!$C$4:$C$9,IF('Loan Input Parameters'!B6="Used",'Depreciation Parameters'!$D$4:$D$9))))} -> 0.23 | C34: 0.22
A35: Year 2 depreciation % | B35: 0.15 | C35: 0.18
A36: Year 3 depreciation % | B36: 0.11 | C36: 0.15
A37: Year 4 depreciation % | B37: 0.11 | C37: 0.13
A38: Year 5 depreciation % | B38: 0.11 | C38: 0.09
A39: Year 6 depreciation % | B39: 0.1 | C39: 0.06
A41: Underlying Insurance Excess % | B41: 0
A42: Underlying Minimum Excess Rand Value | B42: 0
A45: All values include VAT

Sheet Loan Payment Schedule
A1: LOAN PAYMENT SCHEDULE
A3: Instalment number | B3: Date | C3: Opening balance | D3: Loan Instalment due | E3: Interest charged | F3: Administration fee | G3: Capital repayment | H3: Capital balance | I3: % of original Principle Debt
A4: 1 | B4: =EOMONTH('Loan Input Parameters'!B26,0) -> 45230 | C4: ='Loan Input Parameters'!B13 -> 501207.5 | D4: =IF(A4<'Loan Input Parameters'!$B$16,'Loan Input Parameters'!$B$24,IF(A4='Loan Input Parameters'!$B$16,'Loan Input Parameters'!$B$24+'Loan Input Parameters'!$B$20,0)) -> 7931.5631 | E4: =IF('Loan Input Parameters'!$B$17="Advance",0,C4*'Loan Input Parameters'!$B$15/12) -> 4594.4021 | F4: =IF(A4<='Loan Input Parameters'!$B$16,'Loan Input Parameters'!$B$23,0) -> 69 | G4: =D4-E4-F4 -> 3268.161 | H4: =C4-G4 -> 497939.34 | I4: =H4/'Loan Input Parameters'!$B$13 -> 0.99347943
A5: 2 | B5: =EOMONTH(B4,1) -> 45260 | C5: =IF(ROUND(H4,0)>0,H4,0) -> 497939.34 | D5: =IF(A5<'Loan Input Parameters'!$B$16,'Loan Input Parameters'!$B$24,IF(A5='Loan Input Parameters'!$B$16,'Loan Input Parameters'!$B$24+'Loan Input Parameters'!$B$20,0)) -> 7931.5631 | E5: =C5*'Loan Input Parameters'!$B$15/12 -> 4564.4439 | F5: =IF(A5<='Loan Input Parameters'!$B$16,'Loan Input Parameters'!$B$23,0) -> 69 | G5: =D5-E5-F5 -> 3298.1191 | H5: =C5-G5 -> 494641.22 | I5: =H5/'Loan Input Parameters'!$B$13 -> 0.98689908
A6: 3 | B6: =EOMONTH(B5,1) -> 45291 | C6: =IF(ROUND(H5,0)>0,H5,0) -> 494641.22 | D6: =IF(A6<'Loan Input Parameters'!$B$16,'Loan Input Parameters'!$B$24,IF(A6='Loan Input Parameters'!$B$16,'Loan Input Parameters'!$B$24+'Loan Input Parameters'!$B$20,0)) -> 7931.5631 | E6: =C6*'Loan Input Parameters'!$B$15/12 -> 4534.2112 | F6: =IF(A6<='Loan Input Parameters'!$B$16,'Loan Input Parameters'!$B$23,0) -> 69 | G6: =D6-E6-F6 -> 3328.3519 | H6: =C6-G6 -> 491312.87 | I6: =H6/'Loan Input Parameters'!$B$13 -> 0.98025841
A7: 4 | B7: =EOMONTH(B6,1) -> 45322 | C7: =IF(ROUND(H6,0)>0,H6,0) -> 491312.87 | D7: =IF(A7<'Loan Input Parameters'!$B$16,'Loan Input Parameters'!$B$24,IF(A7='Loan Input Parameters'!$B$16,'Loan Input Parameters'!$B$24+'Loan Input Parameters'!$B$20,0)) -> 7931.5631 | E7: =C7*'Loan Input Parameters'!$B$15/12 -> 4503.7013 | F7: =IF(A7<='Loan Input Parameters'!$B$16,'Loan Input Parameters'!$B$23,0) -> 69 | G7: =D7-E7-F7 -> 3358.8618 | H7: =C7-G7 -> 487954.01 | I7: =H7/'Loan Input Parameters'!$B$13 -> 0.97355687
A8: 5 | B8: =EOMONTH(B7,1) -> 45351 | C8: =IF(ROUND(H7,0)>0,H7,0) -> 487954.01 | D8: =IF(A8<'Loan Input Parameters'!$B$16,'Loan Input Parameters'!$B$24,IF(A8='Loan Input Parameters'!$B$16,'Loan Input Parameters'!$B$24+'Loan Input Parameters'!$B$20,0)) -> 7931.5631 | E8: =C8*'Loan Input Parameters'!$B$15/12 -> 4472.9117 | F8: =IF(A8<='Loan Input Parameters'!$B$16,'Loan Input Parameters'!$B$23,0) -> 69 | G8: =D8-E8-F8 -> 3389.6513 | H8: =C8-G8 -> 484564.35 | I8: =H8/'Loan Input Parameters'!$B$13 -> 0.9667939
A9: 6 | B9: =EOMONTH(B8,1) -> 45382 | C9: =IF(ROUND(H8,0)>0,H8,0) -> 484564.35 | D9: =IF(A9<'Loan Input Parameters'!$B$16,'Loan Input Parameters'!$B$24,IF(A9='Loan Input Parameters'!$B$16,'Loan Input Parameters'!$B$24+'Loan Input Parameters'!$B$20,0)) -> 7931.5631 | E9: =C9*'Loan Input Parameters'!$B$15/12 -> 4441.8399 | F9: =IF(A9<='Loan Input Parameters'!$B$16,'Loan Input Parameters'!$B$23,0) -> 69 | G9: =D9-E9-F9 -> 3420.7231 | H9: =C9-G9 -> 481143.63 | I9: =H9/'Loan Input Parameters'!$B$13 -> 0.95996894
A10: 7 | B10: =EOMONTH(B9,1) -> 45412 | C10: =IF(ROUND(H9,0)>0,H9,0) -> 481143.63 | D10: =IF(A10<'Loan Input Parameters'!$B$16,'Loan Input Parameters'!$B$24,IF(A10='Loan Input Parameters'!$B$16,'Loan Input Parameters'!$B$24+'Loan Input Parameters'!$B$20,0)) -> 7931.5631 | E10: =C10*'Loan Input Parameters'!$B$15/12 -> 4410.4833 | F10: =IF(A10<='Loan Input Parameters'!$B$16,'Loan Input Parameters'!$B$23,0) -> 69 | G10: =D10-E10-F10 -> 3452.0798 | H10: =C10-G10 -> 477691.55 | I10: =H10/'Loan Input Parameters'!$B$13 -> 0.95308141
A11: 8 | B11: =EOMONTH(B10,1) -> 45443 | C11: =IF(ROUND(H10,0)>0,H10,0) -> 477691.55 | D11: =IF(A11<'Loan Input Parameters'!$B$16,'Loan Input Parameters'!$B$24,IF(A11='Loan Input Parameters'!$B$16,'Loan Input Parameters'!$B$24+'Loan Input Parameters'!$B$20,0)) -> 7931.5631 | E11: =C11*'Loan Input Parameters'!$B$15/12 -> 4378.8392 | F11: =IF(A11<='Loan Input Parameters'!$B$16,'Loan Input Parameters'!$B$23,0) -> 69 | G11: =D11-E11-F11 -> 3483.7238 | H11: =C11-G11 -> 474207.83 | I11: =H11/'Loan Input Parameters'!$B$13 -> 0.94613075
A12: 9 | B12: =EOMONTH(B11,1) -> 45473 | C12: =IF(ROUND(H11,0)>0,H11,0) -> 474207.83 | D12: =IF(A12<'Loan Input Parameters'!$B$16,'Loan Input Parameters'!$B$24,IF(A12='Loan Input Parameters'!$B$16,'Loan Input Parameters'!$B$24+'Loan Input Parameters'!$B$20,0)) -> 7931.5631 | E12: =C12*'Loan Input Parameters'!$B$15/12 -> 4346.9051 | F12: =IF(A12<='Loan Input Parameters'!$B$16,'Loan Input Parameters'!$B$23,0) -> 69 | G12: =D12-E12-F12 -> 3515.658 | H12: =C12-G12 -> 470692.17 | I12: =H12/'Loan Input Parameters'!$B$13 -> 0.93911637
A13: 10 | B13: =EOMONTH(B12,1) -> 45504 | C13: =IF(ROUND(H12,0)>0,H12,0) -> 470692.17 | D13: =IF(A13<'Loan Input Parameters'!$B$16,'Loan Input Parameters'!$B$24,IF(A13='Loan Input Parameters'!$B$16,'Loan Input Parameters'!$B$24+'Loan Input Parameters'!$B$20,0)) -> 7931.5631 | E13: =C13*'Loan Input Parameters'!$B$15/12 -> 4314.6782 | F13: =IF(A13<='Loan Input Parameters'!$B$16,'Loan Input Parameters'!$B$23,0) -> 69 | G13: =D13-E13-F13 -> 3547.8848 | H13: =C13-G13 -> 467144.29 | I13: =H13/'Loan Input Parameters'!$B$13 -> 0.9320377
A14: 11 | B14: =EOMONTH(B13,1) -> 45535 | C14: =IF(ROUND(H13,0)>0,H13,0) -> 467144.29 | D14: =IF(A14<'Loan Input Parameters'!$B$16,'Loan Input Parameters'!$B$24,IF(A14='Loan Input Parameters'!$B$16,'Loan Input Parameters'!$B$24+'Loan Input Parameters'!$B$20,0)) -> 7931.5631 | E14: =C14*'Loan Input Parameters'!$B$15/12 -> 4282.1559 | F14: =IF(A14<='Loan Input Parameters'!$B$16,'Loan Input Parameters'!$B$23,0) -> 69 | G14: =D14-E14-F14 -> 3580.4071 | H14: =C14-G14 -> 463563.88 | I14: =H14/'Loan Input Parameters'!$B$13 -> 0.92489414
A15: 12 | B15: =EOMONTH(B14,1) -> 45565 | C15: =IF(ROUND(H14,0)>0,H14,0) -> 463563.88 | D15: =IF(A15<'Loan Input Parameters'!$B$16,'Loan Input Parameters'!$B$24,IF(A15='Loan Input Parameters'!$B$16,'Loan Input Parameters'!$B$24+'Loan Input Parameters'!$B$20,0)) -> 7931.5631 | E15: =C15*'Loan Input Parameters'!$B$15/12 -> 4249.3356 | F15: =IF(A15<='Loan Input Parameters'!$B$16,'Loan Input Parameters'!$B$23,0) -> 69 | G15: =D15-E15-F15 -> 3613.2275 | H15: =C15-G15 -> 459950.65 | I15: =H15/'Loan Input Parameters'!$B$13 -> 0.91768509
A16: 13 | B16: =EOMONTH(B15,1) -> 45596 | C16: =IF(ROUND(H15,0)>0,H15,0) -> 459950.65 | D16: =IF(A16<'Loan Input Parameters'!$B$16,'Loan Input Parameters'!$B$24,IF(A16='Loan Input Parameters'!$B$16,'Loan Input Parameters'!$B$24+'Loan Input Parameters'!$B$20,0)) -> 7931.5631 | E16: =C16*'Loan Input Parameters'!$B$15/12 -> 4216.2143 | F16: =IF(A16<='Loan Input Parameters'!$B$16,'Loan Input Parameters'!$B$23,0) -> 69 | G16: =D16-E16-F16 -> 3646.3488 | H16: =C16-G16 -> 456304.3 | I16: =H16/'Loan Input Parameters'!$B$13 -> 0.91040996
... A99: 96 | B99: =EOMONTH(B98,1) -> 48121 | C99: =IF(ROUND(H98,0)>0,H98,0) -> 0 | D99: =IF(A99<'Loan Input Parameters'!$B$16,'Loan Input Parameters'!$B$24,IF(A99='Loan Input Parameters'!$B$16,'Loan Input Parameters'!$B$24+'Loan Input Parameters'!$B$20,0)) -> 0 | E99: =C99*'Loan Input Parameters'!$B$15/12 -> 0 | F99: =IF(A99<='Loan Input Parameters'!$B$16,'Loan Input Parameters'!$B$23,0) -> 0 | G99: =D99-E99-F99 -> 0 | H99: =C99-G99 -> 0 | I99: =H99/'Loan Input Parameters'!$B$13 -> 0

Sheet Loan Payment Summary
A1: LOAN PAYMENT SUMMARY
A3: FULL HISTORY
A5: Total capital paid | B5: =SUM('Loan Payment Schedule'!G4:G75) -> 501207.5
A6: Total interest paid | B6: =SUM('Loan Payment Schedule'!E4:E75) -> 234897.04
A7: Total loan repayments | B7: =SUM('Loan Payment Schedule'!D4:D75) -> 741072.54
A9: PERIODIC REVIEW
A11: Review month | B11: 36
A13: Total capital paid | B13: =SUMIF('Loan Payment Schedule'!$A$4:$A$75,"<="&$B$11,'Loan Payment Schedule'!$G$4:$G$75) -> 138645.6
A14: Total interest paid | B14: =SUMIF('Loan Payment Schedule'!$A$4:$A$75,"<="&$B$11,'Loan Payment Schedule'!$E$4:$E$75) -> 144406.67
A15: Total loan repayments | B15: =SUMIF('Loan Payment Schedule'!$A$4:$A$75,"<="&$B$11,'Loan Payment Schedule'!$D$4:$D$75) -> 285536.27
A17: Total capital outstanding | B17: =VLOOKUP(B11,'Loan Payment Schedule'!$A$4:$H$75,8,0) -> 362561.9

Sheet Shortfall Illustration
A1: ILLUSTRATION OF POTENTIAL SHORTFALL
A3: Instalment number | B3: Date | C3: Opening balance | D3: Loan Instalment due | E3: Interest charged | F3: Administration fee | G3: Capital repayment | H3: Capital balance | I3: % of original Principle Debt | J3: % depreciation | K3: Market Value | L3: Insurance Excess (Based on Market Value) | M3: Market Value less Excess | N3: Illustration of Shortfall Benefit | O3: Potential Loyalty Bonus | P3: Shortfall Benefit Plus Loyalty Bonus
A4: =IFERROR(IF(1<='Loan Input Parameters'!$B$16,1,"-"),0) -> 1 | B4: =EOMONTH('Loan Input Parameters'!B26,0) -> 45230 | C4: ='Loan Input Parameters'!B13 -> 501207.5 | D4: =IF(A4<'Loan Input Parameters'!$B$16,'Loan Input Parameters'!$B$24,IF(A4='Loan Input Parameters'!$B$16,'Loan Input Parameters'!$B$24+'Loan Input Parameters'!$B$20,0)) -> 7931.5631 | E4: =IF('Loan Input Parameters'!$B$17="Advance",0,C4*'Loan Input Parameters'!$B$15/12) -> 4594.4021 | F4: =IF(A4<='Loan Input Parameters'!$B$16,'Loan Input Parameters'!$B$23,0) -> 69 | G4: =IF($A4<'Loan Input Parameters'!$B$16,D4-E4-F4,"0.00") -> 3268.161 | H4: =C4-G4 -> 497939.34 | I4: =H4/'Loan Input Parameters'!$B$13 -> 0.99347943 | J4: =IF('Loan Input Parameters'!$B$32="Overide",'Loan Input Parameters'!$C$34,'Loan Input Parameters'!$B$34) -> 0.23 | K4: =_xlfn.LET(_xlpm.DEPRECIATION,IF('Loan Input Parameters'!$B$6="Used",0.08,0.05), IF( MONTH($B4)=1, 'Depreciation Parameters'!$B$3*(1-(35%*J4)+_xlpm.DEPRECIATION),'Depreciation Parameters'!$B$3*(1-_xlpm.DEPRECIATION))) -> 475000 | L4: =IF(K4*'Loan Input Parameters'!$B$41<'Loan Input Parameters'!$B$42,'Loan Input Parameters'!$B$42,K4*'Loan Input Parameters'!$B$41) -> 0 | M4: =K4-L4 -> 475000 | N4: =H4-(K4-L4) -> 22939.339 | O4: =IF('Loan Input Parameters'!$B$8*3%<=4000,4000,IF('Loan Input Parameters'!$B$8*3%>=18000,18000,'Loan Input Parameters'!$B$8*3%)) -> 15000 | P4: =IF(N4<0,O4,N4+O4) -> 37939.339
A5: =A4+1 -> 2 | B5: =EOMONTH(B4,1) -> 45260 | C5: =IF(ROUND(H4,0)>0,H4,0) -> 497939.34 | D5: =IF(A5<'Loan Input Parameters'!$B$16,'Loan Input Parameters'!$B$24,IF(A5='Loan Input Parameters'!$B$16,'Loan Input Parameters'!$B$24+'Loan Input Parameters'!$B$20,0)) -> 7931.5631 | E5: =IF($A5<'Loan Input Parameters'!$B$16,C5*'Loan Input Parameters'!$B$15/12,"0.00") -> 4564.4439 | F5: =IF(A5<='Loan Input Parameters'!$B$16,'Loan Input Parameters'!$B$23,0) -> 69 | G5: =IF($A5<'Loan Input Parameters'!$B$16,D5-E5-F5,"0.00") -> 3298.1191 | H5: =IF($A5<'Loan Input Parameters'!$B$16,C5-G5,"0.00") -> 494641.22 | I5: =H5/'Loan Input Parameters'!$B$13 -> 0.98689908 | J5: =J4 -> 0.23 | K5: {=IF( AND(MONTH($B5)=1,SUMPRODUCT(--(MONTH($B$4:B5)=1))=1), K4*(1-22%*J5), IF( AND(MONTH($B5)=1,SUMPRODUCT(--(MONTH($B$4:B5)=1))=2), K4*(1-20%*J5), IF($A5<13,K4*(1-(J5*4%)), IF($A5<25,K4*(1-(J5*5%)),K4*(1-J5/12) ) ) ))} -> 470630 | L5: =IF(K5*'Loan Input Parameters'!$B$41<'Loan Input Parameters'!$B$42,'Loan Input Parameters'!$B$42,K5*'Loan Input Parameters'!$B$41) -> 0 | M5: =K5-L5 -> 470630 | N5: =H5-(K5-L5) -> 24011.22 | O5: =IF('Loan Input Parameters'!$B$8*3%<=4000,4000,IF('Loan Input Parameters'!$B$8*3%>=18000,18000,'Loan Input Parameters'!$B$8*3%)) -> 15000 | P5: =IF(N5<0,O5,N5+O5) -> 39011.22
A6: =A5+1 -> 3 | B6: =EOMONTH(B5,1) -> 45291 | C6: =IF(ROUND(H5,0)>0,H5,0) -> 494641.22 | D6: =IF(A6<'Loan Input Parameters'!$B$16,'Loan Input Parameters'!$B$24,IF(A6='Loan Input Parameters'!$B$16,'Loan Input Parameters'!$B$24+'Loan Input Parameters'!$B$20,0)) -> 7931.5631 | E6: =IF($A6<'Loan Input Parameters'!$B$16,C6*'Loan Input Parameters'!$B$15/12,"0.00") -> 4534.2112 | F6: =IF(A6<='Loan Input Parameters'!$B$16,'Loan Input Parameters'!$B$23,0) -> 69 | G6: =IF($A6<'Loan Input Parameters'!$B$16,D6-E6-F6,"0.00") -> 3328.3519 | H6: =IF($A6<'Loan Input Parameters'!$B$16,C6-G6,"0.00") -> 491312.87 | I6: =H6/'Loan Input Parameters'!$B$13 -> 0.98025841 | J6: =J5 -> 0.23 | K6: {=IF( AND(MONTH($B6)=1,SUMPRODUCT(--(MONTH($B$4:B6)=1))=1), K5*(1-22%*J6), IF( AND(MONTH($B6)=1,SUMPRODUCT(--(MONTH($B$4:B6)=1))=2), K5*(1-20%*J6), IF($A6<13,K5*(1-(J6*4%)), IF($A6<25,K5*(1-(J6*5%)),K5*(1-J6/12) ) ) ))} -> 466300.2 | L6: =IF(K6*'Loan Input Parameters'!$B$41<'Loan Input Parameters'!$B$42,'Loan Input Parameters'!$B$42,K6*'Loan Input Parameters'!$B$41) -> 0 | M6: =K6-L6 -> 466300.2 | N6: =H6-(K6-L6) -> 25012.664 | O6: =IF('Loan Input Parameters'!$B$8*3%<=4000,4000,IF('Loan Input Parameters'!$B$8*3%>=18000,18000,'Loan Input Parameters'!$B$8*3%)) -> 15000 | P6: =IF(N6<0,O6,N6+O6) -> 40012.664
A7: =A6+1 -> 4 | B7: =EOMONTH(B6,1) -> 45322 | C7: =IF(ROUND(H6,0)>0,H6,0) -> 491312.87 | D7: =IF(A7<'Loan Input Parameters'!$B$16,'Loan Input Parameters'!$B$24,IF(A7='Loan Input Parameters'!$B$16,'Loan Input Parameters'!$B$24+'Loan Input Parameters'!$B$20,0)) -> 7931.5631 | E7: =IF($A7<'Loan Input Parameters'!$B$16,C7*'Loan Input Parameters'!$B$15/12,"0.00") -> 4503.7013 | F7: =IF(A7<='Loan Input Parameters'!$B$16,'Loan Input Parameters'!$B$23,0) -> 69 | G7: =IF($A7<'Loan Input Parameters'!$B$16,D7-E7-F7,"0.00") -> 3358.8618 | H7: =IF($A7<'Loan Input Parameters'!$B$16,C7-G7,"0.00") -> 487954.01 | I7: =H7/'Loan Input Parameters'!$B$13 -> 0.97355687 | J7: =J6 -> 0.23 | K7: {=IF( AND(MONTH($B7)=1,SUMPRODUCT(--(MONTH($B$4:B7)=1))=1), K6*(1-22%*J7), IF( AND(MONTH($B7)=1,SUMPRODUCT(--(MONTH($B$4:B7)=1))=2), K6*(1-20%*J7), IF($A7<13,K6*(1-(J7*4%)), IF($A7<25,K6*(1-(J7*5%)),K6*(1-J7/12) ) ) ))} -> 442705.41 | L7: =IF(K7*'Loan Input Parameters'!$B$41<'Loan Input Parameters'!$B$42,'Loan Input Parameters'!$B$42,K7*'Loan Input Parameters'!$B$41) -> 0 | M7: =K7-L7 -> 442705.41 | N7: =H7-(K7-L7) -> 45248.593 | O7: =IF('Loan Input Parameters'!$B$8*3%<=4000,4000,IF('Loan Input Parameters'!$B$8*3%>=18000,18000,'Loan Input Parameters'!$B$8*3%)) -> 15000 | P7: =IF(N7<0,O7,N7+O7) -> 60248.593
A8: =A7+1 -> 5 | B8: =EOMONTH(B7,1) -> 45351 | C8: =IF(ROUND(H7,0)>0,H7,0) -> 487954.01 | D8: =IF(A8<'Loan Input Parameters'!$B$16,'Loan Input Parameters'!$B$24,IF(A8='Loan Input Parameters'!$B$16,'Loan Input Parameters'!$B$24+'Loan Input Parameters'!$B$20,0)) -> 7931.5631 | E8: =IF($A8<'Loan Input Parameters'!$B$16,C8*'Loan Input Parameters'!$B$15/12,"0.00") -> 4472.9117 | F8: =IF(A8<='Loan Input Parameters'!$B$16,'Loan Input Parameters'!$B$23,0) -> 69 | G8: =IF($A8<'Loan Input Parameters'!$B$16,D8-E8-F8,"0.00") -> 3389.6513 | H8: =IF($A8<'Loan Input Parameters'!$B$16,C8-G8,"0.00") -> 484564.35 | I8: =H8/'Loan Input Parameters'!$B$13 -> 0.9667939 | J8: =J7 -> 0.23 | K8: {=IF( AND(MONTH($B8)=1,SUMPRODUCT(--(MONTH($B$4:B8)=1))=1), K7*(1-22%*J8), IF( AND(MONTH($B8)=1,SUMPRODUCT(--(MONTH($B$4:B8)=1))=2), K7*(1-20%*J8), IF($A8<13,K7*(1-(J8*4%)), IF($A8<25,K7*(1-(J8*5%)),K7*(1-J8/12) ) ) ))} -> 438632.52 | L8: =IF(K8*'Loan Input Parameters'!$B$41<'Loan Input Parameters'!$B$42,'Loan Input Parameters'!$B$42,K8*'Loan Input Parameters'!$B$41) -> 0 | M8: =K8-L8 -> 438632.52 | N8: =H8-(K8-L8) -> 45931.831 | O8: =IF('Loan Input Parameters'!$B$8*3%<=4000,4000,IF('Loan Input Parameters'!$B$8*3%>=18000,18000,'Loan Input Parameters'!$B$8*3%)) -> 15000 | P8: =IF(N8<0,O8,N8+O8) -> 60931.831
A9: =A8+1 -> 6 | B9: =EOMONTH(B8,1) -> 45382 | C9: =IF(ROUND(H8,0)>0,H8,0) -> 484564.35 | D9: =IF(A9<'Loan Input Parameters'!$B$16,'Loan Input Parameters'!$B$24,IF(A9='Loan Input Parameters'!$B$16,'Loan Input Parameters'!$B$24+'Loan Input Parameters'!$B$20,0)) -> 7931.5631 | E9: =IF($A9<'Loan Input Parameters'!$B$16,C9*'Loan Input Parameters'!$B$15/12,"0.00") -> 4441.8399 | F9: =IF(A9<='Loan Input Parameters'!$B$16,'Loan Input Parameters'!$B$23,0) -> 69 | G9: =IF($A9<'Loan Input Parameters'!$B$16,D9-E9-F9,"0.00") -> 3420.7231 | H9: =IF($A9<'Loan Input Parameters'!$B$16,C9-G9,"0.00") -> 481143.63 | I9: =H9/'Loan Input Parameters'!$B$13 -> 0.95996894 | J9: =J8 -> 0.23 | K9: {=IF( AND(MONTH($B9)=1,SUMPRODUCT(--(MONTH($B$4:B9)=1))=1), K8*(1-22%*J9), IF( AND(MONTH($B9)=1,SUMPRODUCT(--(MONTH($B$4:B9)=1))=2), K8*(1-20%*J9), IF($A9<13,K8*(1-(J9*4%)), IF($A9<25,K8*(1-(J9*5%)),K8*(1-J9/12) ) ) ))} -> 434597.1 | L9: =IF(K9*'Loan Input Parameters'!$B$41<'Loan Input Parameters'!$B$42,'Loan Input Parameters'!$B$42,K9*'Loan Input Parameters'!$B$41) -> 0 | M9: =K9-L9 -> 434597.1 | N9: =H9-(K9-L9) -> 46546.527 | O9: =IF('Loan Input Parameters'!$B$8*3%<=4000,4000,IF('Loan Input Parameters'!$B$8*3%>=18000,18000,'Loan Input Parameters'!$B$8*3%)) -> 15000 | P9: =IF(N9<0,O9,N9+O9) -> 61546.527
A10: =A9+1 -> 7 | B10: =EOMONTH(B9,1) -> 45412 | C10: =IF(ROUND(H9,0)>0,H9,0) -> 481143.63 | D10: =IF(A10<'Loan Input Parameters'!$B$16,'Loan Input Parameters'!$B$24,IF(A10='Loan Input Parameters'!$B$16,'Loan Input Parameters'!$B$24+'Loan Input Parameters'!$B$20,0)) -> 7931.5631 | E10: =IF($A10<'Loan Input Parameters'!$B$16,C10*'Loan Input Parameters'!$B$15/12,"0.00") -> 4410.4833 | F10: =IF(A10<='Loan Input Parameters'!$B$16,'Loan Input Parameters'!$B$23,0) -> 69 | G10: =IF($A10<'Loan Input Parameters'!$B$16,D10-E10-F10,"0.00") -> 3452.0798 | H10: =IF($A10<'Loan Input Parameters'!$B$16,C10-G10,"0.00") -> 477691.55 | I10: =H10/'Loan Input Parameters'!$B$13 -> 0.95308141 | J10: =J9 -> 0.23 | K10: {=IF( AND(MONTH($B10)=1,SUMPRODUCT(--(MONTH($B$4:B10)=1))=1), K9*(1-22%*J10), IF( AND(MONTH($B10)=1,SUMPRODUCT(--(MONTH($B$4:B10)=1))=2), K9*(1-20%*J10), IF($A10<13,K9*(1-(J10*4%)), IF($A10<25,K9*(1-(J10*5%)),K9*(1-J10/12) ) ) ))} -> 430598.81 | L10: =IF(K10*'Loan Input Parameters'!$B$41<'Loan Input Parameters'!$B$42,'Loan Input Parameters'!$B$42,K10*'Loan Input Parameters'!$B$41) -> 0 | M10: =K10-L10 -> 430598.81 | N10: =H10-(K10-L10) -> 47092.741 | O10: =IF('Loan Input Parameters'!$B$8*3%<=4000,4000,IF('Loan Input Parameters'!$B$8*3%>=18000,18000,'Loan Input Parameters'!$B$8*3%)) -> 15000 | P10: =IF(N10<0,O10,N10+O10) -> 62092.741
A11: =A10+1 -> 8 | B11: =EOMONTH(B10,1) -> 45443 | C11: =IF(ROUND(H10,0)>0,H10,0) -> 477691.55 | D11: =IF(A11<'Loan Input Parameters'!$B$16,'Loan Input Parameters'!$B$24,IF(A11='Loan Input Parameters'!$B$16,'Loan Input Parameters'!$B$24+'Loan Input Parameters'!$B$20,0)) -> 7931.5631 | E11: =IF($A11<'Loan Input Parameters'!$B$16,C11*'Loan Input Parameters'!$B$15/12,"0.00") -> 4378.8392 | F11: =IF(A11<='Loan Input Parameters'!$B$16,'Loan Input Parameters'!$B$23,0) -> 69 | G11: =IF($A11<'Loan Input Parameters'!$B$16,D11-E11-F11,"0.00") -> 3483.7238 | H11: =IF($A11<'Loan Input Parameters'!$B$16,C11-G11,"0.00") -> 474207.83 | I11: =H11/'Loan Input Parameters'!$B$13 -> 0.94613075 | J11: =J10 -> 0.23 | K11: {=IF( AND(MONTH($B11)=1,SUMPRODUCT(--(MONTH($B$4:B11)=1))=1), K10*(1-22%*J11), IF( AND(MONTH($B11)=1,SUMPRODUCT(--(MONTH($B$4:B11)=1))=2), K10*(1-20%*J11), IF($A11<13,K10*(1-(J11*4%)), IF($A11<25,K10*(1-(J11*5%)),K10*(1-J11/12) ) ) ))} -> 426637.3 | L11: =IF(K11*'Loan Input Parameters'!$B$41<'Loan Input Parameters'!$B$42,'Loan Input Parameters'!$B$42,K11*'Loan Input Parameters'!$B$41) -> 0 | M11: =K11-L11 -> 426637.3 | N11: =H11-(K11-L11) -> 47570.526 | O11: =IF('Loan Input Parameters'!$B$8*3%<=4000,4000,IF('Loan Input Parameters'!$B$8*3%>=18000,18000,'Loan Input Parameters'!$B$8*3%)) -> 15000 | P11: =IF(N11<0,O11,N11+O11) -> 62570.526
A12: =A11+1 -> 9 | B12: =EOMONTH(B11,1) -> 45473 | C12: =IF(ROUND(H11,0)>0,H11,0) -> 474207.83 | D12: =IF(A12<'Loan Input Parameters'!$B$16,'Loan Input Parameters'!$B$24,IF(A12='Loan Input Parameters'!$B$16,'Loan Input Parameters'!$B$24+'Loan Input Parameters'!$B$20,0)) -> 7931.5631 | E12: =IF($A12<'Loan Input Parameters'!$B$16,C12*'Loan Input Parameters'!$B$15/12,"0.00") -> 4346.9051 | F12: =IF(A12<='Loan Input Parameters'!$B$16,'Loan Input Parameters'!$B$23,0) -> 69 | G12: =IF($A12<'Loan Input Parameters'!$B$16,D12-E12-F12,"0.00") -> 3515.658 | H12: =IF($A12<'Loan Input Parameters'!$B$16,C12-G12,"0.00") -> 470692.17 | I12: =H12/'Loan Input Parameters'!$B$13 -> 0.93911637 | J12: =J11 -> 0.23 | K12: {=IF( AND(MONTH($B12)=1,SUMPRODUCT(--(MONTH($B$4:B12)=1))=1), K11*(1-22%*J12), IF( AND(MONTH($B12)=1,SUMPRODUCT(--(MONTH($B$4:B12)=1))=2), K11*(1-20%*J12), IF($A12<13,K11*(1-(J12*4%)), IF($A12<25,K11*(1-(J12*5%)),K11*(1-J12/12) ) ) ))} -> 422712.24 | L12: =IF(K12*'Loan Input Parameters'!$B$41<'Loan Input Parameters'!$B$42,'Loan Input Parameters'!$B$42,K12*'Loan Input Parameters'!$B$41) -> 0 | M12: =K12-L12 -> 422712.24 | N12: =H12-(K12-L12) -> 47979.931 | O12: =IF('Loan Input Parameters'!$B$8*3%<=4000,4000,IF('Loan Input Parameters'!$B$8*3%>=18000,18000,'Loan Input Parameters'!$B$8*3%)) -> 15000 | P12: =IF(N12<0,O12,N12+O12) -> 62979.931
A13: =A12+1 -> 10 | B13: =EOMONTH(B12,1) -> 45504 | C13: =IF(ROUND(H12,0)>0,H12,0) -> 470692.17 | D13: =IF(A13<'Loan Input Parameters'!$B$16,'Loan Input Parameters'!$B$24,IF(A13='Loan Input Parameters'!$B$16,'Loan Input Parameters'!$B$24+'Loan Input Parameters'!$B$20,0)) -> 7931.5631 | E13: =IF($A13<'Loan Input Parameters'!$B$16,C13*'Loan Input Parameters'!$B$15/12,"0.00") -> 4314.6782 | F13: =IF(A13<='Loan Input Parameters'!$B$16,'Loan Input Parameters'!$B$23,0) -> 69 | G13: =IF($A13<'Loan Input Parameters'!$B$16,D13-E13-F13,"0.00") -> 3547.8848 | H13: =IF($A13<'Loan Input Parameters'!$B$16,C13-G13,"0.00") -> 467144.29 | I13: =H13/'Loan Input Parameters'!$B$13 -> 0.9320377 | J13: =J12 -> 0.23 | K13: {=IF( AND(MONTH($B13)=1,SUMPRODUCT(--(MONTH($B$4:B13)=1))=1), K12*(1-22%*J13), IF( AND(MONTH($B13)=1,SUMPRODUCT(--(MONTH($B$4:B13)=1))=2), K12*(1-20%*J13), IF($A13<13,K12*(1-(J13*4%)), IF($A13<25,K12*(1-(J13*5%)),K12*(1-J13/12) ) ) ))} -> 418823.29 | L13: =IF(K13*'Loan Input Parameters'!$B$41<'Loan Input Parameters'!$B$42,'Loan Input Parameters'!$B$42,K13*'Loan Input Parameters'!$B$41) -> 0 | M13: =K13-L13 -> 418823.29 | N13: =H13-(K13-L13) -> 48320.999 | O13: =IF('Loan Input Parameters'!$B$8*3%<=4000,4000,IF('Loan Input Parameters'!$B$8*3%>=18000,18000,'Loan Input Parameters'!$B$8*3%)) -> 15000 | P13: =IF(N13<0,O13,N13+O13) -> 63320.999
A14: =A13+1 -> 11 | B14: =EOMONTH(B13,1) -> 45535 | C14: =IF(ROUND(H13,0)>0,H13,0) -> 467144.29 | D14: =IF(A14<'Loan Input Parameters'!$B$16,'Loan Input Parameters'!$B$24,IF(A14='Loan Input Parameters'!$B$16,'Loan Input Parameters'!$B$24+'Loan Input Parameters'!$B$20,0)) -> 7931.5631 | E14: =IF($A14<'Loan Input Parameters'!$B$16,C14*'Loan Input Parameters'!$B$15/12,"0.00") -> 4282.1559 | F14: =IF(A14<='Loan Input Parameters'!$B$16,'Loan Input Parameters'!$B$23,0) -> 69 | G14: =IF($A14<'Loan Input Parameters'!$B$16,D14-E14-F14,"0.00") -> 3580.4071 | H14: =IF($A14<'Loan Input Parameters'!$B$16,C14-G14,"0.00") -> 463563.88 | I14: =H14/'Loan Input Parameters'!$B$13 -> 0.92489414 | J14: =J13 -> 0.23 | K14: {=IF( AND(MONTH($B14)=1,SUMPRODUCT(--(MONTH($B$4:B14)=1))=1), K13*(1-22%*J14), IF( AND(MONTH($B14)=1,SUMPRODUCT(--(MONTH($B$4:B14)=1))=2), K13*(1-20%*J14), IF($A14<13,K13*(1-(J14*4%)), IF($A14<25,K13*(1-(J14*5%)),K13*(1-J14/12) ) ) ))} -> 414970.11 | L14: =IF(K14*'Loan Input Parameters'!$B$41<'Loan Input Parameters'!$B$42,'Loan Input Parameters'!$B$42,K14*'Loan Input Parameters'!$B$41) -> 0 | M14: =K14-L14 -> 414970.11 | N14: =H14-(K14-L14) -> 48593.766 | O14: =IF('Loan Input Parameters'!$B$8*3%<=4000,4000,IF('Loan Input Parameters'!$B$8*3%>=18000,18000,'Loan Input Parameters'!$B$8*3%)) -> 15000 | P14: =IF(N14<0,O14,N14+O14) -> 63593.766
A15: =A14+1 -> 12 | B15: =EOMONTH(B14,1) -> 45565 | C15: =IF(ROUND(H14,0)>0,H14,0) -> 463563.88 | D15: =IF(A15<'Loan Input Parameters'!$B$16,'Loan Input Parameters'!$B$24,IF(A15='Loan Input Parameters'!$B$16,'Loan Input Parameters'!$B$24+'Loan Input Parameters'!$B$20,0)) -> 7931.5631 | E15: =IF($A15<'Loan Input Parameters'!$B$16,C15*'Loan Input Parameters'!$B$15/12,"0.00") -> 4249.3356 | F15: =IF(A15<='Loan Input Parameters'!$B$16,'Loan Input Parameters'!$B$23,0) -> 69 | G15: =IF($A15<'Loan Input Parameters'!$B$16,D15-E15-F15,"0.00") -> 3613.2275 | H15: =IF($A15<'Loan Input Parameters'!$B$16,C15-G15,"0.00") -> 459950.65 | I15: =H15/'Loan Input Parameters'!$B$13 -> 0.91768509 | J15: =J14 -> 0.23 | K15: {=IF( AND(MONTH($B15)=1,SUMPRODUCT(--(MONTH($B$4:B15)=1))=1), K14*(1-22%*J15), IF( AND(MONTH($B15)=1,SUMPRODUCT(--(MONTH($B$4:B15)=1))=2), K14*(1-20%*J15), IF($A15<13,K14*(1-(J15*4%)), IF($A15<25,K14*(1-(J15*5%)),K14*(1-J15/12) ) ) ))} -> 411152.39 | L15: =IF(K15*'Loan Input Parameters'!$B$41<'Loan Input Parameters'!$B$42,'Loan Input Parameters'!$B$42,K15*'Loan Input Parameters'!$B$41) -> 0 | M15: =K15-L15 -> 411152.39 | N15: =H15-(K15-L15) -> 48798.264 | O15: =IF('Loan Input Parameters'!$B$8*3%<=4000,4000,IF('Loan Input Parameters'!$B$8*3%>=18000,18000,'Loan Input Parameters'!$B$8*3%)) -> 15000 | P15: =IF(N15<0,O15,N15+O15) -> 63798.264
A16: =A15+1 -> 13 | B16: =EOMONTH(B15,1) -> 45596 | C16: =IF(ROUND(H15,0)>0,H15,0) -> 459950.65 | D16: =IF(A16<'Loan Input Parameters'!$B$16,'Loan Input Parameters'!$B$24,IF(A16='Loan Input Parameters'!$B$16,'Loan Input Parameters'!$B$24+'Loan Input Parameters'!$B$20,0)) -> 7931.5631 | E16: =IF($A16<'Loan Input Parameters'!$B$16,C16*'Loan Input Parameters'!$B$15/12,"0.00") -> 4216.2143 | F16: =IF(A16<='Loan Input Parameters'!$B$16,'Loan Input Parameters'!$B$23,0) -> 69 | G16: =IF($A16<'Loan Input Parameters'!$B$16,D16-E16-F16,"0.00") -> 3646.3488 | H16: =IF($A16<'Loan Input Parameters'!$B$16,C16-G16,"0.00") -> 456304.3 | I16: =H16/'Loan Input Parameters'!$B$13 -> 0.91040996 | J16: =IF('Loan Input Parameters'!$B$32="Overide",'Loan Input Parameters'!$C$35,'Loan Input Parameters'!$B$35) -> 0.15 | K16: =_xlfn.LET(_xlpm.DEPRECIATION,IF('Loan Input Parameters'!$B$6="Used",0.08,0.05), IF( MONTH($B16)=1, K15*(1-(35%*J16)+_xlpm.DEPRECIATION),K15*(1-_xlpm.DEPRECIATION))) -> 390594.77 | L16: =IF(K16*'Loan Input Parameters'!$B$41<'Loan Input Parameters'!$B$42,'Loan Input Parameters'!$B$42,K16*'Loan Input Parameters'!$B$41) -> 0 | M16: =K16-L16 -> 390594.77 | N16: =H16-(K16-L16) -> 65709.534 | O16: =IF('Loan Input Parameters'!$B$8*3%<=4000,4000,IF('Loan Input Parameters'!$B$8*3%>=18000,18000,'Loan Input Parameters'!$B$8*3%)) -> 15000 | P16: =IF(N16<0,O16,N16+O16) -> 80709.534
A17: =A16+1 -> 14 | B17: =EOMONTH(B16,1) -> 45626 | C17: =IF(ROUND(H16,0)>0,H16,0) -> 456304.3 | D17: =IF(A17<'Loan Input Parameters'!$B$16,'Loan Input Parameters'!$B$24,IF(A17='Loan Input Parameters'!$B$16,'Loan Input Parameters'!$B$24+'Loan Input Parameters'!$B$20,0)) -> 7931.5631 | E17: =IF($A17<'Loan Input Parameters'!$B$16,C17*'Loan Input Parameters'!$B$15/12,"0.00") -> 4182.7894 | F17: =IF(A17<='Loan Input Parameters'!$B$16,'Loan Input Parameters'!$B$23,0) -> 69 | G17: =IF($A17<'Loan Input Parameters'!$B$16,D17-E17-F17,"0.00") -> 3679.7736 | H17: =IF($A17<'Loan Input Parameters'!$B$16,C17-G17,"0.00") -> 452624.53 | I17: =H17/'Loan Input Parameters'!$B$13 -> 0.90306815 | J17: =IF('Loan Input Parameters'!$B$32="Overide",'Loan Input Parameters'!$C$35,'Loan Input Parameters'!$B$35) -> 0.15 | K17: {=IF( AND(MONTH($B17)=1,SUMPRODUCT(--(MONTH($B$4:B17)=1))=1), K16*(1-22%*J17), IF( AND(MONTH($B17)=1,SUMPRODUCT(--(MONTH($B$4:B17)=1))=2), K16*(1-20%*J17), IF($A17<13,K16*(1-(J17*4%)), IF($A17<25,K16*(1-(J17*5%)),K16*(1-J17/12)))))} -> 387665.31 | L17: =IF(K17*'Loan Input Parameters'!$B$41<'Loan Input Parameters'!$B$42,'Loan Input Parameters'!$B$42,K17*'Loan Input Parameters'!$B$41) -> 0 | M17: =K17-L17 -> 387665.31 | N17: =H17-(K17-L17) -> 64959.221 | O17: =IF('Loan Input Parameters'!$B$8*3%<=4000,4000,IF('Loan Input Parameters'!$B$8*3%>=18000,18000,'Loan Input Parameters'!$B$8*3%)) -> 15000 | P17: =IF(N17<0,O17,N17+O17) -> 79959.221
A18: =A17+1 -> 15 | B18: =EOMONTH(B17,1) -> 45657 | C18: =IF(ROUND(H17,0)>0,H17,0) -> 452624.53 | D18: =IF(A18<'Loan Input Parameters'!$B$16,'Loan Input Parameters'!$B$24,IF(A18='Loan Input Parameters'!$B$16,'Loan Input Parameters'!$B$24+'Loan Input Parameters'!$B$20,0)) -> 7931.5631 | E18: =IF($A18<'Loan Input Parameters'!$B$16,C18*'Loan Input Parameters'!$B$15/12,"0.00") -> 4149.0582 | F18: =IF(A18<='Loan Input Parameters'!$B$16,'Loan Input Parameters'!$B$23,0) -> 69 | G18: =IF($A18<'Loan Input Parameters'!$B$16,D18-E18-F18,"0.00") -> 3713.5049 | H18: =IF($A18<'Loan Input Parameters'!$B$16,C18-G18,"0.00") -> 448911.02 | I18: =H18/'Loan Input Parameters'!$B$13 -> 0.89565903 | J18: =IF('Loan Input Parameters'!$B$32="Overide",'Loan Input Parameters'!$C$35,'Loan Input Parameters'!$B$35) -> 0.15 | K18: {=IF( AND(MONTH($B18)=1,SUMPRODUCT(--(MONTH($B$4:B18)=1))=1), K17*(1-22%*J18), IF( AND(MONTH($B18)=1,SUMPRODUCT(--(MONTH($B$4:B18)=1))=2), K17*(1-20%*J18), IF($A18<13,K17*(1-(J18*4%)), IF($A18<25,K17*(1-(J18*5%)),K17*(1-J18/12) ) ) ))} -> 384757.82 | L18: =IF(K18*'Loan Input Parameters'!$B$41<'Loan Input Parameters'!$B$42,'Loan Input Parameters'!$B$42,K18*'Loan Input Parameters'!$B$41) -> 0 | M18: =K18-L18 -> 384757.82 | N18: =H18-(K18-L18) -> 64153.206 | O18: =IF('Loan Input Parameters'!$B$8*3%<=4000,4000,IF('Loan Input Parameters'!$B$8*3%>=18000,18000,'Loan Input Parameters'!$B$8*3%)) -> 15000 | P18: =IF(N18<0,O18,N18+O18) -> 79153.206
A19: =A18+1 -> 16 | B19: =EOMONTH(B18,1) -> 45688 | C19: =IF(ROUND(H18,0)>0,H18,0) -> 448911.02 | D19: =IF(A19<'Loan Input Parameters'!$B$16,'Loan Input Parameters'!$B$24,IF(A19='Loan Input Parameters'!$B$16,'Loan Input Parameters'!$B$24+'Loan Input Parameters'!$B$20,0)) -> 7931.5631 | E19: =IF($A19<'Loan Input Parameters'!$B$16,C19*'Loan Input Parameters'!$B$15/12,"0.00") -> 4115.0177 | F19: =IF(A19<='Loan Input Parameters'!$B$16,'Loan Input Parameters'!$B$23,0) -> 69 | G19: =IF($A19<'Loan Input Parameters'!$B$16,D19-E19-F19,"0.00") -> 3747.5453 | H19: =IF($A19<'Loan Input Parameters'!$B$16,C19-G19,"0.00") -> 445163.48 | I19: =H19/'Loan Input Parameters'!$B$13 -> 0.888182 | J19: =IF('Loan Input Parameters'!$B$32="Overide",'Loan Input Parameters'!$C$35,'Loan Input Parameters'!$B$35) -> 0.15 | K19: {=IF( AND(MONTH($B19)=1,SUMPRODUCT(--(MONTH($B$4:B19)=1))=1), K18*(1-22%*J19), IF( AND(MONTH($B19)=1,SUMPRODUCT(--(MONTH($B$4:B19)=1))=2), K18*(1-20%*J19), IF($A19<13,K18*(1-(J19*4%)), IF($A19<25,K18*(1-(J19*5%)),K18*(1-J19/12) ) ) ))} -> 373215.08 | L19: =IF(K19*'Loan Input Parameters'!$B$41<'Loan Input Parameters'!$B$42,'Loan Input Parameters'!$B$42,K19*'Loan Input Parameters'!$B$41) -> 0 | M19: =K19-L19 -> 373215.08 | N19: =H19-(K19-L19) -> 71948.396 | O19: =IF('Loan Input Parameters'!$B$8*3%<=4000,4000,IF('Loan Input Parameters'!$B$8*3%>=18000,18000,'Loan Input Parameters'!$B$8*3%)) -> 15000 | P19: =IF(N19<0,O19,N19+O19) -> 86948.396
A20: =A19+1 -> 17 | B20: =EOMONTH(B19,1) -> 45716 | C20: =IF(ROUND(H19,0)>0,H19,0) -> 445163.48 | D20: =IF(A20<'Loan Input Parameters'!$B$16,'Loan Input Parameters'!$B$24,IF(A20='Loan Input Parameters'!$B$16,'Loan Input Parameters'!$B$24+'Loan Input Parameters'!$B$20,0)) -> 7931.5631 | E20: =IF($A20<'Loan Input Parameters'!$B$16,C20*'Loan Input Parameters'!$B$15/12,"0.00") -> 4080.6652 | F20: =IF(A20<='Loan Input Parameters'!$B$16,'Loan Input Parameters'!$B$23,0) -> 69 | G20: =IF($A20<'Loan Input Parameters'!$B$16,D20-E20-F20,"0.00") -> 3781.8978 | H20: =IF($A20<'Loan Input Parameters'!$B$16,C20-G20,"0.00") -> 441381.58 | I20: =H20/'Loan Input Parameters'!$B$13 -> 0.88063642 | J20: =IF('Loan Input Parameters'!$B$32="Overide",'Loan Input Parameters'!$C$35,'Loan Input Parameters'!$B$35) -> 0.15 | K20: {=IF( AND(MONTH($B20)=1,SUMPRODUCT(--(MONTH($B$4:B20)=1))=1), K19*(1-22%*J20), IF( AND(MONTH($B20)=1,SUMPRODUCT(--(MONTH($B$4:B20)=1))=2), K19*(1-20%*J20), IF($A20<13,K19*(1-(J20*4%)), IF($A20<25,K19*(1-(J20*5%)),K19*(1-J20/12) ) ) ))} -> 370415.97 | L20: =IF(K20*'Loan Input Parameters'!$B$41<'Loan Input Parameters'!$B$42,'Loan Input Parameters'!$B$42,K20*'Loan Input Parameters'!$B$41) -> 0 | M20: =K20-L20 -> 370415.97 | N20: =H20-(K20-L20) -> 70965.611 | O20: =IF('Loan Input Parameters'!$B$8*3%<=4000,4000,IF('Loan Input Parameters'!$B$8*3%>=18000,18000,'Loan Input Parameters'!$B$8*3%)) -> 15000 | P20: =IF(N20<0,O20,N20+O20) -> 85965.611
A21: =A20+1 -> 18 | B21: =EOMONTH(B20,1) -> 45747 | C21: =IF(ROUND(H20,0)>0,H20,0) -> 441381.58 | D21: =IF(A21<'Loan Input Parameters'!$B$16,'Loan Input Parameters'!$B$24,IF(A21='Loan Input Parameters'!$B$16,'Loan Input Parameters'!$B$24+'Loan Input Parameters'!$B$20,0)) -> 7931.5631 | E21: =IF($A21<'Loan Input Parameters'!$B$16,C21*'Loan Input Parameters'!$B$15/12,"0.00") -> 4045.9978 | F21: =IF(A21<='Loan Input Parameters'!$B$16,'Loan Input Parameters'!$B$23,0) -> 69 | G21: =IF($A21<'Loan Input Parameters'!$B$16,D21-E21-F21,"0.00") -> 3816.5652 | H21: =IF($A21<'Loan Input Parameters'!$B$16,C21-G21,"0.00") -> 437565.02 | I21: =H21/'Loan Input Parameters'!$B$13 -> 0.87302168 | J21: =IF('Loan Input Parameters'!$B$32="Overide",'Loan Input Parameters'!$C$35,'Loan Input Parameters'!$B$35) -> 0.15 | K21: {=IF( AND(MONTH($B21)=1,SUMPRODUCT(--(MONTH($B$4:B21)=1))=1), K20*(1-22%*J21), IF( AND(MONTH($B21)=1,SUMPRODUCT(--(MONTH($B$4:B21)=1))=2), K20*(1-20%*J21), IF($A21<13,K20*(1-(J21*4%)), IF($A21<25,K20*(1-(J21*5%)),K20*(1-J21/12) ) ) ))} -> 367637.85 | L21: =IF(K21*'Loan Input Parameters'!$B$41<'Loan Input Parameters'!$B$42,'Loan Input Parameters'!$B$42,K21*'Loan Input Parameters'!$B$41) -> 0 | M21: =K21-L21 -> 367637.85 | N21: =H21-(K21-L21) -> 69927.165 | O21: =IF('Loan Input Parameters'!$B$8*3%<=4000,4000,IF('Loan Input Parameters'!$B$8*3%>=18000,18000,'Loan Input Parameters'!$B$8*3%)) -> 15000 | P21: =IF(N21<0,O21,N21+O21) -> 84927.165
A22: =A21+1 -> 19 | B22: =EOMONTH(B21,1) -> 45777 | C22: =IF(ROUND(H21,0)>0,H21,0) -> 437565.02 | D22: =IF(A22<'Loan Input Parameters'!$B$16,'Loan Input Parameters'!$B$24,IF(A22='Loan Input Parameters'!$B$16,'Loan Input Parameters'!$B$24+'Loan Input Parameters'!$B$20,0)) -> 7931.5631 | E22: =IF($A22<'Loan Input Parameters'!$B$16,C22*'Loan Input Parameters'!$B$15/12,"0.00") -> 4011.0126 | F22: =IF(A22<='Loan Input Parameters'!$B$16,'Loan Input Parameters'!$B$23,0) -> 69 | G22: =IF($A22<'Loan Input Parameters'!$B$16,D22-E22-F22,"0.00") -> 3851.5504 | H22: =IF($A22<'Loan Input Parameters'!$B$16,C22-G22,"0.00") -> 433713.46 | I22: =H22/'Loan Input Parameters'!$B$13 -> 0.86533714 | J22: =IF('Loan Input Parameters'!$B$32="Overide",'Loan Input Parameters'!$C$35,'Loan Input Parameters'!$B$35) -> 0.15 | K22: {=IF( AND(MONTH($B22)=1,SUMPRODUCT(--(MONTH($B$4:B22)=1))=1), K21*(1-22%*J22), IF( AND(MONTH($B22)=1,SUMPRODUCT(--(MONTH($B$4:B22)=1))=2), K21*(1-20%*J22), IF($A22<13,K21*(1-(J22*4%)), IF($A22<25,K21*(1-(J22*5%)),K21*(1-J22/12) ) ) ))} -> 364880.57 | L22: =IF(K22*'Loan Input Parameters'!$B$41<'Loan Input Parameters'!$B$42,'Loan Input Parameters'!$B$42,K22*'Loan Input Parameters'!$B$41) -> 0 | M22: =K22-L22 -> 364880.57 | N22: =H22-(K22-L22) -> 68832.899 | O22: =IF('Loan Input Parameters'!$B$8*3%<=4000,4000,IF('Loan Input Parameters'!$B$8*3%>=18000,18000,'Loan Input Parameters'!$B$8*3%)) -> 15000 | P22: =IF(N22<0,O22,N22+O22) -> 83832.899
A23: =A22+1 -> 20 | B23: =EOMONTH(B22,1) -> 45808 | C23: =IF(ROUND(H22,0)>0,H22,0) -> 433713.46 | D23: =IF(A23<'Loan Input Parameters'!$B$16,'Loan Input Parameters'!$B$24,IF(A23='Loan Input Parameters'!$B$16,'Loan Input Parameters'!$B$24+'Loan Input Parameters'!$B$20,0)) -> 7931.5631 | E23: =IF($A23<'Loan Input Parameters'!$B$16,C23*'Loan Input Parameters'!$B$15/12,"0.00") -> 3975.7068 | F23: =IF(A23<='Loan Input Parameters'!$B$16,'Loan Input Parameters'!$B$23,0) -> 69 | G23: =IF($A23<'Loan Input Parameters'!$B$16,D23-E23-F23,"0.00") -> 3886.8563 | H23: =IF($A23<'Loan Input Parameters'!$B$16,C23-G23,"0.00") -> 429826.61 | I23: =H23/'Loan Input Parameters'!$B$13 -> 0.85758216 | J23: =IF('Loan Input Parameters'!$B$32="Overide",'Loan Input Parameters'!$C$35,'Loan Input Parameters'!$B$35) -> 0.15 | K23: {=IF( AND(MONTH($B23)=1,SUMPRODUCT(--(MONTH($B$4:B23)=1))=1), K22*(1-22%*J23), IF( AND(MONTH($B23)=1,SUMPRODUCT(--(MONTH($B$4:B23)=1))=2), K22*(1-20%*J23), IF($A23<13,K22*(1-(J23*4%)), IF($A23<25,K22*(1-(J23*5%)),K22*(1-J23/12) ) ) ))} -> 362143.96 | L23: =IF(K23*'Loan Input Parameters'!$B$41<'Loan Input Parameters'!$B$42,'Loan Input Parameters'!$B$42,K23*'Loan Input Parameters'!$B$41) -> 0 | M23: =K23-L23 -> 362143.96 | N23: =H23-(K23-L23) -> 67682.647 | O23: =IF('Loan Input Parameters'!$B$8*3%<=4000,4000,IF('Loan Input Parameters'!$B$8*3%>=18000,18000,'Loan Input Parameters'!$B$8*3%)) -> 15000 | P23: =IF(N23<0,O23,N23+O23) -> 82682.647
A24: =A23+1 -> 21 | B24: =EOMONTH(B23,1) -> 45838 | C24: =IF(ROUND(H23,0)>0,H23,0) -> 429826.61 | D24: =IF(A24<'Loan Input Parameters'!$B$16,'Loan Input Parameters'!$B$24,IF(A24='Loan Input Parameters'!$B$16,'Loan Input Parameters'!$B$24+'Loan Input Parameters'!$B$20,0)) -> 7931.5631 | E24: =IF($A24<'Loan Input Parameters'!$B$16,C24*'Loan Input Parameters'!$B$15/12,"0.00") -> 3940.0772 | F24: =IF(A24<='Loan Input Parameters'!$B$16,'Loan Input Parameters'!$B$23,0) -> 69 | G24: =IF($A24<'Loan Input Parameters'!$B$16,D24-E24-F24,"0.00") -> 3922.4858 | H24: =IF($A24<'Loan Input Parameters'!$B$16,C24-G24,"0.00") -> 425904.12 | I24: =H24/'Loan Input Parameters'!$B$13 -> 0.84975608 | J24: =IF('Loan Input Parameters'!$B$32="Overide",'Loan Input Parameters'!$C$35,'Loan Input Parameters'!$B$35) -> 0.15 | K24: {=IF( AND(MONTH($B24)=1,SUMPRODUCT(--(MONTH($B$4:B24)=1))=1), K23*(1-22%*J24), IF( AND(MONTH($B24)=1,SUMPRODUCT(--(MONTH($B$4:B24)=1))=2), K23*(1-20%*J24), IF($A24<13,K23*(1-(J24*4%)), IF($A24<25,K23*(1-(J24*5%)),K23*(1-J24/12) ) ) ))} -> 359427.88 | L24: =IF(K24*'Loan Input Parameters'!$B$41<'Loan Input Parameters'!$B$42,'Loan Input Parameters'!$B$42,K24*'Loan Input Parameters'!$B$41) -> 0 | M24: =K24-L24 -> 359427.88 | N24: =H24-(K24-L24) -> 66476.241 | O24: =IF('Loan Input Parameters'!$B$8*3%<=4000,4000,IF('Loan Input Parameters'!$B$8*3%>=18000,18000,'Loan Input Parameters'!$B$8*3%)) -> 15000 | P24: =IF(N24<0,O24,N24+O24) -> 81476.241
A25: =A24+1 -> 22 | B25: =EOMONTH(B24,1) -> 45869 | C25: =IF(ROUND(H24,0)>0,H24,0) -> 425904.12 | D25: =IF(A25<'Loan Input Parameters'!$B$16,'Loan Input Parameters'!$B$24,IF(A25='Loan Input Parameters'!$B$16,'Loan Input Parameters'!$B$24+'Loan Input Parameters'!$B$20,0)) -> 7931.5631 | E25: =IF($A25<'Loan Input Parameters'!$B$16,C25*'Loan Input Parameters'!$B$15/12,"0.00") -> 3904.1211 | F25: =IF(A25<='Loan Input Parameters'!$B$16,'Loan Input Parameters'!$B$23,0) -> 69 | G25: =IF($A25<'Loan Input Parameters'!$B$16,D25-E25-F25,"0.00") -> 3958.4419 | H25: =IF($A25<'Loan Input Parameters'!$B$16,C25-G25,"0.00") -> 421945.68 | I25: =H25/'Loan Input Parameters'!$B$13 -> 0.84185827 | J25: =IF('Loan Input Parameters'!$B$32="Overide",'Loan Input Parameters'!$C$35,'Loan Input Parameters'!$B$35) -> 0.15 | K25: {=IF( AND(MONTH($B25)=1,SUMPRODUCT(--(MONTH($B$4:B25)=1))=1), K24*(1-22%*J25), IF( AND(MONTH($B25)=1,SUMPRODUCT(--(MONTH($B$4:B25)=1))=2), K24*(1-20%*J25), IF($A25<13,K24*(1-(J25*4%)), IF($A25<25,K24*(1-(J25*5%)),K24*(1-J25/12) ) ) ))} -> 356732.17 | L25: =IF(K25*'Loan Input Parameters'!$B$41<'Loan Input Parameters'!$B$42,'Loan Input Parameters'!$B$42,K25*'Loan Input Parameters'!$B$41) -> 0 | M25: =K25-L25 -> 356732.17 | N25: =H25-(K25-L25) -> 65213.508 | O25: =IF('Loan Input Parameters'!$B$8*3%<=4000,4000,IF('Loan Input Parameters'!$B$8*3%>=18000,18000,'Loan Input Parameters'!$B$8*3%)) -> 15000 | P25: =IF(N25<0,O25,N25+O25) -> 80213.508
A26: =A25+1 -> 23 | B26: =EOMONTH(B25,1) -> 45900 | C26: =IF(ROUND(H25,0)>0,H25,0) -> 421945.68 | D26: =IF(A26<'Loan Input Parameters'!$B$16,'Loan Input Parameters'!$B$24,IF(A26='Loan Input Parameters'!$B$16,'Loan Input Parameters'!$B$24+'Loan Input Parameters'!$B$20,0)) -> 7931.5631 | E26: =IF($A26<'Loan Input Parameters'!$B$16,C26*'Loan Input Parameters'!$B$15/12,"0.00") -> 3867.8354 | F26: =IF(A26<='Loan Input Parameters'!$B$16,'Loan Input Parameters'!$B$23,0) -> 69 | G26: =IF($A26<'Loan Input Parameters'!$B$16,D26-E26-F26,"0.00") -> 3994.7276 | H26: =IF($A26<'Loan Input Parameters'!$B$16,C26-G26,"0.00") -> 417950.95 | I26: =H26/'Loan Input Parameters'!$B$13 -> 0.83388807 | J26: =IF('Loan Input Parameters'!$B$32="Overide",'Loan Input Parameters'!$C$35,'Loan Input Parameters'!$B$35) -> 0.15 | K26: {=IF( AND(MONTH($B26)=1,SUMPRODUCT(--(MONTH($B$4:B26)=1))=1), K25*(1-22%*J26), IF( AND(MONTH($B26)=1,SUMPRODUCT(--(MONTH($B$4:B26)=1))=2), K25*(1-20%*J26), IF($A26<13,K25*(1-(J26*4%)), IF($A26<25,K25*(1-(J26*5%)),K25*(1-J26/12) ) ) ))} -> 354056.68 | L26: =IF(K26*'Loan Input Parameters'!$B$41<'Loan Input Parameters'!$B$42,'Loan Input Parameters'!$B$42,K26*'Loan Input Parameters'!$B$41) -> 0 | M26: =K26-L26 -> 354056.68 | N26: =H26-(K26-L26) -> 63894.271 | O26: =IF('Loan Input Parameters'!$B$8*3%<=4000,4000,IF('Loan Input Parameters'!$B$8*3%>=18000,18000,'Loan Input Parameters'!$B$8*3%)) -> 15000 | P26: =IF(N26<0,O26,N26+O26) -> 78894.271
A27: =A26+1 -> 24 | B27: =EOMONTH(B26,1) -> 45930 | C27: =IF(ROUND(H26,0)>0,H26,0) -> 417950.95 | D27: =IF(A27<'Loan Input Parameters'!$B$16,'Loan Input Parameters'!$B$24,IF(A27='Loan Input Parameters'!$B$16,'Loan Input Parameters'!$B$24+'Loan Input Parameters'!$B$20,0)) -> 7931.5631 | E27: =IF($A27<'Loan Input Parameters'!$B$16,C27*'Loan Input Parameters'!$B$15/12,"0.00") -> 3831.2171 | F27: =IF(A27<='Loan Input Parameters'!$B$16,'Loan Input Parameters'!$B$23,0) -> 69 | G27: =IF($A27<'Loan Input Parameters'!$B$16,D27-E27-F27,"0.00") -> 4031.346 | H27: =IF($A27<'Loan Input Parameters'!$B$16,C27-G27,"0.00") -> 413919.61 | I27: =H27/'Loan Input Parameters'!$B$13 -> 0.8258448 | J27: =IF('Loan Input Parameters'!$B$32="Overide",'Loan Input Parameters'!$C$35,'Loan Input Parameters'!$B$35) -> 0.15 | K27: {=IF( AND(MONTH($B27)=1,SUMPRODUCT(--(MONTH($B$4:B27)=1))=1), K26*(1-22%*J27), IF( AND(MONTH($B27)=1,SUMPRODUCT(--(MONTH($B$4:B27)=1))=2), K26*(1-20%*J27), IF($A27<13,K26*(1-(J27*4%)), IF($A27<25,K26*(1-(J27*5%)),K26*(1-J27/12) ) ) ))} -> 351401.26 | L27: =IF(K27*'Loan Input Parameters'!$B$41<'Loan Input Parameters'!$B$42,'Loan Input Parameters'!$B$42,K27*'Loan Input Parameters'!$B$41) -> 0 | M27: =K27-L27 -> 351401.26 | N27: =H27-(K27-L27) -> 62518.351 | O27: =IF('Loan Input Parameters'!$B$8*3%<=4000,4000,IF('Loan Input Parameters'!$B$8*3%>=18000,18000,'Loan Input Parameters'!$B$8*3%)) -> 15000 | P27: =IF(N27<0,O27,N27+O27) -> 77518.351
A28: =A27+1 -> 25 | B28: =EOMONTH(B27,1) -> 45961 | C28: =IF(ROUND(H27,0)>0,H27,0) -> 413919.61 | D28: =IF(A28<'Loan Input Parameters'!$B$16,'Loan Input Parameters'!$B$24,IF(A28='Loan Input Parameters'!$B$16,'Loan Input Parameters'!$B$24+'Loan Input Parameters'!$B$20,0)) -> 7931.5631 | E28: =IF($A28<'Loan Input Parameters'!$B$16,C28*'Loan Input Parameters'!$B$15/12,"0.00") -> 3794.2631 | F28: =IF(A28<='Loan Input Parameters'!$B$16,'Loan Input Parameters'!$B$23,0) -> 69 | G28: =IF($A28<'Loan Input Parameters'!$B$16,D28-E28-F28,"0.00") -> 4068.3 | H28: =IF($A28<'Loan Input Parameters'!$B$16,C28-G28,"0.00") -> 409851.31 | I28: =H28/'Loan Input Parameters'!$B$13 -> 0.8177278 | J28: =IF('Loan Input Parameters'!$B$32="Overide",'Loan Input Parameters'!$C$36,'Loan Input Parameters'!$B$36) -> 0.11 | K28: {=IF( AND(MONTH($B28)=1,SUMPRODUCT(--(MONTH($B$4:B28)=1))=1), K27*(1-22%*J28), IF( AND(MONTH($B28)=1,SUMPRODUCT(--(MONTH($B$4:B28)=1))=2), K27*(1-20%*J28), IF($A28<13,K27*(1-(J28*4%)), IF($A28<25,K27*(1-(J28*5%)),K27*(1-J28/12) ) ) ))} -> 348180.08 | L28: =IF(K28*'Loan Input Parameters'!$B$41<'Loan Input Parameters'!$B$42,'Loan Input Parameters'!$B$42,K28*'Loan Input Parameters'!$B$41) -> 0 | M28: =K28-L28 -> 348180.08 | N28: =H28-(K28-L28) -> 61671.229 | O28: =IF('Loan Input Parameters'!$B$8*3%<=4000,4000,IF('Loan Input Parameters'!$B$8*3%>=18000,18000,'Loan Input Parameters'!$B$8*3%)) -> 15000 | P28: =IF(N28<0,O28,N28+O28) -> 76671.229
A29: =A28+1 -> 26 | B29: =EOMONTH(B28,1) -> 45991 | C29: =IF(ROUND(H28,0)>0,H28,0) -> 409851.31 | D29: =IF(A29<'Loan Input Parameters'!$B$16,'Loan Input Parameters'!$B$24,IF(A29='Loan Input Parameters'!$B$16,'Loan Input Parameters'!$B$24+'Loan Input Parameters'!$B$20,0)) -> 7931.5631 | E29: =IF($A29<'Loan Input Parameters'!$B$16,C29*'Loan Input Parameters'!$B$15/12,"0.00") -> 3756.9703 | F29: =IF(A29<='Loan Input Parameters'!$B$16,'Loan Input Parameters'!$B$23,0) -> 69 | G29: =IF($A29<'Loan Input Parameters'!$B$16,D29-E29-F29,"0.00") -> 4105.5927 | H29: =IF($A29<'Loan Input Parameters'!$B$16,C29-G29,"0.00") -> 405745.71 | I29: =H29/'Loan Input Parameters'!$B$13 -> 0.8095364 | J29: =J28 -> 0.11 | K29: {=IF( AND(MONTH($B29)=1,SUMPRODUCT(--(MONTH($B$4:B29)=1))=1), K28*(1-22%*J29), IF( AND(MONTH($B29)=1,SUMPRODUCT(--(MONTH($B$4:B29)=1))=2), K28*(1-20%*J29), IF($A29<13,K28*(1-(J29*4%)), IF($A29<25,K28*(1-(J29*5%)),K28*(1-J29/12) ) ) ))} -> 344988.43 | L29: =IF(K29*'Loan Input Parameters'!$B$41<'Loan Input Parameters'!$B$42,'Loan Input Parameters'!$B$42,K29*'Loan Input Parameters'!$B$41) -> 0 | M29: =K29-L29 -> 344988.43 | N29: =H29-(K29-L29) -> 60757.287 | O29: =IF('Loan Input Parameters'!$B$8*3%<=4000,4000,IF('Loan Input Parameters'!$B$8*3%>=18000,18000,'Loan Input Parameters'!$B$8*3%)) -> 15000 | P29: =IF(N29<0,O29,N29+O29) -> 75757.287
A30: =A29+1 -> 27 | B30: =EOMONTH(B29,1) -> 46022 | C30: =IF(ROUND(H29,0)>0,H29,0) -> 405745.71 | D30: =IF(A30<'Loan Input Parameters'!$B$16,'Loan Input Parameters'!$B$24,IF(A30='Loan Input Parameters'!$B$16,'Loan Input Parameters'!$B$24+'Loan Input Parameters'!$B$20,0)) -> 7931.5631 | E30: =IF($A30<'Loan Input Parameters'!$B$16,C30*'Loan Input Parameters'!$B$15/12,"0.00") -> 3719.3357 | F30: =IF(A30<='Loan Input Parameters'!$B$16,'Loan Input Parameters'!$B$23,0) -> 69 | G30: =IF($A30<'Loan Input Parameters'!$B$16,D30-E30-F30,"0.00") -> 4143.2273 | H30: =IF($A30<'Loan Input Parameters'!$B$16,C30-G30,"0.00") -> 401602.49 | I30: =H30/'Loan Input Parameters'!$B$13 -> 0.80126991 | J30: =J29 -> 0.11 | K30: {=IF( AND(MONTH($B30)=1,SUMPRODUCT(--(MONTH($B$4:B30)=1))=1), K29*(1-22%*J30), IF( AND(MONTH($B30)=1,SUMPRODUCT(--(MONTH($B$4:B30)=1))=2), K29*(1-20%*J30), IF($A30<13,K29*(1-(J30*4%)), IF($A30<25,K29*(1-(J30*5%)),K29*(1-J30/12) ) ) ))} -> 341826.03 | L30: =IF(K30*'Loan Input Parameters'!$B$41<'Loan Input Parameters'!$B$42,'Loan Input Parameters'!$B$42,K30*'Loan Input Parameters'!$B$41) -> 0 | M30: =K30-L30 -> 341826.03 | N30: =H30-(K30-L30) -> 59776.453 | O30: =IF('Loan Input Parameters'!$B$8*3%<=4000,4000,IF('Loan Input Parameters'!$B$8*3%>=18000,18000,'Loan Input Parameters'!$B$8*3%)) -> 15000 | P30: =IF(N30<0,O30,N30+O30) -> 74776.453
A31: =A30+1 -> 28 | B31: =EOMONTH(B30,1) -> 46053 | C31: =IF(ROUND(H30,0)>0,H30,0) -> 401602.49 | D31: =IF(A31<'Loan Input Parameters'!$B$16,'Loan Input Parameters'!$B$24,IF(A31='Loan Input Parameters'!$B$16,'Loan Input Parameters'!$B$24+'Loan Input Parameters'!$B$20,0)) -> 7931.5631 | E31: =IF($A31<'Loan Input Parameters'!$B$16,C31*'Loan Input Parameters'!$B$15/12,"0.00") -> 3681.3561 | F31: =IF(A31<='Loan Input Parameters'!$B$16,'Loan Input Parameters'!$B$23,0) -> 69 | G31: =IF($A31<'Loan Input Parameters'!$B$16,D31-E31-F31,"0.00") -> 4181.2069 | H31: =IF($A31<'Loan Input Parameters'!$B$16,C31-G31,"0.00") -> 397421.28 | I31: =H31/'Loan Input Parameters'!$B$13 -> 0.79292764 | J31: =J30 -> 0.11 | K31: {=IF( AND(MONTH($B31)=1,SUMPRODUCT(--(MONTH($B$4:B31)=1))=1), K30*(1-22%*J31), IF( AND(MONTH($B31)=1,SUMPRODUCT(--(MONTH($B$4:B31)=1))=2), K30*(1-20%*J31), IF($A31<13,K30*(1-(J31*4%)), IF($A31<25,K30*(1-(J31*5%)),K30*(1-J31/12) ) ) ))} -> 338692.63 | L31: =IF(K31*'Loan Input Parameters'!$B$41<'Loan Input Parameters'!$B$42,'Loan Input Parameters'!$B$42,K31*'Loan Input Parameters'!$B$41) -> 0 | M31: =K31-L31 -> 338692.63 | N31: =H31-(K31-L31) -> 58728.652 | O31: =IF('Loan Input Parameters'!$B$8*3%<=4000,4000,IF('Loan Input Parameters'!$B$8*3%>=18000,18000,'Loan Input Parameters'!$B$8*3%)) -> 15000 | P31: =IF(N31<0,O31,N31+O31) -> 73728.652
A32: =A31+1 -> 29 | B32: =EOMONTH(B31,1) -> 46081 | C32: =IF(ROUND(H31,0)>0,H31,0) -> 397421.28 | D32: =IF(A32<'Loan Input Parameters'!$B$16,'Loan Input Parameters'!$B$24,IF(A32='Loan Input Parameters'!$B$16,'Loan Input Parameters'!$B$24+'Loan Input Parameters'!$B$20,0)) -> 7931.5631 | E32: =IF($A32<'Loan Input Parameters'!$B$16,C32*'Loan Input Parameters'!$B$15/12,"0.00") -> 3643.0284 | F32: =IF(A32<='Loan Input Parameters'!$B$16,'Loan Input Parameters'!$B$23,0) -> 69 | G32: =IF($A32<'Loan Input Parameters'!$B$16,D32-E32-F32,"0.00") -> 4219.5347 | H32: =IF($A32<'Loan Input Parameters'!$B$16,C32-G32,"0.00") -> 393201.75 | I32: =H32/'Loan Input Parameters'!$B$13 -> 0.7845089 | J32: =J31 -> 0.11 | K32: {=IF( AND(MONTH($B32)=1,SUMPRODUCT(--(MONTH($B$4:B32)=1))=1), K31*(1-22%*J32), IF( AND(MONTH($B32)=1,SUMPRODUCT(--(MONTH($B$4:B32)=1))=2), K31*(1-20%*J32), IF($A32<13,K31*(1-(J32*4%)), IF($A32<25,K31*(1-(J32*5%)),K31*(1-J32/12) ) ) ))} -> 335587.95 | L32: =IF(K32*'Loan Input Parameters'!$B$41<'Loan Input Parameters'!$B$42,'Loan Input Parameters'!$B$42,K32*'Loan Input Parameters'!$B$41) -> 0 | M32: =K32-L32 -> 335587.95 | N32: =H32-(K32-L32) -> 57613.8 | O32: =IF('Loan Input Parameters'!$B$8*3%<=4000,4000,IF('Loan Input Parameters'!$B$8*3%>=18000,18000,'Loan Input Parameters'!$B$8*3%)) -> 15000 | P32: =IF(N32<0,O32,N32+O32) -> 72613.8
A33: =A32+1 -> 30 | B33: =EOMONTH(B32,1) -> 46112 | C33: =IF(ROUND(H32,0)>0,H32,0) -> 393201.75 | D33: =IF(A33<'Loan Input Parameters'!$B$16,'Loan Input Parameters'!$B$24,IF(A33='Loan Input Parameters'!$B$16,'Loan Input Parameters'!$B$24+'Loan Input Parameters'!$B$20,0)) -> 7931.5631 | E33: =IF($A33<'Loan Input Parameters'!$B$16,C33*'Loan Input Parameters'!$B$15/12,"0.00") -> 3604.3493 | F33: =IF(A33<='Loan Input Parameters'!$B$16,'Loan Input Parameters'!$B$23,0) -> 69 | G33: =IF($A33<'Loan Input Parameters'!$B$16,D33-E33-F33,"0.00") -> 4258.2137 | H33: =IF($A33<'Loan Input Parameters'!$B$16,C33-G33,"0.00") -> 388943.53 | I33: =H33/'Loan Input Parameters'!$B$13 -> 0.77601299 | J33: =J32 -> 0.11 | K33: {=IF( AND(MONTH($B33)=1,SUMPRODUCT(--(MONTH($B$4:B33)=1))=1), K32*(1-22%*J33), IF( AND(MONTH($B33)=1,SUMPRODUCT(--(MONTH($B$4:B33)=1))=2), K32*(1-20%*J33), IF($A33<13,K32*(1-(J33*4%)), IF($A33<25,K32*(1-(J33*5%)),K32*(1-J33/12) ) ) ))} -> 332511.72 | L33: =IF(K33*'Loan Input Parameters'!$B$41<'Loan Input Parameters'!$B$42,'Loan Input Parameters'!$B$42,K33*'Loan Input Parameters'!$B$41) -> 0 | M33: =K33-L33 -> 332511.72 | N33: =H33-(K33-L33) -> 56431.809 | O33: =IF('Loan Input Parameters'!$B$8*3%<=4000,4000,IF('Loan Input Parameters'!$B$8*3%>=18000,18000,'Loan Input Parameters'!$B$8*3%)) -> 15000 | P33: =IF(N33<0,O33,N33+O33) -> 71431.809
A34: =A33+1 -> 31 | B34: =EOMONTH(B33,1) -> 46142 | C34: =IF(ROUND(H33,0)>0,H33,0) -> 388943.53 | D34: =IF(A34<'Loan Input Parameters'!$B$16,'Loan Input Parameters'!$B$24,IF(A34='Loan Input Parameters'!$B$16,'Loan Input Parameters'!$B$24+'Loan Input Parameters'!$B$20,0)) -> 7931.5631 | E34: =IF($A34<'Loan Input Parameters'!$B$16,C34*'Loan Input Parameters'!$B$15/12,"0.00") -> 3565.3157 | F34: =IF(A34<='Loan Input Parameters'!$B$16,'Loan Input Parameters'!$B$23,0) -> 69 | G34: =IF($A34<'Loan Input Parameters'!$B$16,D34-E34-F34,"0.00") -> 4297.2473 | H34: =IF($A34<'Loan Input Parameters'!$B$16,C34-G34,"0.00") -> 384646.28 | I34: =H34/'Loan Input Parameters'!$B$13 -> 0.7674392 | J34: =J33 -> 0.11 | K34: {=IF( AND(MONTH($B34)=1,SUMPRODUCT(--(MONTH($B$4:B34)=1))=1), K33*(1-22%*J34), IF( AND(MONTH($B34)=1,SUMPRODUCT(--(MONTH($B$4:B34)=1))=2), K33*(1-20%*J34), IF($A34<13,K33*(1-(J34*4%)), IF($A34<25,K33*(1-(J34*5%)),K33*(1-J34/12) ) ) ))} -> 329463.7 | L34: =IF(K34*'Loan Input Parameters'!$B$41<'Loan Input Parameters'!$B$42,'Loan Input Parameters'!$B$42,K34*'Loan Input Parameters'!$B$41) -> 0 | M34: =K34-L34 -> 329463.7 | N34: =H34-(K34-L34) -> 55182.585 | O34: =IF('Loan Input Parameters'!$B$8*3%<=4000,4000,IF('Loan Input Parameters'!$B$8*3%>=18000,18000,'Loan Input Parameters'!$B$8*3%)) -> 15000 | P34: =IF(N34<0,O34,N34+O34) -> 70182.585
A35: =A34+1 -> 32 | B35: =EOMONTH(B34,1) -> 46173 | C35: =IF(ROUND(H34,0)>0,H34,0) -> 384646.28 | D35: =IF(A35<'Loan Input Parameters'!$B$16,'Loan Input Parameters'!$B$24,IF(A35='Loan Input Parameters'!$B$16,'Loan Input Parameters'!$B$24+'Loan Input Parameters'!$B$20,0)) -> 7931.5631 | E35: =IF($A35<'Loan Input Parameters'!$B$16,C35*'Loan Input Parameters'!$B$15/12,"0.00") -> 3525.9243 | F35: =IF(A35<='Loan Input Parameters'!$B$16,'Loan Input Parameters'!$B$23,0) -> 69 | G35: =IF($A35<'Loan Input Parameters'!$B$16,D35-E35-F35,"0.00") -> 4336.6388 | H35: =IF($A35<'Loan Input Parameters'!$B$16,C35-G35,"0.00") -> 380309.65 | I35: =H35/'Loan Input Parameters'!$B$13 -> 0.75878682 | J35: =J34 -> 0.11 | K35: {=IF( AND(MONTH($B35)=1,SUMPRODUCT(--(MONTH($B$4:B35)=1))=1), K34*(1-22%*J35), IF( AND(MONTH($B35)=1,SUMPRODUCT(--(MONTH($B$4:B35)=1))=2), K34*(1-20%*J35), IF($A35<13,K34*(1-(J35*4%)), IF($A35<25,K34*(1-(J35*5%)),K34*(1-J35/12) ) ) ))} -> 326443.62 | L35: =IF(K35*'Loan Input Parameters'!$B$41<'Loan Input Parameters'!$B$42,'Loan Input Parameters'!$B$42,K35*'Loan Input Parameters'!$B$41) -> 0 | M35: =K35-L35 -> 326443.62 | N35: =H35-(K35-L35) -> 53866.031 | O35: =IF('Loan Input Parameters'!$B$8*3%<=4000,4000,IF('Loan Input Parameters'!$B$8*3%>=18000,18000,'Loan Input Parameters'!$B$8*3%)) -> 15000 | P35: =IF(N35<0,O35,N35+O35) -> 68866.031
A36: =A35+1 -> 33 | B36: =EOMONTH(B35,1) -> 46203 | C36: =IF(ROUND(H35,0)>0,H35,0) -> 380309.65 | D36: =IF(A36<'Loan Input Parameters'!$B$16,'Loan Input Parameters'!$B$24,IF(A36='Loan Input Parameters'!$B$16,'Loan Input Parameters'!$B$24+'Loan Input Parameters'!$B$20,0)) -> 7931.5631 | E36: =IF($A36<'Loan Input Parameters'!$B$16,C36*'Loan Input Parameters'!$B$15/12,"0.00") -> 3486.1718 | F36: =IF(A36<='Loan Input Parameters'!$B$16,'Loan Input Parameters'!$B$23,0) -> 69 | G36: =IF($A36<'Loan Input Parameters'!$B$16,D36-E36-F36,"0.00") -> 4376.3913 | H36: =IF($A36<'Loan Input Parameters'!$B$16,C36-G36,"0.00") -> 375933.25 | I36: =H36/'Loan Input Parameters'!$B$13 -> 0.75005513 | J36: =J35 -> 0.11 | K36: {=IF( AND(MONTH($B36)=1,SUMPRODUCT(--(MONTH($B$4:B36)=1))=1), K35*(1-22%*J36), IF( AND(MONTH($B36)=1,SUMPRODUCT(--(MONTH($B$4:B36)=1))=2), K35*(1-20%*J36), IF($A36<13,K35*(1-(J36*4%)), IF($A36<25,K35*(1-(J36*5%)),K35*(1-J36/12) ) ) ))} -> 323451.22 | L36: =IF(K36*'Loan Input Parameters'!$B$41<'Loan Input Parameters'!$B$42,'Loan Input Parameters'!$B$42,K36*'Loan Input Parameters'!$B$41) -> 0 | M36: =K36-L36 -> 323451.22 | N36: =H36-(K36-L36) -> 52482.039 | O36: =IF('Loan Input Parameters'!$B$8*3%<=4000,4000,IF('Loan Input Parameters'!$B$8*3%>=18000,18000,'Loan Input Parameters'!$B$8*3%)) -> 15000 | P36: =IF(N36<0,O36,N36+O36) -> 67482.039
A37: =A36+1 -> 34 | B37: =EOMONTH(B36,1) -> 46234 | C37: =IF(ROUND(H36,0)>0,H36,0) -> 375933.25 | D37: =IF(A37<'Loan Input Parameters'!$B$16,'Loan Input Parameters'!$B$24,IF(A37='Loan Input Parameters'!$B$16,'Loan Input Parameters'!$B$24+'Loan Input Parameters'!$B$20,0)) -> 7931.5631 | E37: =IF($A37<'Loan Input Parameters'!$B$16,C37*'Loan Input Parameters'!$B$15/12,"0.00") -> 3446.0548 | F37: =IF(A37<='Loan Input Parameters'!$B$16,'Loan Input Parameters'!$B$23,0) -> 69 | G37: =IF($A37<'Loan Input Parameters'!$B$16,D37-E37-F37,"0.00") -> 4416.5082 | H37: =IF($A37<'Loan Input Parameters'!$B$16,C37-G37,"0.00") -> 371516.75 | I37: =H37/'Loan Input Parameters'!$B$13 -> 0.74124339 | J37: =J36 -> 0.11 | K37: {=IF( AND(MONTH($B37)=1,SUMPRODUCT(--(MONTH($B$4:B37)=1))=1), K36*(1-22%*J37), IF( AND(MONTH($B37)=1,SUMPRODUCT(--(MONTH($B$4:B37)=1))=2), K36*(1-20%*J37), IF($A37<13,K36*(1-(J37*4%)), IF($A37<25,K36*(1-(J37*5%)),K36*(1-J37/12) ) ) ))} -> 320486.25 | L37: =IF(K37*'Loan Input Parameters'!$B$41<'Loan Input Parameters'!$B$42,'Loan Input Parameters'!$B$42,K37*'Loan Input Parameters'!$B$41) -> 0 | M37: =K37-L37 -> 320486.25 | N37: =H37-(K37-L37) -> 51030.5 | O37: =IF('Loan Input Parameters'!$B$8*3%<=4000,4000,IF('Loan Input Parameters'!$B$8*3%>=18000,18000,'Loan Input Parameters'!$B$8*3%)) -> 15000 | P37: =IF(N37<0,O37,N37+O37) -> 66030.5
A38: =A37+1 -> 35 | B38: =EOMONTH(B37,1) -> 46265 | C38: =IF(ROUND(H37,0)>0,H37,0) -> 371516.75 | D38: =IF(A38<'Loan Input Parameters'!$B$16,'Loan Input Parameters'!$B$24,IF(A38='Loan Input Parameters'!$B$16,'Loan Input Parameters'!$B$24+'Loan Input Parameters'!$B$20,0)) -> 7931.5631 | E38: =IF($A38<'Loan Input Parameters'!$B$16,C38*'Loan Input Parameters'!$B$15/12,"0.00") -> 3405.5702 | F38: =IF(A38<='Loan Input Parameters'!$B$16,'Loan Input Parameters'!$B$23,0) -> 69 | G38: =IF($A38<'Loan Input Parameters'!$B$16,D38-E38-F38,"0.00") -> 4456.9929 | H38: =IF($A38<'Loan Input Parameters'!$B$16,C38-G38,"0.00") -> 367059.75 | I38: =H38/'Loan Input Parameters'!$B$13 -> 0.73235088 | J38: =J37 -> 0.11 | K38: {=IF( AND(MONTH($B38)=1,SUMPRODUCT(--(MONTH($B$4:B38)=1))=1), K37*(1-22%*J38), IF( AND(MONTH($B38)=1,SUMPRODUCT(--(MONTH($B$4:B38)=1))=2), K37*(1-20%*J38), IF($A38<13,K37*(1-(J38*4%)), IF($A38<25,K37*(1-(J38*5%)),K37*(1-J38/12) ) ) ))} -> 317548.46 | L38: =IF(K38*'Loan Input Parameters'!$B$41<'Loan Input Parameters'!$B$42,'Loan Input Parameters'!$B$42,K38*'Loan Input Parameters'!$B$41) -> 0 | M38: =K38-L38 -> 317548.46 | N38: =H38-(K38-L38) -> 49511.298 | O38: =IF('Loan Input Parameters'!$B$8*3%<=4000,4000,IF('Loan Input Parameters'!$B$8*3%>=18000,18000,'Loan Input Parameters'!$B$8*3%)) -> 15000 | P38: =IF(N38<0,O38,N38+O38) -> 64511.298
A39: =A38+1 -> 36 | B39: =EOMONTH(B38,1) -> 46295 | C39: =IF(ROUND(H38,0)>0,H38,0) -> 367059.75 | D39: =IF(A39<'Loan Input Parameters'!$B$16,'Loan Input Parameters'!$B$24,IF(A39='Loan Input Parameters'!$B$16,'Loan Input Parameters'!$B$24+'Loan Input Parameters'!$B$20,0)) -> 7931.5631 | E39: =IF($A39<'Loan Input Parameters'!$B$16,C39*'Loan Input Parameters'!$B$15/12,"0.00") -> 3364.7144 | F39: =IF(A39<='Loan Input Parameters'!$B$16,'Loan Input Parameters'!$B$23,0) -> 69 | G39: =IF($A39<'Loan Input Parameters'!$B$16,D39-E39-F39,"0.00") -> 4497.8486 | H39: =IF($A39<'Loan Input Parameters'!$B$16,C39-G39,"0.00") -> 362561.9 | I39: =H39/'Loan Input Parameters'!$B$13 -> 0.72337685 | J39: =J38 -> 0.11 | K39: {=IF( AND(MONTH($B39)=1,SUMPRODUCT(--(MONTH($B$4:B39)=1))=1), K38*(1-22%*J39), IF( AND(MONTH($B39)=1,SUMPRODUCT(--(MONTH($B$4:B39)=1))=2), K38*(1-20%*J39), IF($A39<13,K38*(1-(J39*4%)), IF($A39<25,K38*(1-(J39*5%)),K38*(1-J39/12) ) ) ))} -> 314637.59 | L39: =IF(K39*'Loan Input Parameters'!$B$41<'Loan Input Parameters'!$B$42,'Loan Input Parameters'!$B$42,K39*'Loan Input Parameters'!$B$41) -> 0 | M39: =K39-L39 -> 314637.59 | N39: =H39-(K39-L39) -> 47924.31 | O39: =IF('Loan Input Parameters'!$B$8*3%<=4000,4000,IF('Loan Input Parameters'!$B$8*3%>=18000,18000,'Loan Input Parameters'!$B$8*3%)) -> 15000 | P39: =IF(N39<0,O39,N39+O39) -> 62924.31
A40: =A39+1 -> 37 | B40: =EOMONTH(B39,1) -> 46326 | C40: =IF(ROUND(H39,0)>0,H39,0) -> 362561.9 | D40: =IF(A40<'Loan Input Parameters'!$B$16,'Loan Input Parameters'!$B$24,IF(A40='Loan Input Parameters'!$B$16,'Loan Input Parameters'!$B$24+'Loan Input Parameters'!$B$20,0)) -> 7931.5631 | E40: =IF($A40<'Loan Input Parameters'!$B$16,C40*'Loan Input Parameters'!$B$15/12,"0.00") -> 3323.4841 | F40: =IF(A40<='Loan Input Parameters'!$B$16,'Loan Input Parameters'!$B$23,0) -> 69 | G40: =IF($A40<'Loan Input Parameters'!$B$16,D40-E40-F40,"0.00") -> 4539.0789 | H40: =IF($A40<'Loan Input Parameters'!$B$16,C40-G40,"0.00") -> 358022.83 | I40: =H40/'Loan Input Parameters'!$B$13 -> 0.71432057 | J40: =IF('Loan Input Parameters'!$B$32="Overide",'Loan Input Parameters'!$C$37,'Loan Input Parameters'!$B$37) -> 0.11 | K40: {=IF( AND(MONTH($B40)=1,SUMPRODUCT(--(MONTH($B$4:B40)=1))=1), K39*(1-22%*J40), IF( AND(MONTH($B40)=1,SUMPRODUCT(--(MONTH($B$4:B40)=1))=2), K39*(1-20%*J40), IF($A40<13,K39*(1-(J40*4%)), IF($A40<25,K39*(1-(J40*5%)),K39*(1-J40/12) ) ) ))} -> 311753.42 | L40: =IF(K40*'Loan Input Parameters'!$B$41<'Loan Input Parameters'!$B$42,'Loan Input Parameters'!$B$42,K40*'Loan Input Parameters'!$B$41) -> 0 | M40: =K40-L40 -> 311753.42 | N40: =H40-(K40-L40) -> 46269.409 | O40: =IF('Loan Input Parameters'!$B$8*3%<=4000,4000,IF('Loan Input Parameters'!$B$8*3%>=18000,18000,'Loan Input Parameters'!$B$8*3%)) -> 15000 | P40: =IF(N40<0,O40,N40+O40) -> 61269.409
A41: =A40+1 -> 38 | B41: =EOMONTH(B40,1) -> 46356 | C41: =IF(ROUND(H40,0)>0,H40,0) -> 358022.83 | D41: =IF(A41<'Loan Input Parameters'!$B$16,'Loan Input Parameters'!$B$24,IF(A41='Loan Input Parameters'!$B$16,'Loan Input Parameters'!$B$24+'Loan Input Parameters'!$B$20,0)) -> 7931.5631 | E41: =IF($A41<'Loan Input Parameters'!$B$16,C41*'Loan Input Parameters'!$B$15/12,"0.00") -> 3281.8759 | F41: =IF(A41<='Loan Input Parameters'!$B$16,'Loan Input Parameters'!$B$23,0) -> 69 | G41: =IF($A41<'Loan Input Parameters'!$B$16,D41-E41-F41,"0.00") -> 4580.6872 | H41: =IF($A41<'Loan Input Parameters'!$B$16,C41-G41,"0.00") -> 353442.14 | I41: =H41/'Loan Input Parameters'!$B$13 -> 0.70518126 | J41: =J40 -> 0.11 | K41: {=IF( AND(MONTH($B41)=1,SUMPRODUCT(--(MONTH($B$4:B41)=1))=1), K40*(1-22%*J41), IF( AND(MONTH($B41)=1,SUMPRODUCT(--(MONTH($B$4:B41)=1))=2), K40*(1-20%*J41), IF($A41<13,K40*(1-(J41*4%)), IF($A41<25,K40*(1-(J41*5%)),K40*(1-J41/12) ) ) ))} -> 308895.68 | L41: =IF(K41*'Loan Input Parameters'!$B$41<'Loan Input Parameters'!$B$42,'Loan Input Parameters'!$B$42,K41*'Loan Input Parameters'!$B$41) -> 0 | M41: =K41-L41 -> 308895.68 | N41: =H41-(K41-L41) -> 44546.462 | O41: =IF('Loan Input Parameters'!$B$8*3%<=4000,4000,IF('Loan Input Parameters'!$B$8*3%>=18000,18000,'Loan Input Parameters'!$B$8*3%)) -> 15000 | P41: =IF(N41<0,O41,N41+O41) -> 59546.462
A42: =A41+1 -> 39 | B42: =EOMONTH(B41,1) -> 46387 | C42: =IF(ROUND(H41,0)>0,H41,0) -> 353442.14 | D42: =IF(A42<'Loan Input Parameters'!$B$16,'Loan Input Parameters'!$B$24,IF(A42='Loan Input Parameters'!$B$16,'Loan Input Parameters'!$B$24+'Loan Input Parameters'!$B$20,0)) -> 7931.5631 | E42: =IF($A42<'Loan Input Parameters'!$B$16,C42*'Loan Input Parameters'!$B$15/12,"0.00") -> 3239.8863 | F42: =IF(A42<='Loan Input Parameters'!$B$16,'Loan Input Parameters'!$B$23,0) -> 69 | G42: =IF($A42<'Loan Input Parameters'!$B$16,D42-E42-F42,"0.00") -> 4622.6768 | H42: =IF($A42<'Loan Input Parameters'!$B$16,C42-G42,"0.00") -> 348819.46 | I42: =H42/'Loan Input Parameters'!$B$13 -> 0.69595818 | J42: =J41 -> 0.11 | K42: {=IF( AND(MONTH($B42)=1,SUMPRODUCT(--(MONTH($B$4:B42)=1))=1), K41*(1-22%*J42), IF( AND(MONTH($B42)=1,SUMPRODUCT(--(MONTH($B$4:B42)=1))=2), K41*(1-20%*J42), IF($A42<13,K41*(1-(J42*4%)), IF($A42<25,K41*(1-(J42*5%)),K41*(1-J42/12) ) ) ))} -> 306064.13 | L42: =IF(K42*'Loan Input Parameters'!$B$41<'Loan Input Parameters'!$B$42,'Loan Input Parameters'!$B$42,K42*'Loan Input Parameters'!$B$41) -> 0 | M42: =K42-L42 -> 306064.13 | N42: =H42-(K42-L42) -> 42755.329 | O42: =IF('Loan Input Parameters'!$B$8*3%<=4000,4000,IF('Loan Input Parameters'!$B$8*3%>=18000,18000,'Loan Input Parameters'!$B$8*3%)) -> 15000 | P42: =IF(N42<0,O42,N42+O42) -> 57755.329
A43: =A42+1 -> 40 | B43: =EOMONTH(B42,1) -> 46418 | C43: =IF(ROUND(H42,0)>0,H42,0) -> 348819.46 | D43: =IF(A43<'Loan Input Parameters'!$B$16,'Loan Input Parameters'!$B$24,IF(A43='Loan Input Parameters'!$B$16,'Loan Input Parameters'!$B$24+'Loan Input Parameters'!$B$20,0)) -> 7931.5631 | E43: =IF($A43<'Loan Input Parameters'!$B$16,C43*'Loan Input Parameters'!$B$15/12,"0.00") -> 3197.5117 | F43: =IF(A43<='Loan Input Parameters'!$B$16,'Loan Input Parameters'!$B$23,0) -> 69 | G43: =IF($A43<'Loan Input Parameters'!$B$16,D43-E43-F43,"0.00") -> 4665.0513 | H43: =IF($A43<'Loan Input Parameters'!$B$16,C43-G43,"0.00") -> 344154.41 | I43: =H43/'Loan Input Parameters'!$B$13 -> 0.68665056 | J43: =J42 -> 0.11 | K43: {=IF( AND(MONTH($B43)=1,SUMPRODUCT(--(MONTH($B$4:B43)=1))=1), K42*(1-22%*J43), IF( AND(MONTH($B43)=1,SUMPRODUCT(--(MONTH($B$4:B43)=1))=2), K42*(1-20%*J43), IF($A43<13,K42*(1-(J43*4%)), IF($A43<25,K42*(1-(J43*5%)),K42*(1-J43/12) ) ) ))} -> 303258.55 | L43: =IF(K43*'Loan Input Parameters'!$B$41<'Loan Input Parameters'!$B$42,'Loan Input Parameters'!$B$42,K43*'Loan Input Parameters'!$B$41) -> 0 | M43: =K43-L43 -> 303258.55 | N43: =H43-(K43-L43) -> 40895.865 | O43: =IF('Loan Input Parameters'!$B$8*3%<=4000,4000,IF('Loan Input Parameters'!$B$8*3%>=18000,18000,'Loan Input Parameters'!$B$8*3%)) -> 15000 | P43: =IF(N43<0,O43,N43+O43) -> 55895.865
A44: =A43+1 -> 41 | B44: =EOMONTH(B43,1) -> 46446 | C44: =IF(ROUND(H43,0)>0,H43,0) -> 344154.41 | D44: =IF(A44<'Loan Input Parameters'!$B$16,'Loan Input Parameters'!$B$24,IF(A44='Loan Input Parameters'!$B$16,'Loan Input Parameters'!$B$24+'Loan Input Parameters'!$B$20,0)) -> 7931.5631 | E44: =IF($A44<'Loan Input Parameters'!$B$16,C44*'Loan Input Parameters'!$B$15/12,"0.00") -> 3154.7488 | F44: =IF(A44<='Loan Input Parameters'!$B$16,'Loan Input Parameters'!$B$23,0) -> 69 | G44: =IF($A44<'Loan Input Parameters'!$B$16,D44-E44-F44,"0.00") -> 4707.8143 | H44: =IF($A44<'Loan Input Parameters'!$B$16,C44-G44,"0.00") -> 339446.6 | I44: =H44/'Loan Input Parameters'!$B$13 -> 0.67725762 | J44: =J43 -> 0.11 | K44: {=IF( AND(MONTH($B44)=1,SUMPRODUCT(--(MONTH($B$4:B44)=1))=1), K43*(1-22%*J44), IF( AND(MONTH($B44)=1,SUMPRODUCT(--(MONTH($B$4:B44)=1))=2), K43*(1-20%*J44), IF($A44<13,K43*(1-(J44*4%)), IF($A44<25,K43*(1-(J44*5%)),K43*(1-J44/12) ) ) ))} -> 300478.68 | L44: =IF(K44*'Loan Input Parameters'!$B$41<'Loan Input Parameters'!$B$42,'Loan Input Parameters'!$B$42,K44*'Loan Input Parameters'!$B$41) -> 0 | M44: =K44-L44 -> 300478.68 | N44: =H44-(K44-L44) -> 38967.921 | O44: =IF('Loan Input Parameters'!$B$8*3%<=4000,4000,IF('Loan Input Parameters'!$B$8*3%>=18000,18000,'Loan Input Parameters'!$B$8*3%)) -> 15000 | P44: =IF(N44<0,O44,N44+O44) -> 53967.921
A45: =A44+1 -> 42 | B45: =EOMONTH(B44,1) -> 46477 | C45: =IF(ROUND(H44,0)>0,H44,0) -> 339446.6 | D45: =IF(A45<'Loan Input Parameters'!$B$16,'Loan Input Parameters'!$B$24,IF(A45='Loan Input Parameters'!$B$16,'Loan Input Parameters'!$B$24+'Loan Input Parameters'!$B$20,0)) -> 7931.5631 | E45: =IF($A45<'Loan Input Parameters'!$B$16,C45*'Loan Input Parameters'!$B$15/12,"0.00") -> 3111.5938 | F45: =IF(A45<='Loan Input Parameters'!$B$16,'Loan Input Parameters'!$B$23,0) -> 69 | G45: =IF($A45<'Loan Input Parameters'!$B$16,D45-E45-F45,"0.00") -> 4750.9693 | H45: =IF($A45<'Loan Input Parameters'!$B$16,C45-G45,"0.00") -> 334695.63 | I45: =H45/'Loan Input Parameters'!$B$13 -> 0.66777857 | J45: =J44 -> 0.11 | K45: {=IF( AND(MONTH($B45)=1,SUMPRODUCT(--(MONTH($B$4:B45)=1))=1), K44*(1-22%*J45), IF( AND(MONTH($B45)=1,SUMPRODUCT(--(MONTH($B$4:B45)=1))=2), K44*(1-20%*J45), IF($A45<13,K44*(1-(J45*4%)), IF($A45<25,K44*(1-(J45*5%)),K44*(1-J45/12) ) ) ))} -> 297724.29 | L45: =IF(K45*'Loan Input Parameters'!$B$41<'Loan Input Parameters'!$B$42,'Loan Input Parameters'!$B$42,K45*'Loan Input Parameters'!$B$41) -> 0 | M45: =K45-L45 -> 297724.29 | N45: =H45-(K45-L45) -> 36971.339 | O45: =IF('Loan Input Parameters'!$B$8*3%<=4000,4000,IF('Loan Input Parameters'!$B$8*3%>=18000,18000,'Loan Input Parameters'!$B$8*3%)) -> 15000 | P45: =IF(N45<0,O45,N45+O45) -> 51971.339
A46: =A45+1 -> 43 | B46: =EOMONTH(B45,1) -> 46507 | C46: =IF(ROUND(H45,0)>0,H45,0) -> 334695.63 | D46: =IF(A46<'Loan Input Parameters'!$B$16,'Loan Input Parameters'!$B$24,IF(A46='Loan Input Parameters'!$B$16,'Loan Input Parameters'!$B$24+'Loan Input Parameters'!$B$20,0)) -> 7931.5631 | E46: =IF($A46<'Loan Input Parameters'!$B$16,C46*'Loan Input Parameters'!$B$15/12,"0.00") -> 3068.0432 | F46: =IF(A46<='Loan Input Parameters'!$B$16,'Loan Input Parameters'!$B$23,0) -> 69 | G46: =IF($A46<'Loan Input Parameters'!$B$16,D46-E46-F46,"0.00") -> 4794.5198 | H46: =IF($A46<'Loan Input Parameters'!$B$16,C46-G46,"0.00") -> 329901.11 | I46: =H46/'Loan Input Parameters'!$B$13 -> 0.65821263 | J46: =J45 -> 0.11 | K46: {=IF( AND(MONTH($B46)=1,SUMPRODUCT(--(MONTH($B$4:B46)=1))=1), K45*(1-22%*J46), IF( AND(MONTH($B46)=1,SUMPRODUCT(--(MONTH($B$4:B46)=1))=2), K45*(1-20%*J46), IF($A46<13,K45*(1-(J46*4%)), IF($A46<25,K45*(1-(J46*5%)),K45*(1-J46/12) ) ) ))} -> 294995.15 | L46: =IF(K46*'Loan Input Parameters'!$B$41<'Loan Input Parameters'!$B$42,'Loan Input Parameters'!$B$42,K46*'Loan Input Parameters'!$B$41) -> 0 | M46: =K46-L46 -> 294995.15 | N46: =H46-(K46-L46) -> 34905.959 | O46: =IF('Loan Input Parameters'!$B$8*3%<=4000,4000,IF('Loan Input Parameters'!$B$8*3%>=18000,18000,'Loan Input Parameters'!$B$8*3%)) -> 15000 | P46: =IF(N46<0,O46,N46+O46) -> 49905.959
A47: =A46+1 -> 44 | B47: =EOMONTH(B46,1) -> 46538 | C47: =IF(ROUND(H46,0)>0,H46,0) -> 329901.11 | D47: =IF(A47<'Loan Input Parameters'!$B$16,'Loan Input Parameters'!$B$24,IF(A47='Loan Input Parameters'!$B$16,'Loan Input Parameters'!$B$24+'Loan Input Parameters'!$B$20,0)) -> 7931.5631 | E47: =IF($A47<'Loan Input Parameters'!$B$16,C47*'Loan Input Parameters'!$B$15/12,"0.00") -> 3024.0935 | F47: =IF(A47<='Loan Input Parameters'!$B$16,'Loan Input Parameters'!$B$23,0) -> 69 | G47: =IF($A47<'Loan Input Parameters'!$B$16,D47-E47-F47,"0.00") -> 4838.4696 | H47: =IF($A47<'Loan Input Parameters'!$B$16,C47-G47,"0.00") -> 325062.64 | I47: =H47/'Loan Input Parameters'!$B$13 -> 0.648559 | J47: =J46 -> 0.11 | K47: {=IF( AND(MONTH($B47)=1,SUMPRODUCT(--(MONTH($B$4:B47)=1))=1), K46*(1-22%*J47), IF( AND(MONTH($B47)=1,SUMPRODUCT(--(MONTH($B$4:B47)=1))=2), K46*(1-20%*J47), IF($A47<13,K46*(1-(J47*4%)), IF($A47<25,K46*(1-(J47*5%)),K46*(1-J47/12) ) ) ))} -> 292291.03 | L47: =IF(K47*'Loan Input Parameters'!$B$41<'Loan Input Parameters'!$B$42,'Loan Input Parameters'!$B$42,K47*'Loan Input Parameters'!$B$41) -> 0 | M47: =K47-L47 -> 292291.03 | N47: =H47-(K47-L47) -> 32771.612 | O47: =IF('Loan Input Parameters'!$B$8*3%<=4000,4000,IF('Loan Input Parameters'!$B$8*3%>=18000,18000,'Loan Input Parameters'!$B$8*3%)) -> 15000 | P47: =IF(N47<0,O47,N47+O47) -> 47771.612
A48: =A47+1 -> 45 | B48: =EOMONTH(B47,1) -> 46568 | C48: =IF(ROUND(H47,0)>0,H47,0) -> 325062.64 | D48: =IF(A48<'Loan Input Parameters'!$B$16,'Loan Input Parameters'!$B$24,IF(A48='Loan Input Parameters'!$B$16,'Loan Input Parameters'!$B$24+'Loan Input Parameters'!$B$20,0)) -> 7931.5631 | E48: =IF($A48<'Loan Input Parameters'!$B$16,C48*'Loan Input Parameters'!$B$15/12,"0.00") -> 2979.7408 | F48: =IF(A48<='Loan Input Parameters'!$B$16,'Loan Input Parameters'!$B$23,0) -> 69 | G48: =IF($A48<'Loan Input Parameters'!$B$16,D48-E48-F48,"0.00") -> 4882.8222 | H48: =IF($A48<'Loan Input Parameters'!$B$16,C48-G48,"0.00") -> 320179.82 | I48: =H48/'Loan Input Parameters'!$B$13 -> 0.63881689 | J48: =J47 -> 0.11 | K48: {=IF( AND(MONTH($B48)=1,SUMPRODUCT(--(MONTH($B$4:B48)=1))=1), K47*(1-22%*J48), IF( AND(MONTH($B48)=1,SUMPRODUCT(--(MONTH($B$4:B48)=1))=2), K47*(1-20%*J48), IF($A48<13,K47*(1-(J48*4%)), IF($A48<25,K47*(1-(J48*5%)),K47*(1-J48/12) ) ) ))} -> 289611.69 | L48: =IF(K48*'Loan Input Parameters'!$B$41<'Loan Input Parameters'!$B$42,'Loan Input Parameters'!$B$42,K48*'Loan Input Parameters'!$B$41) -> 0 | M48: =K48-L48 -> 289611.69 | N48: =H48-(K48-L48) -> 30568.124 | O48: =IF('Loan Input Parameters'!$B$8*3%<=4000,4000,IF('Loan Input Parameters'!$B$8*3%>=18000,18000,'Loan Input Parameters'!$B$8*3%)) -> 15000 | P48: =IF(N48<0,O48,N48+O48) -> 45568.124
A49: =A48+1 -> 46 | B49: =EOMONTH(B48,1) -> 46599 | C49: =IF(ROUND(H48,0)>0,H48,0) -> 320179.82 | D49: =IF(A49<'Loan Input Parameters'!$B$16,'Loan Input Parameters'!$B$24,IF(A49='Loan Input Parameters'!$B$16,'Loan Input Parameters'!$B$24+'Loan Input Parameters'!$B$20,0)) -> 7931.5631 | E49: =IF($A49<'Loan Input Parameters'!$B$16,C49*'Loan Input Parameters'!$B$15/12,"0.00") -> 2934.9816 | F49: =IF(A49<='Loan Input Parameters'!$B$16,'Loan Input Parameters'!$B$23,0) -> 69 | G49: =IF($A49<'Loan Input Parameters'!$B$16,D49-E49-F49,"0.00") -> 4927.5814 | H49: =IF($A49<'Loan Input Parameters'!$B$16,C49-G49,"0.00") -> 315252.23 | I49: =H49/'Loan Input Parameters'!$B$13 -> 0.62898547 | J49: =J48 -> 0.11 | K49: {=IF( AND(MONTH($B49)=1,SUMPRODUCT(--(MONTH($B$4:B49)=1))=1), K48*(1-22%*J49), IF( AND(MONTH($B49)=1,SUMPRODUCT(--(MONTH($B$4:B49)=1))=2), K48*(1-20%*J49), IF($A49<13,K48*(1-(J49*4%)), IF($A49<25,K48*(1-(J49*5%)),K48*(1-J49/12) ) ) ))} -> 286956.92 | L49: =IF(K49*'Loan Input Parameters'!$B$41<'Loan Input Parameters'!$B$42,'Loan Input Parameters'!$B$42,K49*'Loan Input Parameters'!$B$41) -> 0 | M49: =K49-L49 -> 286956.92 | N49: =H49-(K49-L49) -> 28295.316 | O49: =IF('Loan Input Parameters'!$B$8*3%<=4000,4000,IF('Loan Input Parameters'!$B$8*3%>=18000,18000,'Loan Input Parameters'!$B$8*3%)) -> 15000 | P49: =IF(N49<0,O49,N49+O49) -> 43295.316
A50: =A49+1 -> 47 | B50: =EOMONTH(B49,1) -> 46630 | C50: =IF(ROUND(H49,0)>0,H49,0) -> 315252.23 | D50: =IF(A50<'Loan Input Parameters'!$B$16,'Loan Input Parameters'!$B$24,IF(A50='Loan Input Parameters'!$B$16,'Loan Input Parameters'!$B$24+'Loan Input Parameters'!$B$20,0)) -> 7931.5631 | E50: =IF($A50<'Loan Input Parameters'!$B$16,C50*'Loan Input Parameters'!$B$15/12,"0.00") -> 2889.8121 | F50: =IF(A50<='Loan Input Parameters'!$B$16,'Loan Input Parameters'!$B$23,0) -> 69 | G50: =IF($A50<'Loan Input Parameters'!$B$16,D50-E50-F50,"0.00") -> 4972.7509 | H50: =IF($A50<'Loan Input Parameters'!$B$16,C50-G50,"0.00") -> 310279.48 | I50: =H50/'Loan Input Parameters'!$B$13 -> 0.61906393 | J50: =J49 -> 0.11 | K50: {=IF( AND(MONTH($B50)=1,SUMPRODUCT(--(MONTH($B$4:B50)=1))=1), K49*(1-22%*J50), IF( AND(MONTH($B50)=1,SUMPRODUCT(--(MONTH($B$4:B50)=1))=2), K49*(1-20%*J50), IF($A50<13,K49*(1-(J50*4%)), IF($A50<25,K49*(1-(J50*5%)),K49*(1-J50/12) ) ) ))} -> 284326.48 | L50: =IF(K50*'Loan Input Parameters'!$B$41<'Loan Input Parameters'!$B$42,'Loan Input Parameters'!$B$42,K50*'Loan Input Parameters'!$B$41) -> 0 | M50: =K50-L50 -> 284326.48 | N50: =H50-(K50-L50) -> 25953.004 | O50: =IF('Loan Input Parameters'!$B$8*3%<=4000,4000,IF('Loan Input Parameters'!$B$8*3%>=18000,18000,'Loan Input Parameters'!$B$8*3%)) -> 15000 | P50: =IF(N50<0,O50,N50+O50) -> 40953.004
A51: =A50+1 -> 48 | B51: =EOMONTH(B50,1) -> 46660 | C51: =IF(ROUND(H50,0)>0,H50,0) -> 310279.48 | D51: =IF(A51<'Loan Input Parameters'!$B$16,'Loan Input Parameters'!$B$24,IF(A51='Loan Input Parameters'!$B$16,'Loan Input Parameters'!$B$24+'Loan Input Parameters'!$B$20,0)) -> 7931.5631 | E51: =IF($A51<'Loan Input Parameters'!$B$16,C51*'Loan Input Parameters'!$B$15/12,"0.00") -> 2844.2286 | F51: =IF(A51<='Loan Input Parameters'!$B$16,'Loan Input Parameters'!$B$23,0) -> 69 | G51: =IF($A51<'Loan Input Parameters'!$B$16,D51-E51-F51,"0.00") -> 5018.3345 | H51: =IF($A51<'Loan Input Parameters'!$B$16,C51-G51,"0.00") -> 305261.15 | I51: =H51/'Loan Input Parameters'!$B$13 -> 0.60905144 | J51: =J50 -> 0.11 | K51: {=IF( AND(MONTH($B51)=1,SUMPRODUCT(--(MONTH($B$4:B51)=1))=1), K50*(1-22%*J51), IF( AND(MONTH($B51)=1,SUMPRODUCT(--(MONTH($B$4:B51)=1))=2), K50*(1-20%*J51), IF($A51<13,K50*(1-(J51*4%)), IF($A51<25,K50*(1-(J51*5%)),K50*(1-J51/12) ) ) ))} -> 281720.15 | L51: =IF(K51*'Loan Input Parameters'!$B$41<'Loan Input Parameters'!$B$42,'Loan Input Parameters'!$B$42,K51*'Loan Input Parameters'!$B$41) -> 0 | M51: =K51-L51 -> 281720.15 | N51: =H51-(K51-L51) -> 23540.995 | O51: =IF('Loan Input Parameters'!$B$8*3%<=4000,4000,IF('Loan Input Parameters'!$B$8*3%>=18000,18000,'Loan Input Parameters'!$B$8*3%)) -> 15000 | P51: =IF(N51<0,O51,N51+O51) -> 38540.995
A52: =A51+1 -> 49 | B52: =EOMONTH(B51,1) -> 46691 | C52: =IF(ROUND(H51,0)>0,H51,0) -> 305261.15 | D52: =IF(A52<'Loan Input Parameters'!$B$16,'Loan Input Parameters'!$B$24,IF(A52='Loan Input Parameters'!$B$16,'Loan Input Parameters'!$B$24+'Loan Input Parameters'!$B$20,0)) -> 7931.5631 | E52: =IF($A52<'Loan Input Parameters'!$B$16,C52*'Loan Input Parameters'!$B$15/12,"0.00") -> 2798.2272 | F52: =IF(A52<='Loan Input Parameters'!$B$16,'Loan Input Parameters'!$B$23,0) -> 69 | G52: =IF($A52<'Loan Input Parameters'!$B$16,D52-E52-F52,"0.00") -> 5064.3359 | H52: =IF($A52<'Loan Input Parameters'!$B$16,C52-G52,"0.00") -> 300196.81 | I52: =H52/'Loan Input Parameters'!$B$13 -> 0.59894717 | J52: =IF('Loan Input Parameters'!$B$32="Overide",'Loan Input Parameters'!$C$38,'Loan Input Parameters'!$B$38) -> 0.11 | K52: {=IF( AND(MONTH($B52)=1,SUMPRODUCT(--(MONTH($B$4:B52)=1))=1), K51*(1-22%*J52), IF( AND(MONTH($B52)=1,SUMPRODUCT(--(MONTH($B$4:B52)=1))=2), K51*(1-20%*J52), IF($A52<13,K51*(1-(J52*4%)), IF($A52<25,K51*(1-(J52*5%)),K51*(1-J52/12) ) ) ))} -> 279137.72 | L52: =IF(K52*'Loan Input Parameters'!$B$41<'Loan Input Parameters'!$B$42,'Loan Input Parameters'!$B$42,K52*'Loan Input Parameters'!$B$41) -> 0 | M52: =K52-L52 -> 279137.72 | N52: =H52-(K52-L52) -> 21059.094 | O52: =IF('Loan Input Parameters'!$B$8*3%<=4000,4000,IF('Loan Input Parameters'!$B$8*3%>=18000,18000,'Loan Input Parameters'!$B$8*3%)) -> 15000 | P52: =IF(N52<0,O52,N52+O52) -> 36059.094
A53: =A52+1 -> 50 | B53: =EOMONTH(B52,1) -> 46721 | C53: =IF(ROUND(H52,0)>0,H52,0) -> 300196.81 | D53: =IF(A53<'Loan Input Parameters'!$B$16,'Loan Input Parameters'!$B$24,IF(A53='Loan Input Parameters'!$B$16,'Loan Input Parameters'!$B$24+'Loan Input Parameters'!$B$20,0)) -> 7931.5631 | E53: =IF($A53<'Loan Input Parameters'!$B$16,C53*'Loan Input Parameters'!$B$15/12,"0.00") -> 2751.8041 | F53: =IF(A53<='Loan Input Parameters'!$B$16,'Loan Input Parameters'!$B$23,0) -> 69 | G53: =IF($A53<'Loan Input Parameters'!$B$16,D53-E53-F53,"0.00") -> 5110.7589 | H53: =IF($A53<'Loan Input Parameters'!$B$16,C53-G53,"0.00") -> 295086.05 | I53: =H53/'Loan Input Parameters'!$B$13 -> 0.58875028 | J53: =J52 -> 0.11 | K53: {=IF( AND(MONTH($B53)=1,SUMPRODUCT(--(MONTH($B$4:B53)=1))=1), K52*(1-22%*J53), IF( AND(MONTH($B53)=1,SUMPRODUCT(--(MONTH($B$4:B53)=1))=2), K52*(1-20%*J53), IF($A53<13,K52*(1-(J53*4%)), IF($A53<25,K52*(1-(J53*5%)),K52*(1-J53/12) ) ) ))} -> 276578.96 | L53: =IF(K53*'Loan Input Parameters'!$B$41<'Loan Input Parameters'!$B$42,'Loan Input Parameters'!$B$42,K53*'Loan Input Parameters'!$B$41) -> 0 | M53: =K53-L53 -> 276578.96 | N53: =H53-(K53-L53) -> 18507.098 | O53: =IF('Loan Input Parameters'!$B$8*3%<=4000,4000,IF('Loan Input Parameters'!$B$8*3%>=18000,18000,'Loan Input Parameters'!$B$8*3%)) -> 15000 | P53: =IF(N53<0,O53,N53+O53) -> 33507.098
A54: =A53+1 -> 51 | B54: =EOMONTH(B53,1) -> 46752 | C54: =IF(ROUND(H53,0)>0,H53,0) -> 295086.05 | D54: =IF(A54<'Loan Input Parameters'!$B$16,'Loan Input Parameters'!$B$24,IF(A54='Loan Input Parameters'!$B$16,'Loan Input Parameters'!$B$24+'Loan Input Parameters'!$B$20,0)) -> 7931.5631 | E54: =IF($A54<'Loan Input Parameters'!$B$16,C54*'Loan Input Parameters'!$B$15/12,"0.00") -> 2704.9555 | F54: =IF(A54<='Loan Input Parameters'!$B$16,'Loan Input Parameters'!$B$23,0) -> 69 | G54: =IF($A54<'Loan Input Parameters'!$B$16,D54-E54-F54,"0.00") -> 5157.6076 | H54: =IF($A54<'Loan Input Parameters'!$B$16,C54-G54,"0.00") -> 289928.45 | I54: =H54/'Loan Input Parameters'!$B$13 -> 0.57845991 | J54: =J53 -> 0.11 | K54: {=IF( AND(MONTH($B54)=1,SUMPRODUCT(--(MONTH($B$4:B54)=1))=1), K53*(1-22%*J54), IF( AND(MONTH($B54)=1,SUMPRODUCT(--(MONTH($B$4:B54)=1))=2), K53*(1-20%*J54), IF($A54<13,K53*(1-(J54*4%)), IF($A54<25,K53*(1-(J54*5%)),K53*(1-J54/12) ) ) ))} -> 274043.65 | L54: =IF(K54*'Loan Input Parameters'!$B$41<'Loan Input Parameters'!$B$42,'Loan Input Parameters'!$B$42,K54*'Loan Input Parameters'!$B$41) -> 0 | M54: =K54-L54 -> 274043.65 | N54: =H54-(K54-L54) -> 15884.797 | O54: =IF('Loan Input Parameters'!$B$8*3%<=4000,4000,IF('Loan Input Parameters'!$B$8*3%>=18000,18000,'Loan Input Parameters'!$B$8*3%)) -> 15000 | P54: =IF(N54<0,O54,N54+O54) -> 30884.797
A55: =A54+1 -> 52 | B55: =EOMONTH(B54,1) -> 46783 | C55: =IF(ROUND(H54,0)>0,H54,0) -> 289928.45 | D55: =IF(A55<'Loan Input Parameters'!$B$16,'Loan Input Parameters'!$B$24,IF(A55='Loan Input Parameters'!$B$16,'Loan Input Parameters'!$B$24+'Loan Input Parameters'!$B$20,0)) -> 7931.5631 | E55: =IF($A55<'Loan Input Parameters'!$B$16,C55*'Loan Input Parameters'!$B$15/12,"0.00") -> 2657.6774 | F55: =IF(A55<='Loan Input Parameters'!$B$16,'Loan Input Parameters'!$B$23,0) -> 69 | G55: =IF($A55<'Loan Input Parameters'!$B$16,D55-E55-F55,"0.00") -> 5204.8856 | H55: =IF($A55<'Loan Input Parameters'!$B$16,C55-G55,"0.00") -> 284723.56 | I55: =H55/'Loan Input Parameters'!$B$13 -> 0.56807522 | J55: =J54 -> 0.11 | K55: {=IF( AND(MONTH($B55)=1,SUMPRODUCT(--(MONTH($B$4:B55)=1))=1), K54*(1-22%*J55), IF( AND(MONTH($B55)=1,SUMPRODUCT(--(MONTH($B$4:B55)=1))=2), K54*(1-20%*J55), IF($A55<13,K54*(1-(J55*4%)), IF($A55<25,K54*(1-(J55*5%)),K54*(1-J55/12) ) ) ))} -> 271531.58 | L55: =IF(K55*'Loan Input Parameters'!$B$41<'Loan Input Parameters'!$B$42,'Loan Input Parameters'!$B$42,K55*'Loan Input Parameters'!$B$41) -> 0 | M55: =K55-L55 -> 271531.58 | N55: =H55-(K55-L55) -> 13191.978 | O55: =IF('Loan Input Parameters'!$B$8*3%<=4000,4000,IF('Loan Input Parameters'!$B$8*3%>=18000,18000,'Loan Input Parameters'!$B$8*3%)) -> 15000 | P55: =IF(N55<0,O55,N55+O55) -> 28191.978
A56: =A55+1 -> 53 | B56: =EOMONTH(B55,1) -> 46812 | C56: =IF(ROUND(H55,0)>0,H55,0) -> 284723.56 | D56: =IF(A56<'Loan Input Parameters'!$B$16,'Loan Input Parameters'!$B$24,IF(A56='Loan Input Parameters'!$B$16,'Loan Input Parameters'!$B$24+'Loan Input Parameters'!$B$20,0)) -> 7931.5631 | E56: =IF($A56<'Loan Input Parameters'!$B$16,C56*'Loan Input Parameters'!$B$15/12,"0.00") -> 2609.966 | F56: =IF(A56<='Loan Input Parameters'!$B$16,'Loan Input Parameters'!$B$23,0) -> 69 | G56: =IF($A56<'Loan Input Parameters'!$B$16,D56-E56-F56,"0.00") -> 5252.5971 | H56: =IF($A56<'Loan Input Parameters'!$B$16,C56-G56,"0.00") -> 279470.96 | I56: =H56/'Loan Input Parameters'!$B$13 -> 0.55759533 | J56: =J55 -> 0.11 | K56: {=IF( AND(MONTH($B56)=1,SUMPRODUCT(--(MONTH($B$4:B56)=1))=1), K55*(1-22%*J56), IF( AND(MONTH($B56)=1,SUMPRODUCT(--(MONTH($B$4:B56)=1))=2), K55*(1-20%*J56), IF($A56<13,K55*(1-(J56*4%)), IF($A56<25,K55*(1-(J56*5%)),K55*(1-J56/12) ) ) ))} -> 269042.54 | L56: =IF(K56*'Loan Input Parameters'!$B$41<'Loan Input Parameters'!$B$42,'Loan Input Parameters'!$B$42,K56*'Loan Input Parameters'!$B$41) -> 0 | M56: =K56-L56 -> 269042.54 | N56: =H56-(K56-L56) -> 10428.421 | O56: =IF('Loan Input Parameters'!$B$8*3%<=4000,4000,IF('Loan Input Parameters'!$B$8*3%>=18000,18000,'Loan Input Parameters'!$B$8*3%)) -> 15000 | P56: =IF(N56<0,O56,N56+O56) -> 25428.421
A57: =A56+1 -> 54 | B57: =EOMONTH(B56,1) -> 46843 | C57: =IF(ROUND(H56,0)>0,H56,0) -> 279470.96 | D57: =IF(A57<'Loan Input Parameters'!$B$16,'Loan Input Parameters'!$B$24,IF(A57='Loan Input Parameters'!$B$16,'Loan Input Parameters'!$B$24+'Loan Input Parameters'!$B$20,0)) -> 7931.5631 | E57: =IF($A57<'Loan Input Parameters'!$B$16,C57*'Loan Input Parameters'!$B$15/12,"0.00") -> 2561.8172 | F57: =IF(A57<='Loan Input Parameters'!$B$16,'Loan Input Parameters'!$B$23,0) -> 69 | G57: =IF($A57<'Loan Input Parameters'!$B$16,D57-E57-F57,"0.00") -> 5300.7459 | H57: =IF($A57<'Loan Input Parameters'!$B$16,C57-G57,"0.00") -> 274170.22 | I57: =H57/'Loan Input Parameters'!$B$13 -> 0.54701938 | J57: =J56 -> 0.11 | K57: {=IF( AND(MONTH($B57)=1,SUMPRODUCT(--(MONTH($B$4:B57)=1))=1), K56*(1-22%*J57), IF( AND(MONTH($B57)=1,SUMPRODUCT(--(MONTH($B$4:B57)=1))=2), K56*(1-20%*J57), IF($A57<13,K56*(1-(J57*4%)), IF($A57<25,K56*(1-(J57*5%)),K56*(1-J57/12) ) ) ))} -> 266576.32 | L57: =IF(K57*'Loan Input Parameters'!$B$41<'Loan Input Parameters'!$B$42,'Loan Input Parameters'!$B$42,K57*'Loan Input Parameters'!$B$41) -> 0 | M57: =K57-L57 -> 266576.32 | N57: =H57-(K57-L57) -> 7593.8982 | O57: =IF('Loan Input Parameters'!$B$8*3%<=4000,4000,IF('Loan Input Parameters'!$B$8*3%>=18000,18000,'Loan Input Parameters'!$B$8*3%)) -> 15000 | P57: =IF(N57<0,O57,N57+O57) -> 22593.898
A58: =A57+1 -> 55 | B58: =EOMONTH(B57,1) -> 46873 | C58: =IF(ROUND(H57,0)>0,H57,0) -> 274170.22 | D58: =IF(A58<'Loan Input Parameters'!$B$16,'Loan Input Parameters'!$B$24,IF(A58='Loan Input Parameters'!$B$16,'Loan Input Parameters'!$B$24+'Loan Input Parameters'!$B$20,0)) -> 7931.5631 | E58: =IF($A58<'Loan Input Parameters'!$B$16,C58*'Loan Input Parameters'!$B$15/12,"0.00") -> 2513.227 | F58: =IF(A58<='Loan Input Parameters'!$B$16,'Loan Input Parameters'!$B$23,0) -> 69 | G58: =IF($A58<'Loan Input Parameters'!$B$16,D58-E58-F58,"0.00") -> 5349.3361 | H58: =IF($A58<'Loan Input Parameters'!$B$16,C58-G58,"0.00") -> 268820.88 | I58: =H58/'Loan Input Parameters'!$B$13 -> 0.53634649 | J58: =J57 -> 0.11 | K58: {=IF( AND(MONTH($B58)=1,SUMPRODUCT(--(MONTH($B$4:B58)=1))=1), K57*(1-22%*J58), IF( AND(MONTH($B58)=1,SUMPRODUCT(--(MONTH($B$4:B58)=1))=2), K57*(1-20%*J58), IF($A58<13,K57*(1-(J58*4%)), IF($A58<25,K57*(1-(J58*5%)),K57*(1-J58/12) ) ) ))} -> 264132.7 | L58: =IF(K58*'Loan Input Parameters'!$B$41<'Loan Input Parameters'!$B$42,'Loan Input Parameters'!$B$42,K58*'Loan Input Parameters'!$B$41) -> 0 | M58: =K58-L58 -> 264132.7 | N58: =H58-(K58-L58) -> 4688.1784 | O58: =IF('Loan Input Parameters'!$B$8*3%<=4000,4000,IF('Loan Input Parameters'!$B$8*3%>=18000,18000,'Loan Input Parameters'!$B$8*3%)) -> 15000 | P58: =IF(N58<0,O58,N58+O58) -> 19688.178
A59: =A58+1 -> 56 | B59: =EOMONTH(B58,1) -> 46904 | C59: =IF(ROUND(H58,0)>0,H58,0) -> 268820.88 | D59: =IF(A59<'Loan Input Parameters'!$B$16,'Loan Input Parameters'!$B$24,IF(A59='Loan Input Parameters'!$B$16,'Loan Input Parameters'!$B$24+'Loan Input Parameters'!$B$20,0)) -> 7931.5631 | E59: =IF($A59<'Loan Input Parameters'!$B$16,C59*'Loan Input Parameters'!$B$15/12,"0.00") -> 2464.1914 | F59: =IF(A59<='Loan Input Parameters'!$B$16,'Loan Input Parameters'!$B$23,0) -> 69 | G59: =IF($A59<'Loan Input Parameters'!$B$16,D59-E59-F59,"0.00") -> 5398.3716 | H59: =IF($A59<'Loan Input Parameters'!$B$16,C59-G59,"0.00") -> 263422.51 | I59: =H59/'Loan Input Parameters'!$B$13 -> 0.52557575 | J59: =J58 -> 0.11 | K59: {=IF( AND(MONTH($B59)=1,SUMPRODUCT(--(MONTH($B$4:B59)=1))=1), K58*(1-22%*J59), IF( AND(MONTH($B59)=1,SUMPRODUCT(--(MONTH($B$4:B59)=1))=2), K58*(1-20%*J59), IF($A59<13,K58*(1-(J59*4%)), IF($A59<25,K58*(1-(J59*5%)),K58*(1-J59/12) ) ) ))} -> 261711.49 | L59: =IF(K59*'Loan Input Parameters'!$B$41<'Loan Input Parameters'!$B$42,'Loan Input Parameters'!$B$42,K59*'Loan Input Parameters'!$B$41) -> 0 | M59: =K59-L59 -> 261711.49 | N59: =H59-(K59-L59) -> 1711.0232 | O59: =IF('Loan Input Parameters'!$B$8*3%<=4000,4000,IF('Loan Input Parameters'!$B$8*3%>=18000,18000,'Loan Input Parameters'!$B$8*3%)) -> 15000 | P59: =IF(N59<0,O59,N59+O59) -> 16711.023
A60: =A59+1 -> 57 | B60: =EOMONTH(B59,1) -> 46934 | C60: =IF(ROUND(H59,0)>0,H59,0) -> 263422.51 | D60: =IF(A60<'Loan Input Parameters'!$B$16,'Loan Input Parameters'!$B$24,IF(A60='Loan Input Parameters'!$B$16,'Loan Input Parameters'!$B$24+'Loan Input Parameters'!$B$20,0)) -> 7931.5631 | E60: =IF($A60<'Loan Input Parameters'!$B$16,C60*'Loan Input Parameters'!$B$15/12,"0.00") -> 2414.7063 | F60: =IF(A60<='Loan Input Parameters'!$B$16,'Loan Input Parameters'!$B$23,0) -> 69 | G60: =IF($A60<'Loan Input Parameters'!$B$16,D60-E60-F60,"0.00") -> 5447.8567 | H60: =IF($A60<'Loan Input Parameters'!$B$16,C60-G60,"0.00") -> 257974.65 | I60: =H60/'Loan Input Parameters'!$B$13 -> 0.51470629 | J60: =J59 -> 0.11 | K60: {=IF( AND(MONTH($B60)=1,SUMPRODUCT(--(MONTH($B$4:B60)=1))=1), K59*(1-22%*J60), IF( AND(MONTH($B60)=1,SUMPRODUCT(--(MONTH($B$4:B60)=1))=2), K59*(1-20%*J60), IF($A60<13,K59*(1-(J60*4%)), IF($A60<25,K59*(1-(J60*5%)),K59*(1-J60/12) ) ) ))} -> 259312.46 | L60: =IF(K60*'Loan Input Parameters'!$B$41<'Loan Input Parameters'!$B$42,'Loan Input Parameters'!$B$42,K60*'Loan Input Parameters'!$B$41) -> 0 | M60: =K60-L60 -> 259312.46 | N60: =H60-(K60-L60) -> -1337.8116 | O60: =IF('Loan Input Parameters'!$B$8*3%<=4000,4000,IF('Loan Input Parameters'!$B$8*3%>=18000,18000,'Loan Input Parameters'!$B$8*3%)) -> 15000 | P60: =IF(N60<0,O60,N60+O60) -> 15000
A61: =A60+1 -> 58 | B61: =EOMONTH(B60,1) -> 46965 | C61: =IF(ROUND(H60,0)>0,H60,0) -> 257974.65 | D61: =IF(A61<'Loan Input Parameters'!$B$16,'Loan Input Parameters'!$B$24,IF(A61='Loan Input Parameters'!$B$16,'Loan Input Parameters'!$B$24+'Loan Input Parameters'!$B$20,0)) -> 7931.5631 | E61: =IF($A61<'Loan Input Parameters'!$B$16,C61*'Loan Input Parameters'!$B$15/12,"0.00") -> 2364.7677 | F61: =IF(A61<='Loan Input Parameters'!$B$16,'Loan Input Parameters'!$B$23,0) -> 69 | G61: =IF($A61<'Loan Input Parameters'!$B$16,D61-E61-F61,"0.00") -> 5497.7954 | H61: =IF($A61<'Loan Input Parameters'!$B$16,C61-G61,"0.00") -> 252476.86 | I61: =H61/'Loan Input Parameters'!$B$13 -> 0.50373719 | J61: =J60 -> 0.11 | K61: {=IF( AND(MONTH($B61)=1,SUMPRODUCT(--(MONTH($B$4:B61)=1))=1), K60*(1-22%*J61), IF( AND(MONTH($B61)=1,SUMPRODUCT(--(MONTH($B$4:B61)=1))=2), K60*(1-20%*J61), IF($A61<13,K60*(1-(J61*4%)), IF($A61<25,K60*(1-(J61*5%)),K60*(1-J61/12) ) ) ))} -> 256935.43 | L61: =IF(K61*'Loan Input Parameters'!$B$41<'Loan Input Parameters'!$B$42,'Loan Input Parameters'!$B$42,K61*'Loan Input Parameters'!$B$41) -> 0 | M61: =K61-L61 -> 256935.43 | N61: =H61-(K61-L61) -> -4458.576 | O61: =IF('Loan Input Parameters'!$B$8*3%<=4000,4000,IF('Loan Input Parameters'!$B$8*3%>=18000,18000,'Loan Input Parameters'!$B$8*3%)) -> 15000 | P61: =IF(N61<0,O61,N61+O61) -> 15000
A62: =A61+1 -> 59 | B62: =EOMONTH(B61,1) -> 46996 | C62: =IF(ROUND(H61,0)>0,H61,0) -> 252476.86 | D62: =IF(A62<'Loan Input Parameters'!$B$16,'Loan Input Parameters'!$B$24,IF(A62='Loan Input Parameters'!$B$16,'Loan Input Parameters'!$B$24+'Loan Input Parameters'!$B$20,0)) -> 7931.5631 | E62: =IF($A62<'Loan Input Parameters'!$B$16,C62*'Loan Input Parameters'!$B$15/12,"0.00") -> 2314.3712 | F62: =IF(A62<='Loan Input Parameters'!$B$16,'Loan Input Parameters'!$B$23,0) -> 69 | G62: =IF($A62<'Loan Input Parameters'!$B$16,D62-E62-F62,"0.00") -> 5548.1919 | H62: =IF($A62<'Loan Input Parameters'!$B$16,C62-G62,"0.00") -> 246928.67 | I62: =H62/'Loan Input Parameters'!$B$13 -> 0.49266754 | J62: =J61 -> 0.11 | K62: {=IF( AND(MONTH($B62)=1,SUMPRODUCT(--(MONTH($B$4:B62)=1))=1), K61*(1-22%*J62), IF( AND(MONTH($B62)=1,SUMPRODUCT(--(MONTH($B$4:B62)=1))=2), K61*(1-20%*J62), IF($A62<13,K61*(1-(J62*4%)), IF($A62<25,K61*(1-(J62*5%)),K61*(1-J62/12) ) ) ))} -> 254580.19 | L62: =IF(K62*'Loan Input Parameters'!$B$41<'Loan Input Parameters'!$B$42,'Loan Input Parameters'!$B$42,K62*'Loan Input Parameters'!$B$41) -> 0 | M62: =K62-L62 -> 254580.19 | N62: =H62-(K62-L62) -> -7651.5264 | O62: =IF('Loan Input Parameters'!$B$8*3%<=4000,4000,IF('Loan Input Parameters'!$B$8*3%>=18000,18000,'Loan Input Parameters'!$B$8*3%)) -> 15000 | P62: =IF(N62<0,O62,N62+O62) -> 15000
A63: =A62+1 -> 60 | B63: =EOMONTH(B62,1) -> 47026 | C63: =IF(ROUND(H62,0)>0,H62,0) -> 246928.67 | D63: =IF(A63<'Loan Input Parameters'!$B$16,'Loan Input Parameters'!$B$24,IF(A63='Loan Input Parameters'!$B$16,'Loan Input Parameters'!$B$24+'Loan Input Parameters'!$B$20,0)) -> 7931.5631 | E63: =IF($A63<'Loan Input Parameters'!$B$16,C63*'Loan Input Parameters'!$B$15/12,"0.00") -> 2263.5128 | F63: =IF(A63<='Loan Input Parameters'!$B$16,'Loan Input Parameters'!$B$23,0) -> 69 | G63: =IF($A63<'Loan Input Parameters'!$B$16,D63-E63-F63,"0.00") -> 5599.0503 | H63: =IF($A63<'Loan Input Parameters'!$B$16,C63-G63,"0.00") -> 241329.62 | I63: =H63/'Loan Input Parameters'!$B$13 -> 0.48149642 | J63: =J62 -> 0.11 | K63: {=IF( AND(MONTH($B63)=1,SUMPRODUCT(--(MONTH($B$4:B63)=1))=1), K62*(1-22%*J63), IF( AND(MONTH($B63)=1,SUMPRODUCT(--(MONTH($B$4:B63)=1))=2), K62*(1-20%*J63), IF($A63<13,K62*(1-(J63*4%)), IF($A63<25,K62*(1-(J63*5%)),K62*(1-J63/12) ) ) ))} -> 252246.54 | L63: =IF(K63*'Loan Input Parameters'!$B$41<'Loan Input Parameters'!$B$42,'Loan Input Parameters'!$B$42,K63*'Loan Input Parameters'!$B$41) -> 0 | M63: =K63-L63 -> 252246.54 | N63: =H63-(K63-L63) -> -10916.925 | O63: =IF('Loan Input Parameters'!$B$8*3%<=4000,4000,IF('Loan Input Parameters'!$B$8*3%>=18000,18000,'Loan Input Parameters'!$B$8*3%)) -> 15000 | P63: =IF(N63<0,O63,N63+O63) -> 15000
A64: =A63+1 -> 61 | B64: =EOMONTH(B63,1) -> 47057 | C64: =IF(ROUND(H63,0)>0,H63,0) -> 241329.62 | D64: =IF(A64<'Loan Input Parameters'!$B$16,'Loan Input Parameters'!$B$24,IF(A64='Loan Input Parameters'!$B$16,'Loan Input Parameters'!$B$24+'Loan Input Parameters'!$B$20,0)) -> 7931.5631 | E64: =IF($A64<'Loan Input Parameters'!$B$16,C64*'Loan Input Parameters'!$B$15/12,"0.00") -> 2212.1881 | F64: =IF(A64<='Loan Input Parameters'!$B$16,'Loan Input Parameters'!$B$23,0) -> 69 | G64: =IF($A64<'Loan Input Parameters'!$B$16,D64-E64-F64,"0.00") -> 5650.3749 | H64: =IF($A64<'Loan Input Parameters'!$B$16,C64-G64,"0.00") -> 235679.24 | I64: =H64/'Loan Input Parameters'!$B$13 -> 0.47022289 | J64: =IF('Loan Input Parameters'!$B$32="Overide",'Loan Input Parameters'!$C$39,'Loan Input Parameters'!$B$39) -> 0.1 | K64: {=IF( AND(MONTH($B64)=1,SUMPRODUCT(--(MONTH($B$4:B64)=1))=1), K63*(1-22%*J64), IF( AND(MONTH($B64)=1,SUMPRODUCT(--(MONTH($B$4:B64)=1))=2), K63*(1-20%*J64), IF($A64<13,K63*(1-(J64*4%)), IF($A64<25,K63*(1-(J64*5%)),K63*(1-J64/12) ) ) ))} -> 250144.49 | L64: =IF(K64*'Loan Input Parameters'!$B$41<'Loan Input Parameters'!$B$42,'Loan Input Parameters'!$B$42,K64*'Loan Input Parameters'!$B$41) -> 0 | M64: =IFERROR(K64-L64,"") -> 250144.49 | N64: =IFERROR(H64-(K64-L64),"") -> -14465.245 | O64: =IF('Loan Input Parameters'!$B$8*3%<=4000,4000,IF('Loan Input Parameters'!$B$8*3%>=18000,18000,'Loan Input Parameters'!$B$8*3%)) -> 15000 | P64: =IF(N64<0,O64,N64+O64) -> 15000
A65: =A64+1 -> 62 | B65: =EOMONTH(B64,1) -> 47087 | C65: =IF(ROUND(H64,0)>0,H64,0) -> 235679.24 | D65: =IF(A65<'Loan Input Parameters'!$B$16,'Loan Input Parameters'!$B$24,IF(A65='Loan Input Parameters'!$B$16,'Loan Input Parameters'!$B$24+'Loan Input Parameters'!$B$20,0)) -> 7931.5631 | E65: =IF($A65<'Loan Input Parameters'!$B$16,C65*'Loan Input Parameters'!$B$15/12,"0.00") -> 2160.393 | F65: =IF(A65<='Loan Input Parameters'!$B$16,'Loan Input Parameters'!$B$23,0) -> 69 | G65: =IF($A65<'Loan Input Parameters'!$B$16,D65-E65-F65,"0.00") -> 5702.17 | H65: =IF($A65<'Loan Input Parameters'!$B$16,C65-G65,"0.00") -> 229977.07 | I65: =H65/'Loan Input Parameters'!$B$13 -> 0.45884603 | J65: =J64 -> 0.1 | K65: {=IF( AND(MONTH($B65)=1,SUMPRODUCT(--(MONTH($B$4:B65)=1))=1), K64*(1-22%*J65), IF( AND(MONTH($B65)=1,SUMPRODUCT(--(MONTH($B$4:B65)=1))=2), K64*(1-20%*J65), IF($A65<13,K64*(1-(J65*4%)), IF($A65<25,K64*(1-(J65*5%)),K64*(1-J65/12) ) ) ))} -> 248059.95 | L65: =IF(K65*'Loan Input Parameters'!$B$41<'Loan Input Parameters'!$B$42,'Loan Input Parameters'!$B$42,K65*'Loan Input Parameters'!$B$41) -> 0 | M65: =IFERROR(K65-L65,"") -> 248059.95 | N65: =IFERROR(H65-(K65-L65),"") -> -18082.878 | O65: =IF('Loan Input Parameters'!$B$8*3%<=4000,4000,IF('Loan Input Parameters'!$B$8*3%>=18000,18000,'Loan Input Parameters'!$B$8*3%)) -> 15000 | P65: =IF(N65<0,O65,N65+O65) -> 15000
A66: =A65+1 -> 63 | B66: =EOMONTH(B65,1) -> 47118 | C66: =IF(ROUND(H65,0)>0,H65,0) -> 229977.07 | D66: =IF(A66<'Loan Input Parameters'!$B$16,'Loan Input Parameters'!$B$24,IF(A66='Loan Input Parameters'!$B$16,'Loan Input Parameters'!$B$24+'Loan Input Parameters'!$B$20,0)) -> 7931.5631 | E66: =IF($A66<'Loan Input Parameters'!$B$16,C66*'Loan Input Parameters'!$B$15/12,"0.00") -> 2108.1231 | F66: =IF(A66<='Loan Input Parameters'!$B$16,'Loan Input Parameters'!$B$23,0) -> 69 | G66: =IF($A66<'Loan Input Parameters'!$B$16,D66-E66-F66,"0.00") -> 5754.4399 | H66: =IF($A66<'Loan Input Parameters'!$B$16,C66-G66,"0.00") -> 224222.63 | I66: =H66/'Loan Input Parameters'!$B$13 -> 0.44736488 | J66: =J65 -> 0.1 | K66: {=IF( AND(MONTH($B66)=1,SUMPRODUCT(--(MONTH($B$4:B66)=1))=1), K65*(1-22%*J66), IF( AND(MONTH($B66)=1,SUMPRODUCT(--(MONTH($B$4:B66)=1))=2), K65*(1-20%*J66), IF($A66<13,K65*(1-(J66*4%)), IF($A66<25,K65*(1-(J66*5%)),K65*(1-J66/12) ) ) ))} -> 245992.78 | L66: =IF(K66*'Loan Input Parameters'!$B$41<'Loan Input Parameters'!$B$42,'Loan Input Parameters'!$B$42,K66*'Loan Input Parameters'!$B$41) -> 0 | M66: =IFERROR(K66-L66,"") -> 245992.78 | N66: =IFERROR(H66-(K66-L66),"") -> -21770.152 | O66: =IF('Loan Input Parameters'!$B$8*3%<=4000,4000,IF('Loan Input Parameters'!$B$8*3%>=18000,18000,'Loan Input Parameters'!$B$8*3%)) -> 15000 | P66: =IF(N66<0,O66,N66+O66) -> 15000
A67: =A66+1 -> 64 | B67: =EOMONTH(B66,1) -> 47149 | C67: =IF(ROUND(H66,0)>0,H66,0) -> 224222.63 | D67: =IF(A67<'Loan Input Parameters'!$B$16,'Loan Input Parameters'!$B$24,IF(A67='Loan Input Parameters'!$B$16,'Loan Input Parameters'!$B$24+'Loan Input Parameters'!$B$20,0)) -> 7931.5631 | E67: =IF($A67<'Loan Input Parameters'!$B$16,C67*'Loan Input Parameters'!$B$15/12,"0.00") -> 2055.3741 | F67: =IF(A67<='Loan Input Parameters'!$B$16,'Loan Input Parameters'!$B$23,0) -> 69 | G67: =IF($A67<'Loan Input Parameters'!$B$16,D67-E67-F67,"0.00") -> 5807.1889 | H67: =IF($A67<'Loan Input Parameters'!$B$16,C67-G67,"0.00") -> 218415.44 | I67: =H67/'Loan Input Parameters'!$B$13 -> 0.43577848 | J67: =J66 -> 0.1 | K67: {=IF( AND(MONTH($B67)=1,SUMPRODUCT(--(MONTH($B$4:B67)=1))=1), K66*(1-22%*J67), IF( AND(MONTH($B67)=1,SUMPRODUCT(--(MONTH($B$4:B67)=1))=2), K66*(1-20%*J67), IF($A67<13,K66*(1-(J67*4%)), IF($A67<25,K66*(1-(J67*5%)),K66*(1-J67/12) ) ) ))} -> 243942.84 | L67: =IF(K67*'Loan Input Parameters'!$B$41<'Loan Input Parameters'!$B$42,'Loan Input Parameters'!$B$42,K67*'Loan Input Parameters'!$B$41) -> 0 | M67: =IFERROR(K67-L67,"") -> 243942.84 | N67: =IFERROR(H67-(K67-L67),"") -> -25527.401 | O67: =IF('Loan Input Parameters'!$B$8*3%<=4000,4000,IF('Loan Input Parameters'!$B$8*3%>=18000,18000,'Loan Input Parameters'!$B$8*3%)) -> 15000 | P67: =IF(N67<0,O67,N67+O67) -> 15000
A68: =A67+1 -> 65 | B68: =EOMONTH(B67,1) -> 47177 | C68: =IF(ROUND(H67,0)>0,H67,0) -> 218415.44 | D68: =IF(A68<'Loan Input Parameters'!$B$16,'Loan Input Parameters'!$B$24,IF(A68='Loan Input Parameters'!$B$16,'Loan Input Parameters'!$B$24+'Loan Input Parameters'!$B$20,0)) -> 7931.5631 | E68: =IF($A68<'Loan Input Parameters'!$B$16,C68*'Loan Input Parameters'!$B$15/12,"0.00") -> 2002.1415 | F68: =IF(A68<='Loan Input Parameters'!$B$16,'Loan Input Parameters'!$B$23,0) -> 69 | G68: =IF($A68<'Loan Input Parameters'!$B$16,D68-E68-F68,"0.00") -> 5860.4215 | H68: =IF($A68<'Loan Input Parameters'!$B$16,C68-G68,"0.00") -> 212555.02 | I68: =H68/'Loan Input Parameters'!$B$13 -> 0.42408587 | J68: =J67 -> 0.1 | K68: {=IF( AND(MONTH($B68)=1,SUMPRODUCT(--(MONTH($B$4:B68)=1))=1), K67*(1-22%*J68), IF( AND(MONTH($B68)=1,SUMPRODUCT(--(MONTH($B$4:B68)=1))=2), K67*(1-20%*J68), IF($A68<13,K67*(1-(J68*4%)), IF($A68<25,K67*(1-(J68*5%)),K67*(1-J68/12) ) ) ))} -> 241909.99 | L68: =IF(K68*'Loan Input Parameters'!$B$41<'Loan Input Parameters'!$B$42,'Loan Input Parameters'!$B$42,K68*'Loan Input Parameters'!$B$41) -> 0 | M68: =IFERROR(K68-L68,"") -> 241909.99 | N68: =IFERROR(H68-(K68-L68),"") -> -29354.965 | O68: =IF('Loan Input Parameters'!$B$8*3%<=4000,4000,IF('Loan Input Parameters'!$B$8*3%>=18000,18000,'Loan Input Parameters'!$B$8*3%)) -> 15000 | P68: =IF(N68<0,O68,N68+O68) -> 15000
A69: =A68+1 -> 66 | B69: =EOMONTH(B68,1) -> 47208 | C69: =IF(ROUND(H68,0)>0,H68,0) -> 212555.02 | D69: =IF(A69<'Loan Input Parameters'!$B$16,'Loan Input Parameters'!$B$24,IF(A69='Loan Input Parameters'!$B$16,'Loan Input Parameters'!$B$24+'Loan Input Parameters'!$B$20,0)) -> 7931.5631 | E69: =IF($A69<'Loan Input Parameters'!$B$16,C69*'Loan Input Parameters'!$B$15/12,"0.00") -> 1948.421 | F69: =IF(A69<='Loan Input Parameters'!$B$16,'Loan Input Parameters'!$B$23,0) -> 69 | G69: =IF($A69<'Loan Input Parameters'!$B$16,D69-E69-F69,"0.00") -> 5914.142 | H69: =IF($A69<'Loan Input Parameters'!$B$16,C69-G69,"0.00") -> 206640.88 | I69: =H69/'Loan Input Parameters'!$B$13 -> 0.41228609 | J69: =J68 -> 0.1 | K69: {=IF( AND(MONTH($B69)=1,SUMPRODUCT(--(MONTH($B$4:B69)=1))=1), K68*(1-22%*J69), IF( AND(MONTH($B69)=1,SUMPRODUCT(--(MONTH($B$4:B69)=1))=2), K68*(1-20%*J69), IF($A69<13,K68*(1-(J69*4%)), IF($A69<25,K68*(1-(J69*5%)),K68*(1-J69/12) ) ) ))} -> 239894.07 | L69: =IF(K69*'Loan Input Parameters'!$B$41<'Loan Input Parameters'!$B$42,'Loan Input Parameters'!$B$42,K69*'Loan Input Parameters'!$B$41) -> 0 | M69: =IFERROR(K69-L69,"") -> 239894.07 | N69: =IFERROR(H69-(K69-L69),"") -> -33253.191 | O69: =IF('Loan Input Parameters'!$B$8*3%<=4000,4000,IF('Loan Input Parameters'!$B$8*3%>=18000,18000,'Loan Input Parameters'!$B$8*3%)) -> 15000 | P69: =IF(N69<0,O69,N69+O69) -> 15000
A70: =A69+1 -> 67 | B70: =EOMONTH(B69,1) -> 47238 | C70: =IF(ROUND(H69,0)>0,H69,0) -> 206640.88 | D70: =IF(A70<'Loan Input Parameters'!$B$16,'Loan Input Parameters'!$B$24,IF(A70='Loan Input Parameters'!$B$16,'Loan Input Parameters'!$B$24+'Loan Input Parameters'!$B$20,0)) -> 7931.5631 | E70: =IF($A70<'Loan Input Parameters'!$B$16,C70*'Loan Input Parameters'!$B$15/12,"0.00") -> 1894.2081 | F70: =IF(A70<='Loan Input Parameters'!$B$16,'Loan Input Parameters'!$B$23,0) -> 69 | G70: =IF($A70<'Loan Input Parameters'!$B$16,D70-E70-F70,"0.00") -> 5968.355 | H70: =IF($A70<'Loan Input Parameters'!$B$16,C70-G70,"0.00") -> 200672.52 | I70: =H70/'Loan Input Parameters'!$B$13 -> 0.40037813 | J70: =J69 -> 0.1 | K70: {=IF( AND(MONTH($B70)=1,SUMPRODUCT(--(MONTH($B$4:B70)=1))=1), K69*(1-22%*J70), IF( AND(MONTH($B70)=1,SUMPRODUCT(--(MONTH($B$4:B70)=1))=2), K69*(1-20%*J70), IF($A70<13,K69*(1-(J70*4%)), IF($A70<25,K69*(1-(J70*5%)),K69*(1-J70/12) ) ) ))} -> 237894.95 | L70: =IF(K70*'Loan Input Parameters'!$B$41<'Loan Input Parameters'!$B$42,'Loan Input Parameters'!$B$42,K70*'Loan Input Parameters'!$B$41) -> 0 | M70: =IFERROR(K70-L70,"") -> 237894.95 | N70: =IFERROR(H70-(K70-L70),"") -> -37222.428 | O70: =IF('Loan Input Parameters'!$B$8*3%<=4000,4000,IF('Loan Input Parameters'!$B$8*3%>=18000,18000,'Loan Input Parameters'!$B$8*3%)) -> 15000 | P70: =IF(N70<0,O70,N70+O70) -> 15000
A71: =A70+1 -> 68 | B71: =EOMONTH(B70,1) -> 47269 | C71: =IF(ROUND(H70,0)>0,H70,0) -> 200672.52 | D71: =IF(A71<'Loan Input Parameters'!$B$16,'Loan Input Parameters'!$B$24,IF(A71='Loan Input Parameters'!$B$16,'Loan Input Parameters'!$B$24+'Loan Input Parameters'!$B$20,0)) -> 7931.5631 | E71: =IF($A71<'Loan Input Parameters'!$B$16,C71*'Loan Input Parameters'!$B$15/12,"0.00") -> 1839.4981 | F71: =IF(A71<='Loan Input Parameters'!$B$16,'Loan Input Parameters'!$B$23,0) -> 69 | G71: =IF($A71<'Loan Input Parameters'!$B$16,D71-E71-F71,"0.00") -> 6023.0649 | H71: =IF($A71<'Loan Input Parameters'!$B$16,C71-G71,"0.00") -> 194649.46 | I71: =H71/'Loan Input Parameters'!$B$13 -> 0.38836102 | J71: =J70 -> 0.1 | K71: {=IF( AND(MONTH($B71)=1,SUMPRODUCT(--(MONTH($B$4:B71)=1))=1), K70*(1-22%*J71), IF( AND(MONTH($B71)=1,SUMPRODUCT(--(MONTH($B$4:B71)=1))=2), K70*(1-20%*J71), IF($A71<13,K70*(1-(J71*4%)), IF($A71<25,K70*(1-(J71*5%)),K70*(1-J71/12) ) ) ))} -> 235912.49 | L71: =IF(K71*'Loan Input Parameters'!$B$41<'Loan Input Parameters'!$B$42,'Loan Input Parameters'!$B$42,K71*'Loan Input Parameters'!$B$41) -> 0 | M71: =IFERROR(K71-L71,"") -> 235912.49 | N71: =IFERROR(H71-(K71-L71),"") -> -41263.035 | O71: =IF('Loan Input Parameters'!$B$8*3%<=4000,4000,IF('Loan Input Parameters'!$B$8*3%>=18000,18000,'Loan Input Parameters'!$B$8*3%)) -> 15000 | P71: =IF(N71<0,O71,N71+O71) -> 15000
A72: =A71+1 -> 69 | B72: =EOMONTH(B71,1) -> 47299 | C72: =IF(ROUND(H71,0)>0,H71,0) -> 194649.46 | D72: =IF(A72<'Loan Input Parameters'!$B$16,'Loan Input Parameters'!$B$24,IF(A72='Loan Input Parameters'!$B$16,'Loan Input Parameters'!$B$24+'Loan Input Parameters'!$B$20,0)) -> 7931.5631 | E72: =IF($A72<'Loan Input Parameters'!$B$16,C72*'Loan Input Parameters'!$B$15/12,"0.00") -> 1784.2867 | F72: =IF(A72<='Loan Input Parameters'!$B$16,'Loan Input Parameters'!$B$23,0) -> 69 | G72: =IF($A72<'Loan Input Parameters'!$B$16,D72-E72-F72,"0.00") -> 6078.2764 | H72: =IF($A72<'Loan Input Parameters'!$B$16,C72-G72,"0.00") -> 188571.18 | I72: =H72/'Loan Input Parameters'!$B$13 -> 0.37623376 | J72: =J71 -> 0.1 | K72: {=IF( AND(MONTH($B72)=1,SUMPRODUCT(--(MONTH($B$4:B72)=1))=1), K71*(1-22%*J72), IF( AND(MONTH($B72)=1,SUMPRODUCT(--(MONTH($B$4:B72)=1))=2), K71*(1-20%*J72), IF($A72<13,K71*(1-(J72*4%)), IF($A72<25,K71*(1-(J72*5%)),K71*(1-J72/12) ) ) ))} -> 233946.56 | L72: =IF(K72*'Loan Input Parameters'!$B$41<'Loan Input Parameters'!$B$42,'Loan Input Parameters'!$B$42,K72*'Loan Input Parameters'!$B$41) -> 0 | M72: =IFERROR(K72-L72,"") -> 233946.56 | N72: =IFERROR(H72-(K72-L72),"") -> -45375.374 | O72: =IF('Loan Input Parameters'!$B$8*3%<=4000,4000,IF('Loan Input Parameters'!$B$8*3%>=18000,18000,'Loan Input Parameters'!$B$8*3%)) -> 15000 | P72: =IF(N72<0,O72,N72+O72) -> 15000
A73: =A72+1 -> 70 | B73: =EOMONTH(B72,1) -> 47330 | C73: =IF(ROUND(H72,0)>0,H72,0) -> 188571.18 | D73: =IF(A73<'Loan Input Parameters'!$B$16,'Loan Input Parameters'!$B$24,IF(A73='Loan Input Parameters'!$B$16,'Loan Input Parameters'!$B$24+'Loan Input Parameters'!$B$20,0)) -> 7931.5631 | E73: =IF($A73<'Loan Input Parameters'!$B$16,C73*'Loan Input Parameters'!$B$15/12,"0.00") -> 1728.5692 | F73: =IF(A73<='Loan Input Parameters'!$B$16,'Loan Input Parameters'!$B$23,0) -> 69 | G73: =IF($A73<'Loan Input Parameters'!$B$16,D73-E73-F73,"0.00") -> 6133.9939 | H73: =IF($A73<'Loan Input Parameters'!$B$16,C73-G73,"0.00") -> 182437.19 | I73: =H73/'Loan Input Parameters'!$B$13 -> 0.36399533 | J73: =J72 -> 0.1 | K73: {=IF( AND(MONTH($B73)=1,SUMPRODUCT(--(MONTH($B$4:B73)=1))=1), K72*(1-22%*J73), IF( AND(MONTH($B73)=1,SUMPRODUCT(--(MONTH($B$4:B73)=1))=2), K72*(1-20%*J73), IF($A73<13,K72*(1-(J73*4%)), IF($A73<25,K72*(1-(J73*5%)),K72*(1-J73/12) ) ) ))} -> 231997 | L73: =IF(K73*'Loan Input Parameters'!$B$41<'Loan Input Parameters'!$B$42,'Loan Input Parameters'!$B$42,K73*'Loan Input Parameters'!$B$41) -> 0 | M73: =IFERROR(K73-L73,"") -> 231997 | N73: =IFERROR(H73-(K73-L73),"") -> -49559.814 | O73: =IF('Loan Input Parameters'!$B$8*3%<=4000,4000,IF('Loan Input Parameters'!$B$8*3%>=18000,18000,'Loan Input Parameters'!$B$8*3%)) -> 15000 | P73: =IF(N73<0,O73,N73+O73) -> 15000
A74: =A73+1 -> 71 | B74: =EOMONTH(B73,1) -> 47361 | C74: =IF(ROUND(H73,0)>0,H73,0) -> 182437.19 | D74: =IF(A74<'Loan Input Parameters'!$B$16,'Loan Input Parameters'!$B$24,IF(A74='Loan Input Parameters'!$B$16,'Loan Input Parameters'!$B$24+'Loan Input Parameters'!$B$20,0)) -> 7931.5631 | E74: =IF($A74<'Loan Input Parameters'!$B$16,C74*'Loan Input Parameters'!$B$15/12,"0.00") -> 1672.3409 | F74: =IF(A74<='Loan Input Parameters'!$B$16,'Loan Input Parameters'!$B$23,0) -> 69 | G74: =IF($A74<'Loan Input Parameters'!$B$16,D74-E74-F74,"0.00") -> 6190.2222 | H74: =IF($A74<'Loan Input Parameters'!$B$16,C74-G74,"0.00") -> 176246.97 | I74: =H74/'Loan Input Parameters'!$B$13 -> 0.35164471 | J74: =J73 -> 0.1 | K74: {=IF( AND(MONTH($B74)=1,SUMPRODUCT(--(MONTH($B$4:B74)=1))=1), K73*(1-22%*J74), IF( AND(MONTH($B74)=1,SUMPRODUCT(--(MONTH($B$4:B74)=1))=2), K73*(1-20%*J74), IF($A74<13,K73*(1-(J74*4%)), IF($A74<25,K73*(1-(J74*5%)),K73*(1-J74/12) ) ) ))} -> 230063.69 | L74: =IF(K74*'Loan Input Parameters'!$B$41<'Loan Input Parameters'!$B$42,'Loan Input Parameters'!$B$42,K74*'Loan Input Parameters'!$B$41) -> 0 | M74: =IFERROR(K74-L74,"") -> 230063.69 | N74: =IFERROR(H74-(K74-L74),"") -> -53816.727 | O74: =IF('Loan Input Parameters'!$B$8*3%<=4000,4000,IF('Loan Input Parameters'!$B$8*3%>=18000,18000,'Loan Input Parameters'!$B$8*3%)) -> 15000 | P74: =IF(N74<0,O74,N74+O74) -> 15000
A75: =A74+1 -> 72 | B75: =EOMONTH(B74,1) -> 47391 | C75: =IF(ROUND(H74,0)>0,H74,0) -> 176246.97 | D75: =IF(A75<'Loan Input Parameters'!$B$16,'Loan Input Parameters'!$B$24,IF(A75='Loan Input Parameters'!$B$16,'Loan Input Parameters'!$B$24,0)) -> 7931.5631 | E75: =IF($A75<'Loan Input Parameters'!$B$16,C75*'Loan Input Parameters'!$B$15/12,"0.00") -> 0.00 | F75: =IF(A75<='Loan Input Parameters'!$B$16,'Loan Input Parameters'!$B$23,0) -> 69 | G75: =IF($A75<'Loan Input Parameters'!$B$16,D75-E75-F75,"0.00") -> 0.00 | H75: =IF($A75<'Loan Input Parameters'!$B$16,C75-G75,"0.00") -> 0.00 | I75: =H75/'Loan Input Parameters'!$B$13 -> 0 | J75: =J74 -> 0.1 | K75: {=IF( AND(MONTH($B75)=1,SUMPRODUCT(--(MONTH($B$4:B75)=1))=1), K74*(1-22%*J75), IF( AND(MONTH($B75)=1,SUMPRODUCT(--(MONTH($B$4:B75)=1))=2), K74*(1-20%*J75), IF($A75<13,K74*(1-(J75*4%)), IF($A75<25,K74*(1-(J75*5%)),K74*(1-J75/12) ) ) ))} -> 228146.5 | L75: =IF(K75*'Loan Input Parameters'!$B$41<'Loan Input Parameters'!$B$42,'Loan Input Parameters'!$B$42,K75*'Loan Input Parameters'!$B$41) -> 0 | M75: =IFERROR(K75-L75,"") -> 228146.5 | N75: =IFERROR(H75-(K75-L75),"") -> -228146.5 | O75: =IF('Loan Input Parameters'!$B$8*3%<=4000,4000,IF('Loan Input Parameters'!$B$8*3%>=18000,18000,'Loan Input Parameters'!$B$8*3%)) -> 15000 | P75: =IF(N75<0,O75,N75+O75) -> 15000
A76: =A75+1 -> 73 | B76: =EOMONTH(B75,1) -> 47422 | C76: =IF(ROUND(H75,0)>0,H75,0) -> 0 | D76: =IF(A76<'Loan Input Parameters'!$B$16,'Loan Input Parameters'!$B$24,IF(A76='Loan Input Parameters'!$B$16,'Loan Input Parameters'!$B$24,0)) -> 0 | E76: =IF($A76<'Loan Input Parameters'!$B$16,C76*'Loan Input Parameters'!$B$15/12,"0.00") -> 0.00 | F76: =IF(A76<='Loan Input Parameters'!$B$16,'Loan Input Parameters'!$B$23,0) -> 0 | G76: =IF($A76<'Loan Input Parameters'!$B$16,D76-E76-F76,"0.00") -> 0.00 | H76: =IF($A76<'Loan Input Parameters'!$B$16,C76-G76,"0.00") -> 0.00 | I76: =H76/'Loan Input Parameters'!$B$13 -> 0 | J76: =J75 -> 0.1 | K76: {=IF( AND(MONTH($B76)=1,SUMPRODUCT(--(MONTH($B$4:B76)=1))=1), K75*(1-22%*J76), IF( AND(MONTH($B76)=1,SUMPRODUCT(--(MONTH($B$4:B76)=1))=2), K75*(1-20%*J76), IF($A76<13,K75*(1-(J76*4%)), IF($A76<25,K75*(1-(J76*5%)),K75*(1-J76/12) ) ) ))} -> 226245.28 | L76: =IF(K76*'Loan Input Parameters'!$B$41<'Loan Input Parameters'!$B$42,'Loan Input Parameters'!$B$42,K76*'Loan Input Parameters'!$B$41) -> 0 | M76: =IFERROR(K76-L76,"") -> 226245.28 | N76: =IFERROR(H76-(K76-L76),"") -> -226245.28 | O76: =IF('Loan Input Parameters'!$B$8*3%<=4000,4000,IF('Loan Input Parameters'!$B$8*3%>=18000,18000,'Loan Input Parameters'!$B$8*3%)) -> 15000 | P76: =IF(N76<0,O76,N76+O76) -> 15000
A77: =A76+1 -> 74 | B77: =EOMONTH(B76,1) -> 47452 | C77: =IF(ROUND(H76,0)>0,H76,0) -> 0 | D77: =IF(A77<'Loan Input Parameters'!$B$16,'Loan Input Parameters'!$B$24,IF(A77='Loan Input Parameters'!$B$16,'Loan Input Parameters'!$B$24,0)) -> 0 | E77: =IF($A77<'Loan Input Parameters'!$B$16,C77*'Loan Input Parameters'!$B$15/12,"0.00") -> 0.00 | F77: =IF(A77<='Loan Input Parameters'!$B$16,'Loan Input Parameters'!$B$23,0) -> 0 | G77: =IF($A77<'Loan Input Parameters'!$B$16,D77-E77-F77,"0.00") -> 0.00 | H77: =IF($A77<'Loan Input Parameters'!$B$16,C77-G77,"0.00") -> 0.00 | I77: =H77/'Loan Input Parameters'!$B$13 -> 0 | J77: =J76 -> 0.1 | K77: {=IF( AND(MONTH($B77)=1,SUMPRODUCT(--(MONTH($B$4:B77)=1))=1), K76*(1-22%*J77), IF( AND(MONTH($B77)=1,SUMPRODUCT(--(MONTH($B$4:B77)=1))=2), K76*(1-20%*J77), IF($A77<13,K76*(1-(J77*4%)), IF($A77<25,K76*(1-(J77*5%)),K76*(1-J77/12) ) ) ))} -> 224359.9 | L77: =IF(K77*'Loan Input Parameters'!$B$41<'Loan Input Parameters'!$B$42,'Loan Input Parameters'!$B$42,K77*'Loan Input Parameters'!$B$41) -> 0 | M77: =IFERROR(K77-L77,"") -> 224359.9 | N77: =IFERROR(H77-(K77-L77),"") -> -224359.9 | O77: =IF('Loan Input Parameters'!$B$8*3%<=4000,4000,IF('Loan Input Parameters'!$B$8*3%>=18000,18000,'Loan Input Parameters'!$B$8*3%)) -> 15000 | P77: =IF(N77<0,O77,N77+O77) -> 15000
A78: =A77+1 -> 75 | B78: =EOMONTH(B77,1) -> 47483 | C78: =IF(ROUND(H77,0)>0,H77,0) -> 0 | D78: =IF(A78<'Loan Input Parameters'!$B$16,'Loan Input Parameters'!$B$24,IF(A78='Loan Input Parameters'!$B$16,'Loan Input Parameters'!$B$24,0)) -> 0 | E78: =IF($A78<'Loan Input Parameters'!$B$16,C78*'Loan Input Parameters'!$B$15/12,"0.00") -> 0.00 | F78: =IF(A78<='Loan Input Parameters'!$B$16,'Loan Input Parameters'!$B$23,0) -> 0 | G78: =IF($A78<'Loan Input Parameters'!$B$16,D78-E78-F78,"0.00") -> 0.00 | H78: =IF($A78<'Loan Input Parameters'!$B$16,C78-G78,"0.00") -> 0.00 | I78: =H78/'Loan Input Parameters'!$B$13 -> 0 | J78: =J77 -> 0.1 | K78: {=IF( AND(MONTH($B78)=1,SUMPRODUCT(--(MONTH($B$4:B78)=1))=1), K77*(1-22%*J78), IF( AND(MONTH($B78)=1,SUMPRODUCT(--(MONTH($B$4:B78)=1))=2), K77*(1-20%*J78), IF($A78<13,K77*(1-(J78*4%)), IF($A78<25,K77*(1-(J78*5%)),K77*(1-J78/12) ) ) ))} -> 222490.23 | L78: =IF(K78*'Loan Input Parameters'!$B$41<'Loan Input Parameters'!$B$42,'Loan Input Parameters'!$B$42,K78*'Loan Input Parameters'!$B$41) -> 0 | M78: =IFERROR(K78-L78,"") -> 222490.23 | N78: =IFERROR(H78-(K78-L78),"") -> -222490.23 | O78: =IF('Loan Input Parameters'!$B$8*3%<=4000,4000,IF('Loan Input Parameters'!$B$8*3%>=18000,18000,'Loan Input Parameters'!$B$8*3%)) -> 15000 | P78: =IF(N78<0,O78,N78+O78) -> 15000
A79: =A78+1 -> 76 | B79: =EOMONTH(B78,1) -> 47514 | C79: =IF(ROUND(H78,0)>0,H78,0) -> 0 | D79: =IF(A79<'Loan Input Parameters'!$B$16,'Loan Input Parameters'!$B$24,IF(A79='Loan Input Parameters'!$B$16,'Loan Input Parameters'!$B$24,0)) -> 0 | E79: =IF($A79<'Loan Input Parameters'!$B$16,C79*'Loan Input Parameters'!$B$15/12,"0.00") -> 0.00 | F79: =IF(A79<='Loan Input Parameters'!$B$16,'Loan Input Parameters'!$B$23,0) -> 0 | G79: =IF($A79<'Loan Input Parameters'!$B$16,D79-E79-F79,"0.00") -> 0.00 | H79: =IF($A79<'Loan Input Parameters'!$B$16,C79-G79,"0.00") -> 0.00 | I79: =H79/'Loan Input Parameters'!$B$13 -> 0 | J79: =J78 -> 0.1 | K79: {=IF( AND(MONTH($B79)=1,SUMPRODUCT(--(MONTH($B$4:B79)=1))=1), K78*(1-22%*J79), IF( AND(MONTH($B79)=1,SUMPRODUCT(--(MONTH($B$4:B79)=1))=2), K78*(1-20%*J79), IF($A79<13,K78*(1-(J79*4%)), IF($A79<25,K78*(1-(J79*5%)),K78*(1-J79/12) ) ) ))} -> 220636.15 | L79: =IF(K79*'Loan Input Parameters'!$B$41<'Loan Input Parameters'!$B$42,'Loan Input Parameters'!$B$42,K79*'Loan Input Parameters'!$B$41) -> 0 | M79: =IFERROR(K79-L79,"") -> 220636.15 | N79: =IFERROR(H79-(K79-L79),"") -> -220636.15 | O79: =IF('Loan Input Parameters'!$B$8*3%<=4000,4000,IF('Loan Input Parameters'!$B$8*3%>=18000,18000,'Loan Input Parameters'!$B$8*3%)) -> 15000 | P79: =IF(N79<0,O79,N79+O79) -> 15000
A80: =A79+1 -> 77 | B80: =EOMONTH(B79,1) -> 47542 | C80: =IF(ROUND(H79,0)>0,H79,0) -> 0 | D80: =IF(A80<'Loan Input Parameters'!$B$16,'Loan Input Parameters'!$B$24,IF(A80='Loan Input Parameters'!$B$16,'Loan Input Parameters'!$B$24,0)) -> 0 | E80: =IF($A80<'Loan Input Parameters'!$B$16,C80*'Loan Input Parameters'!$B$15/12,"0.00") -> 0.00 | F80: =IF(A80<='Loan Input Parameters'!$B$16,'Loan Input Parameters'!$B$23,0) -> 0 | G80: =IF($A80<'Loan Input Parameters'!$B$16,D80-E80-F80,"0.00") -> 0.00 | H80: =IF($A80<'Loan Input Parameters'!$B$16,C80-G80,"0.00") -> 0.00 | I80: =H80/'Loan Input Parameters'!$B$13 -> 0 | J80: =J79 -> 0.1 | K80: {=IF( AND(MONTH($B80)=1,SUMPRODUCT(--(MONTH($B$4:B80)=1))=1), K79*(1-22%*J80), IF( AND(MONTH($B80)=1,SUMPRODUCT(--(MONTH($B$4:B80)=1))=2), K79*(1-20%*J80), IF($A80<13,K79*(1-(J80*4%)), IF($A80<25,K79*(1-(J80*5%)),K79*(1-J80/12) ) ) ))} -> 218797.51 | L80: =IF(K80*'Loan Input Parameters'!$B$41<'Loan Input Parameters'!$B$42,'Loan Input Parameters'!$B$42,K80*'Loan Input Parameters'!$B$41) -> 0 | M80: =IFERROR(K80-L80,"") -> 218797.51 | N80: =IFERROR(H80-(K80-L80),"") -> -218797.51 | O80: =IF('Loan Input Parameters'!$B$8*3%<=4000,4000,IF('Loan Input Parameters'!$B$8*3%>=18000,18000,'Loan Input Parameters'!$B$8*3%)) -> 15000 | P80: =IF(N80<0,O80,N80+O80) -> 15000
A81: =A80+1 -> 78 | B81: =EOMONTH(B80,1) -> 47573 | C81: =IF(ROUND(H80,0)>0,H80,0) -> 0 | D81: =IF(A81<'Loan Input Parameters'!$B$16,'Loan Input Parameters'!$B$24,IF(A81='Loan Input Parameters'!$B$16,'Loan Input Parameters'!$B$24,0)) -> 0 | E81: =IF($A81<'Loan Input Parameters'!$B$16,C81*'Loan Input Parameters'!$B$15/12,"0.00") -> 0.00 | F81: =IF(A81<='Loan Input Parameters'!$B$16,'Loan Input Parameters'!$B$23,0) -> 0 | G81: =IF($A81<'Loan Input Parameters'!$B$16,D81-E81-F81,"0.00") -> 0.00 | H81: =IF($A81<'Loan Input Parameters'!$B$16,C81-G81,"0.00") -> 0.00 | I81: =H81/'Loan Input Parameters'!$B$13 -> 0 | J81: =J80 -> 0.1 | K81: {=IF( AND(MONTH($B81)=1,SUMPRODUCT(--(MONTH($B$4:B81)=1))=1), K80*(1-22%*J81), IF( AND(MONTH($B81)=1,SUMPRODUCT(--(MONTH($B$4:B81)=1))=2), K80*(1-20%*J81), IF($A81<13,K80*(1-(J81*4%)), IF($A81<25,K80*(1-(J81*5%)),K80*(1-J81/12) ) ) ))} -> 216974.2 | L81: =IF(K81*'Loan Input Parameters'!$B$41<'Loan Input Parameters'!$B$42,'Loan Input Parameters'!$B$42,K81*'Loan Input Parameters'!$B$41) -> 0 | M81: =IFERROR(K81-L81,"") -> 216974.2 | N81: =IFERROR(H81-(K81-L81),"") -> -216974.2 | O81: =IF('Loan Input Parameters'!$B$8*3%<=4000,4000,IF('Loan Input Parameters'!$B$8*3%>=18000,18000,'Loan Input Parameters'!$B$8*3%)) -> 15000 | P81: =IF(N81<0,O81,N81+O81) -> 15000
A82: =A81+1 -> 79 | B82: =EOMONTH(B81,1) -> 47603 | C82: =IF(ROUND(H81,0)>0,H81,0) -> 0 | D82: =IF(A82<'Loan Input Parameters'!$B$16,'Loan Input Parameters'!$B$24,IF(A82='Loan Input Parameters'!$B$16,'Loan Input Parameters'!$B$24,0)) -> 0 | E82: =IF($A82<'Loan Input Parameters'!$B$16,C82*'Loan Input Parameters'!$B$15/12,"0.00") -> 0.00 | F82: =IF(A82<='Loan Input Parameters'!$B$16,'Loan Input Parameters'!$B$23,0) -> 0 | G82: =IF($A82<'Loan Input Parameters'!$B$16,D82-E82-F82,"0.00") -> 0.00 | H82: =IF($A82<'Loan Input Parameters'!$B$16,C82-G82,"0.00") -> 0.00 | I82: =H82/'Loan Input Parameters'!$B$13 -> 0 | J82: =J81 -> 0.1 | K82: {=IF( AND(MONTH($B82)=1,SUMPRODUCT(--(MONTH($B$4:B82)=1))=1), K81*(1-22%*J82), IF( AND(MONTH($B82)=1,SUMPRODUCT(--(MONTH($B$4:B82)=1))=2), K81*(1-20%*J82), IF($A82<13,K81*(1-(J82*4%)), IF($A82<25,K81*(1-(J82*5%)),K81*(1-J82/12) ) ) ))} -> 215166.08 | L82: =IF(K82*'Loan Input Parameters'!$B$41<'Loan Input Parameters'!$B$42,'Loan Input Parameters'!$B$42,K82*'Loan Input Parameters'!$B$41) -> 0 | M82: =IFERROR(K82-L82,"") -> 215166.08 | N82: =IFERROR(H82-(K82-L82),"") -> -215166.08 | O82: =IF('Loan Input Parameters'!$B$8*3%<=4000,4000,IF('Loan Input Parameters'!$B$8*3%>=18000,18000,'Loan Input Parameters'!$B$8*3%)) -> 15000 | P82: =IF(N82<0,O82,N82+O82) -> 15000
A83: =A82+1 -> 80 | B83: =EOMONTH(B82,1) -> 47634 | C83: =IF(ROUND(H82,0)>0,H82,0) -> 0 | D83: =IF(A83<'Loan Input Parameters'!$B$16,'Loan Input Parameters'!$B$24,IF(A83='Loan Input Parameters'!$B$16,'Loan Input Parameters'!$B$24,0)) -> 0 | E83: =IF($A83<'Loan Input Parameters'!$B$16,C83*'Loan Input Parameters'!$B$15/12,"0.00") -> 0.00 | F83: =IF(A83<='Loan Input Parameters'!$B$16,'Loan Input Parameters'!$B$23,0) -> 0 | G83: =IF($A83<'Loan Input Parameters'!$B$16,D83-E83-F83,"0.00") -> 0.00 | H83: =IF($A83<'Loan Input Parameters'!$B$16,C83-G83,"0.00") -> 0.00 | I83: =H83/'Loan Input Parameters'!$B$13 -> 0 | J83: =J82 -> 0.1 | K83: {=IF( AND(MONTH($B83)=1,SUMPRODUCT(--(MONTH($B$4:B83)=1))=1), K82*(1-22%*J83), IF( AND(MONTH($B83)=1,SUMPRODUCT(--(MONTH($B$4:B83)=1))=2), K82*(1-20%*J83), IF($A83<13,K82*(1-(J83*4%)), IF($A83<25,K82*(1-(J83*5%)),K82*(1-J83/12) ) ) ))} -> 213373.03 | L83: =IF(K83*'Loan Input Parameters'!$B$41<'Loan Input Parameters'!$B$42,'Loan Input Parameters'!$B$42,K83*'Loan Input Parameters'!$B$41) -> 0 | M83: =IFERROR(K83-L83,"") -> 213373.03 | N83: =IFERROR(H83-(K83-L83),"") -> -213373.03 | O83: =IF('Loan Input Parameters'!$B$8*3%<=4000,4000,IF('Loan Input Parameters'!$B$8*3%>=18000,18000,'Loan Input Parameters'!$B$8*3%)) -> 15000 | P83: =IF(N83<0,O83,N83+O83) -> 15000
A84: =A83+1 -> 81 | B84: =EOMONTH(B83,1) -> 47664 | C84: =IF(ROUND(H83,0)>0,H83,0) -> 0 | D84: =IF(A84<'Loan Input Parameters'!$B$16,'Loan Input Parameters'!$B$24,IF(A84='Loan Input Parameters'!$B$16,'Loan Input Parameters'!$B$24,0)) -> 0 | E84: =IF($A84<'Loan Input Parameters'!$B$16,C84*'Loan Input Parameters'!$B$15/12,"0.00") -> 0.00 | F84: =IF(A84<='Loan Input Parameters'!$B$16,'Loan Input Parameters'!$B$23,0) -> 0 | G84: =IF($A84<'Loan Input Parameters'!$B$16,D84-E84-F84,"0.00") -> 0.00 | H84: =IF($A84<'Loan Input Parameters'!$B$16,C84-G84,"0.00") -> 0.00 | I84: =H84/'Loan Input Parameters'!$B$13 -> 0 | J84: =J83 -> 0.1 | K84: {=IF( AND(MONTH($B84)=1,SUMPRODUCT(--(MONTH($B$4:B84)=1))=1), K83*(1-22%*J84), IF( AND(MONTH($B84)=1,SUMPRODUCT(--(MONTH($B$4:B84)=1))=2), K83*(1-20%*J84), IF($A84<13,K83*(1-(J84*4%)), IF($A84<25,K83*(1-(J84*5%)),K83*(1-J84/12) ) ) ))} -> 211594.92 | L84: =IF(K84*'Loan Input Parameters'!$B$41<'Loan Input Parameters'!$B$42,'Loan Input Parameters'!$B$42,K84*'Loan Input Parameters'!$B$41) -> 0 | M84: =IFERROR(K84-L84,"") -> 211594.92 | N84: =IFERROR(H84-(K84-L84),"") -> -211594.92 | O84: =IF('Loan Input Parameters'!$B$8*3%<=4000,4000,IF('Loan Input Parameters'!$B$8*3%>=18000,18000,'Loan Input Parameters'!$B$8*3%)) -> 15000 | P84: =IF(N84<0,O84,N84+O84) -> 15000
A85: =A84+1 -> 82 | B85: =EOMONTH(B84,1) -> 47695 | C85: =IF(ROUND(H84,0)>0,H84,0) -> 0 | D85: =IF(A85<'Loan Input Parameters'!$B$16,'Loan Input Parameters'!$B$24,IF(A85='Loan Input Parameters'!$B$16,'Loan Input Parameters'!$B$24,0)) -> 0 | E85: =IF($A85<'Loan Input Parameters'!$B$16,C85*'Loan Input Parameters'!$B$15/12,"0.00") -> 0.00 | F85: =IF(A85<='Loan Input Parameters'!$B$16,'Loan Input Parameters'!$B$23,0) -> 0 | G85: =IF($A85<'Loan Input Parameters'!$B$16,D85-E85-F85,"0.00") -> 0.00 | H85: =IF($A85<'Loan Input Parameters'!$B$16,C85-G85,"0.00") -> 0.00 | I85: =H85/'Loan Input Parameters'!$B$13 -> 0 | J85: =J84 -> 0.1 | K85: {=IF( AND(MONTH($B85)=1,SUMPRODUCT(--(MONTH($B$4:B85)=1))=1), K84*(1-22%*J85), IF( AND(MONTH($B85)=1,SUMPRODUCT(--(MONTH($B$4:B85)=1))=2), K84*(1-20%*J85), IF($A85<13,K84*(1-(J85*4%)), IF($A85<25,K84*(1-(J85*5%)),K84*(1-J85/12) ) ) ))} -> 209831.63 | L85: =IF(K85*'Loan Input Parameters'!$B$41<'Loan Input Parameters'!$B$42,'Loan Input Parameters'!$B$42,K85*'Loan Input Parameters'!$B$41) -> 0 | M85: =IFERROR(K85-L85,"") -> 209831.63 | N85: =IFERROR(H85-(K85-L85),"") -> -209831.63 | O85: =IF('Loan Input Parameters'!$B$8*3%<=4000,4000,IF('Loan Input Parameters'!$B$8*3%>=18000,18000,'Loan Input Parameters'!$B$8*3%)) -> 15000 | P85: =IF(N85<0,O85,N85+O85) -> 15000
A86: =A85+1 -> 83 | B86: =EOMONTH(B85,1) -> 47726 | C86: =IF(ROUND(H85,0)>0,H85,0) -> 0 | D86: =IF(A86<'Loan Input Parameters'!$B$16,'Loan Input Parameters'!$B$24,IF(A86='Loan Input Parameters'!$B$16,'Loan Input Parameters'!$B$24,0)) -> 0 | E86: =IF($A86<'Loan Input Parameters'!$B$16,C86*'Loan Input Parameters'!$B$15/12,"0.00") -> 0.00 | F86: =IF(A86<='Loan Input Parameters'!$B$16,'Loan Input Parameters'!$B$23,0) -> 0 | G86: =IF($A86<'Loan Input Parameters'!$B$16,D86-E86-F86,"0.00") -> 0.00 | H86: =IF($A86<'Loan Input Parameters'!$B$16,C86-G86,"0.00") -> 0.00 | I86: =H86/'Loan Input Parameters'!$B$13 -> 0 | J86: =J85 -> 0.1 | K86: {=IF( AND(MONTH($B86)=1,SUMPRODUCT(--(MONTH($B$4:B86)=1))=1), K85*(1-22%*J86), IF( AND(MONTH($B86)=1,SUMPRODUCT(--(MONTH($B$4:B86)=1))=2), K85*(1-20%*J86), IF($A86<13,K85*(1-(J86*4%)), IF($A86<25,K85*(1-(J86*5%)),K85*(1-J86/12) ) ) ))} -> 208083.03 | L86: =IF(K86*'Loan Input Parameters'!$B$41<'Loan Input Parameters'!$B$42,'Loan Input Parameters'!$B$42,K86*'Loan Input Parameters'!$B$41) -> 0 | M86: =IFERROR(K86-L86,"") -> 208083.03 | N86: =IFERROR(H86-(K86-L86),"") -> -208083.03 | O86: =IF('Loan Input Parameters'!$B$8*3%<=4000,4000,IF('Loan Input Parameters'!$B$8*3%>=18000,18000,'Loan Input Parameters'!$B$8*3%)) -> 15000 | P86: =IF(N86<0,O86,N86+O86) -> 15000
... A99: =A98+1 -> 96 | B99: =EOMONTH(B98,1) -> 48121 | C99: =IF(ROUND(H98,0)>0,H98,0) -> 0 | D99: =IF(A99<'Loan Input Parameters'!$B$16,'Loan Input Parameters'!$B$24,IF(A99='Loan Input Parameters'!$B$16,'Loan Input Parameters'!$B$24,0)) -> 0 | E99: =IF($A99<'Loan Input Parameters'!$B$16,C99*'Loan Input Parameters'!$B$15/12,"0.00") -> 0.00 | F99: =IF(A99<='Loan Input Parameters'!$B$16,'Loan Input Parameters'!$B$23,0) -> 0 | G99: =IF($A99<'Loan Input Parameters'!$B$16,D99-E99-F99,"0.00") -> 0.00 | H99: =IF($A99<'Loan Input Parameters'!$B$16,C99-G99,"0.00") -> 0.00 | I99: =H99/'Loan Input Parameters'!$B$13 -> 0 | J99: =J98 -> 0.1 | K99: {=IF( AND(MONTH($B99)=1,SUMPRODUCT(--(MONTH($B$4:B99)=1))=1), K98*(1-22%*J99), IF( AND(MONTH($B99)=1,SUMPRODUCT(--(MONTH($B$4:B99)=1))=2), K98*(1-20%*J99), IF($A99<13,K98*(1-(J99*4%)), IF($A99<25,K98*(1-(J99*5%)),K98*(1-J99/12) ) ) ))} -> 186634.09 | L99: =IF(K99*'Loan Input Parameters'!$B$41<'Loan Input Parameters'!$B$42,'Loan Input Parameters'!$B$42,K99*'Loan Input Parameters'!$B$41) -> 0 | M99: =IFERROR(K99-L99,"") -> 186634.09 | N99: =IFERROR(H99-(K99-L99),"") -> -186634.09 | O99: =IF('Loan Input Parameters'!$B$8*3%<=4000,4000,IF('Loan Input Parameters'!$B$8*3%>=18000,18000,'Loan Input Parameters'!$B$8*3%)) -> 15000 | P99: =IF(N99<0,O99,N99+O99) -> 15000

Sheet Shortfall Graph

Sheet Depreciation Parameters
A1: VEHICLE DEPRECIATION PARAMETERS
B2: NEW | C2: DEMO | D2: USED
A3: Vehicle Selling Price | B3: ='Loan Input Parameters'!B8 -> 500000 | C3: ='Loan Input Parameters'!B8 -> 500000 | D3: ='Loan Input Parameters'!B8 -> 500000
A4: Year 1 depreciation % | B4: 0.23 | C4: 0.19 | D4: 0.11
A5: Year 2 depreciation % | B5: 0.15 | C5: 0.15 | D5: 0.11
A6: Year 3 depreciation % | B6: 0.11 | C6: 0.11 | D6: 0.1
A7: Year 4 depreciation % | B7: 0.11 | C7: 0.11 | D7: 0.1
A8: Year 5 depreciation % | B8: 0.11 | C8: 0.1 | D8: 0.1
A9: Year 6 depreciation % | B9: 0.1 | C9: 0.09 | D9: 0.08
A11: All values include VAT where applicable

Sheet template
A1: PRODUCT LIST | B1: FREQUENCY | C1: PRODUCT PLAN | D1: Vlookup Data | E1: Base Premium | F1: % Applied to Purchase Price | K1: CATEGORY | M1: CATEGORY | N1: PRODUCT LIST | O1: FREQUENCY | Q1: TOP UP PRODUCT PLAN | S1: RTI PRODUCT PLAN | U1: DEFERRED RTI PRODUCT PLAN
A2: TRAFICC TOP-UP (G305) | B2: MONTHLY | C2: Top-up | D2: =A2&C2 -> TRAFICC TOP-UP (G305)Top-up | E2: 25 | F2: 0.00057 | G2: Total Premium = Base Premium + (Percentage x Insured Value) | K2: TOP UP | M2: TOP UP | N2: TRAFICC TOP-UP (G305) | O2: MONTHLY | Q2: TOP-UP | S2: RETURN TO INVOICE | U2: DEFERRED RETURN TO INVOICE | W2: New | Y2: Standard | AA2: ='Loan Input Parameters'!A3&": "&'Loan Input Parameters'!B3 -> Client: Sean Van Wyk | AC2: Yes
A3: TRAFICC TOP-UP (G305) | B3: MONTHLY | C3: Top-up With Deposit | D3: =A3&C3 -> TRAFICC TOP-UP (G305)Top-up With Deposit | E3: 25 | F3: 0.0009 | G3: =G2 -> Total Premium = Base Premium + (Percentage x Insured Value) | K3: RETURN TO INVOICE | M3: RETURN TO INVOICE | N3: TRAFICC RETURN TO INVOICE (G305) | O3: MONTHLY | Q3: TOP-UP WITH DEPOSIT | S3: RETURN TO INVOICE WITH EXCESS PROTECTOR | W3: Demo | Y3: Overide | AA3: ='Loan Input Parameters'!A4&": "&'Loan Input Parameters'!B4 -> Transaction number: ZAETC123456789 | AC3: No
A4: TRAFICC TOP-UP (G305) | B4: MONTHLY | C4: Top-up With Excess Protector | D4: =A4&C4 -> TRAFICC TOP-UP (G305)Top-up With Excess Protector | E4: 25 | F4: 0.00093 | G4: =G3 -> Total Premium = Base Premium + (Percentage x Insured Value) | N4: TRAFICC TAXI OWNERS TOP-UP (G305T) | O4: MONTHLY | Q4: TOP-UP WITH EXCESS PROTECTOR | S4: RETURN TO INVOICE WITH EXCESS PROTECTOR AND INSTALMENT PROTECTOR | W4: Used | AA4: ='Loan Input Parameters'!$A$30&": "&"R "&ROUND(VALUE('Loan Input Parameters'!B30),2) -> Monthly Premium: R 310
A5: TRAFICC TOP-UP (G305) | B5: MONTHLY | C5: Top-up With Excess Protector And Instalment Protector | D5: =A5&C5 -> TRAFICC TOP-UP (G305)Top-up With Excess Protector And Instalment Protector | E5: 25 | F5: 0.00111 | G5: =G4 -> Total Premium = Base Premium + (Percentage x Insured Value) | Q5: TOP-UP WITH EXCESS PROTECTOR AND INSTALMENT PROTECTOR | S5: RETURN TO INVOICE WITH INSTALMENT PROTECTOR | AA5: =TODAY() -> 46161
A6: TRAFICC TOP-UP (G305) | B6: MONTHLY | C6: Top-up With Excess And Deposit Protector | D6: =A6&C6 -> TRAFICC TOP-UP (G305)Top-up With Excess And Deposit Protector | E6: 25 | F6: 0.00126 | G6: =G5 -> Total Premium = Base Premium + (Percentage x Insured Value) | Q6: TOP-UP WITH EXCESS AND DEPOSIT PROTECTOR
A7: TRAFICC TOP-UP (G305) | B7: MONTHLY | C7: Top-up With Excess, Instalment Protector And Deposit Protector | D7: =A7&C7 -> TRAFICC TOP-UP (G305)Top-up With Excess, Instalment Protector And Deposit Protector | E7: 25 | F7: 0.00144 | G7: =G6 -> Total Premium = Base Premium + (Percentage x Insured Value) | Q7: TOP-UP WITH EXCESS, INSTALMENT PROTECTOR AND DEPOSIT PROTECTOR
A8: TRAFICC TOP-UP (G305) | B8: MONTHLY | C8: Top-up With Instalment Protector | D8: =A8&C8 -> TRAFICC TOP-UP (G305)Top-up With Instalment Protector | E8: 25 | F8: 0.00075 | G8: =G7 -> Total Premium = Base Premium + (Percentage x Insured Value) | Q8: TOP-UP WITH INSTALMENT PROTECTOR
A9: TRAFICC TOP-UP (G305) | B9: MONTHLY | C9: Top-up With Instalment Protector And Deposit Protector | D9: =A9&C9 -> TRAFICC TOP-UP (G305)Top-up With Instalment Protector And Deposit Protector | E9: 25 | F9: 0.00108 | G9: =G4 -> Total Premium = Base Premium + (Percentage x Insured Value)
A10: TRAFICC RETURN TO INVOICE (G305) | B10: MONTHLY | C10: Return To Invoice | D10: =A10&C10 -> TRAFICC RETURN TO INVOICE (G305)Return To Invoice | E10: 25 | F10: 0.00115 | G10: Total Premium = Base Premium + (Percentage x Insured Value)
A11: TRAFICC RETURN TO INVOICE (G305) | B11: MONTHLY | C11: Return To Invoice with Excess Protector | D11: =A11&C11 -> TRAFICC RETURN TO INVOICE (G305)Return To Invoice with Excess Protector | E11: 25 | F11: 0.00151 | G11: =G10 -> Total Premium = Base Premium + (Percentage x Insured Value)
A12: TRAFICC RETURN TO INVOICE (G305) | B12: MONTHLY | C12: Return To Invoice with Excess Protector And Instalment Protector | D12: =A12&C12 -> TRAFICC RETURN TO INVOICE (G305)Return To Invoice with Excess Protector And Instalment Protector | E12: 25 | F12: 0.00169 | G12: =G11 -> Total Premium = Base Premium + (Percentage x Insured Value)
A13: TRAFICC RETURN TO INVOICE (G305) | B13: MONTHLY | C13: Return To Invoice with Instalment Protector | D13: =A13&C13 -> TRAFICC RETURN TO INVOICE (G305)Return To Invoice with Instalment Protector | E13: 25 | F13: 0.00133 | G13: =G9 -> Total Premium = Base Premium + (Percentage x Insured Value) | Q13: TOP-UP WITH INSTALMENT PROTECTOR AND DEPOSIT PROTECTOR
A14: TRAFICC TAXI OWNERS TOP-UP (G305T) | B14: MONTHLY | C14: Top-up | D14: =A14&C14 -> TRAFICC TAXI OWNERS TOP-UP (G305T)Top-up | E14: 25 | F14: 0.00135 | G14: =G10 -> Total Premium = Base Premium + (Percentage x Insured Value)
A15: TRAFICC TAXI OWNERS TOP-UP (G305T) | B15: MONTHLY | C15: Top-up With Deposit | D15: =A15&C15 -> TRAFICC TAXI OWNERS TOP-UP (G305T)Top-up With Deposit | E15: 25 | F15: 0.00175 | G15: =G11 -> Total Premium = Base Premium + (Percentage x Insured Value)
